Workbook

Sheet Guide
A1: GUIDE | C1: GUIDE — HOW THIS WORKBOOK WORKS | G1: =" as of "&TEXT(TODAY(),"ddd mmm d") -> as of Sun Aug 2
C3: Gallatin Ford · Advanced Deal Log v6 · daily driver
B5: ="PVR month-to-date: "&IF('Aug 31'!$C$62=0,"— (no delivered units yet)",TEXT('Aug 31'!$C$63/'Aug 31'!$C$62,"$#,##0")&" per copy · "&'Aug 31'!$C$62&" units · "&TEXT('Aug 31'!$C$63,"$#,##0")&" total gross") -> PVR month-to-date: — (no delivered units yet)
B7: Daily flow | C7: Open today’s day tab (gold TODAY chip, or click a calendar day on the Dashboard). One deal per row: type, stock, deal#, customer, SP1/SP2, vehicle, gross, lender, ad source, status. Splits: put both reps in SP1 and SP2 — credit auto-splits ½/½. The strip at the top of every day tab shows today at a glance.
B8: Status drives everything | C8: Any deal with a Deal# counts (units, gross, pace, pay) unless its Status is Pending, Unwind or Back Out. That one rule now runs the whole book — Commissions included.
B9: Flags on the day tab | C9: Red Front Gross on a used deal = water (losing money on the front). Amber Lender / Front Gross / Ad Source = a delivered deal missing that field. Red ACV−MMR = we allowed more than the over-allowance limit above MMR (tune limits on Staff & Lists → BENCHMARKS).
B10: Dashboard | C10: Live month roll-up: MTD cards, goal & pace band with projected finish (▲/▼ vs goal), clickable calendar, salesperson leaderboard, channel mix, products, and the USED DESK & F&I INTEL band — used:new ratio, water count, wholesale %, product penetration vs target, PVR, per-F&I-manager split.
B11: Deal Explorer | C11: Every deal in one table. Use the header filter arrows, or set the criteria row (Salesperson matches SP1 or SP2, Type, Status, Certified, Min Gross, Search) and filter the ✓ column.
B12: Commissions | C12: Retro pay: final monthly units set the tier for every deal. Draw is entered by payroll (yellow column); Balance = Earnings − Draw. Six internal audits sit under the table.
B13: Trade Report | C13: Per-day trades, turned-in vs kept, ACV, wholesaled count, ACV−MMR spread and aged-kept flags (⏰ after the turn-in deadline). Recap row grades appraisal capture and immediate-wholesale % against the benchmarks.
B14: Nightly Text | C14: Fill the yellow live inputs, wait for “✅ READY TO COPY”, then copy the box at the bottom into Teams. Day-override cell re-runs a prior day. Pace cells show projected units and gross.
B15: Goals, Benchmarks & Pay Plan | C15: Set monthly goals on Goals (yellow). Tune targets on Staff & Lists → BENCHMARKS (yellow) — every flag and verdict reads them live. Pay Plan (hidden tab) is the single source of truth for commission math.

Sheet Goals
A1: GALLATIN FORD — AUGUST 2026 GOALS
A4: MONTH FACTS
A5: Month | C5: August 2026
A6: Days in Month | C6: 31
A7: Closed (Sundays) | C7: 5
A8: Selling Days | C8: 26
A10: MONTHLY GOALS
B11: Units | C11: Gross
A12: New
A13: Used
A14: Total | B14: =IF(COUNT(B12:B13)=0,"",SUM(B12:B13)) | C14: =IF(COUNT(C12:C13)=0,"",SUM(C12:C13))
A17: PVR GOALS (per copy)
A18: Front PVR
A19: Back PVR
A20: Total PVR | B20: =IF(COUNT(B18:B19)=0,"",SUM(B18:B19))
A23: PER-SELLING-DAY TARGETS
A24: Units / Day | B24: =IF(OR($C$8="",$C$8=0,B14=""),"",ROUND(B14/$C$8,1))
A25: Gross / Day | B25: =IF(OR($C$8="",$C$8=0,C14=""),"",ROUND(C14/$C$8,0))
A28: CONSISTENCY CHECK (±2%)
A29: =IF(OR(B14="",C14="",B18="",B19=""),"-",IF(ABS(B14*(B18+B19)-C14)<=0.02*C14,"✓ CONSISTENT — units × PVR ≈ gross goal","⚠ CHECK — units × PVR ≠ gross goal (±2%)")) -> -

Sheet Scoreboard
A1: SCOREBOARD | C1: SCOREBOARD — AUGUST 2026 | E1: =" as of "&TEXT(TODAY(),"ddd mmm d") -> as of Sun Aug 2
C3: Goal vs month-to-date · blank until goals + deals are entered
A6: UNITS
C7: Goal | D7: MTD | E7: % Goal | F7: To Go
B8: New | C8: =IF(GoalUnitsNew="","-",GoalUnitsNew) -> - | D8: =$B$36 -> 0 | E8: =IF(OR(GoalUnitsNew="",GoalUnitsNew=0),"-",$B$36/GoalUnitsNew) -> - | F8: =IF(GoalUnitsNew="","-",MAX(0,GoalUnitsNew-$B$36)) -> - | G8: =IF(OR($C8="-",N($C8)=0),"",REPT("█",MIN(20,ROUND($D8/$C8*20,0)))&IF($D8>=$C8," ✔",""))
B9: Used | C9: =IF(GoalUnitsUsed="","-",GoalUnitsUsed) -> - | D9: =$B$37 -> 0 | E9: =IF(OR(GoalUnitsUsed="",GoalUnitsUsed=0),"-",$B$37/GoalUnitsUsed) -> - | F9: =IF(GoalUnitsUsed="","-",MAX(0,GoalUnitsUsed-$B$37)) -> - | G9: =IF(OR($C9="-",N($C9)=0),"",REPT("█",MIN(20,ROUND($D9/$C9*20,0)))&IF($D9>=$C9," ✔",""))
B10: Total | C10: =IF(GoalUnitsTotal="","-",GoalUnitsTotal) -> - | D10: ='Aug 31'!$C$62 -> 0 | E10: =IF(OR(GoalUnitsTotal="",GoalUnitsTotal=0),"-",'Aug 31'!$C$62/GoalUnitsTotal) -> - | F10: =IF(GoalUnitsTotal="","-",MAX(0,GoalUnitsTotal-'Aug 31'!$C$62)) -> - | G10: =IF(OR($C10="-",N($C10)=0),"",REPT("█",MIN(20,ROUND($D10/$C10*20,0)))&IF($D10>=$C10," ✔",""))
A12: GROSS
C13: Goal | D13: MTD | E13: % Goal | F13: To Go
B14: New | C14: =IF(GoalGrossNew="","-",GoalGrossNew) -> - | D14: =$B$38 -> 0 | E14: =IF(OR(GoalGrossNew="",GoalGrossNew=0),"-",$B$38/GoalGrossNew) -> - | F14: =IF(GoalGrossNew="","-",MAX(0,GoalGrossNew-$B$38)) -> - | G14: =IF(OR($C14="-",N($C14)=0),"",REPT("█",MIN(20,ROUND($D14/$C14*20,0)))&IF($D14>=$C14," ✔",""))
B15: Used | C15: =IF(GoalGrossUsed="","-",GoalGrossUsed) -> - | D15: =$B$39 -> 0 | E15: =IF(OR(GoalGrossUsed="",GoalGrossUsed=0),"-",$B$39/GoalGrossUsed) -> - | F15: =IF(GoalGrossUsed="","-",MAX(0,GoalGrossUsed-$B$39)) -> - | G15: =IF(OR($C15="-",N($C15)=0),"",REPT("█",MIN(20,ROUND($D15/$C15*20,0)))&IF($D15>=$C15," ✔",""))
B16: Total | C16: =IF(GoalGrossTotal="","-",GoalGrossTotal) -> - | D16: ='Aug 31'!$C$63 -> 0 | E16: =IF(OR(GoalGrossTotal="",GoalGrossTotal=0),"-",'Aug 31'!$C$63/GoalGrossTotal) -> - | F16: =IF(GoalGrossTotal="","-",MAX(0,GoalGrossTotal-'Aug 31'!$C$63)) -> - | G16: =IF(OR($C16="-",N($C16)=0),"",REPT("█",MIN(20,ROUND($D16/$C16*20,0)))&IF($D16>=$C16," ✔",""))
A18: PVR & PACE
B19: PVR (MTD) | C19: goal | D19: =IF('Aug 31'!$C$62=0,"-",'Aug 31'!$C$63/'Aug 31'!$C$62) -> - | E19: =IF(GoalPVRTotal="","-",GoalPVRTotal) -> -
B20: Selling days left | D20: =Dashboard!$BT$5 -> 25
B21: % to unit goal | D21: =IF(OR(GoalUnitsTotal="",GoalUnitsTotal=0),"-",'Aug 31'!$C$62/GoalUnitsTotal) -> -
B22: % to gross goal | D22: =IF(OR(GoalGrossTotal="",GoalGrossTotal=0),"-",'Aug 31'!$C$63/GoalGrossTotal) -> -
B24: PACE — projected finish
B25: Units | C25: =IF(Dashboard!$BT$4=0,"-",ROUND('Aug 31'!$C$62/Dashboard!$BT$4*GoalSellingDays,1)) -> 0 | D25: =IF(OR(GoalUnitsTotal="",C25="-"),"-",IF(C25>=GoalUnitsTotal,"▲ +"&TEXT(C25-GoalUnitsTotal,"0.0"),"▼ "&TEXT(C25-GoalUnitsTotal,"0.0"))) -> -
B26: Gross | C26: =IF(Dashboard!$BT$4=0,"-",ROUND('Aug 31'!$C$63/Dashboard!$BT$4*GoalSellingDays,0)) -> 0 | D26: =IF(OR(GoalGrossTotal="",C26="-"),"-",IF(C26>=GoalGrossTotal,"▲ "&TEXT(C26-GoalGrossTotal,"$#,##0"),"▼ "&TEXT(C26-GoalGrossTotal,"$#,##0"))) -> -
B36: ='Aug 1'!$C$46+'Aug 2'!$C$46+'Aug 3'!$C$46+'Aug 4'!$C$46+'Aug 5'!$C$46+'Aug 6'!$C$46+'Aug 7'!$C$46+'Aug 8'!$C$46+'Aug 9'!$C$46+'Aug 10'!$C$46+'Aug 11'!$C$46+'Aug 12'!$C$46+'Aug 13'!$C$46+'Aug 14'!$C$46+'Aug 15'!$C$46+'Aug 16'!$C$46+'Aug 17'!$C$46+'Aug 18'!$C$46+'Aug 19'!$C$46+'Aug 20'!$C$46+'Aug 21'!$C$46+'Aug 22'!$C$46+'Aug 23'!$C$46+'Aug 24'!$C$46+'Aug 25'!$C$46+'Aug 26'!$C$46+'Aug 27'!$C$46+'Aug 28'!$C$46+'Aug 29'!$C$46+'Aug 30'!$C$46+'Aug 31'!$C$46 -> 0
B37: ='Aug 1'!$E$46+'Aug 2'!$E$46+'Aug 3'!$E$46+'Aug 4'!$E$46+'Aug 5'!$E$46+'Aug 6'!$E$46+'Aug 7'!$E$46+'Aug 8'!$E$46+'Aug 9'!$E$46+'Aug 10'!$E$46+'Aug 11'!$E$46+'Aug 12'!$E$46+'Aug 13'!$E$46+'Aug 14'!$E$46+'Aug 15'!$E$46+'Aug 16'!$E$46+'Aug 17'!$E$46+'Aug 18'!$E$46+'Aug 19'!$E$46+'Aug 20'!$E$46+'Aug 21'!$E$46+'Aug 22'!$E$46+'Aug 23'!$E$46+'Aug 24'!$E$46+'Aug 25'!$E$46+'Aug 26'!$E$46+'Aug 27'!$E$46+'Aug 28'!$E$46+'Aug 29'!$E$46+'Aug 30'!$E$46+'Aug 31'!$E$46 -> 0
B38: ='Aug 1'!$C$49+'Aug 2'!$C$49+'Aug 3'!$C$49+'Aug 4'!$C$49+'Aug 5'!$C$49+'Aug 6'!$C$49+'Aug 7'!$C$49+'Aug 8'!$C$49+'Aug 9'!$C$49+'Aug 10'!$C$49+'Aug 11'!$C$49+'Aug 12'!$C$49+'Aug 13'!$C$49+'Aug 14'!$C$49+'Aug 15'!$C$49+'Aug 16'!$C$49+'Aug 17'!$C$49+'Aug 18'!$C$49+'Aug 19'!$C$49+'Aug 20'!$C$49+'Aug 21'!$C$49+'Aug 22'!$C$49+'Aug 23'!$C$49+'Aug 24'!$C$49+'Aug 25'!$C$49+'Aug 26'!$C$49+'Aug 27'!$C$49+'Aug 28'!$C$49+'Aug 29'!$C$49+'Aug 30'!$C$49+'Aug 31'!$C$49 -> 0
B39: ='Aug 1'!$E$49+'Aug 2'!$E$49+'Aug 3'!$E$49+'Aug 4'!$E$49+'Aug 5'!$E$49+'Aug 6'!$E$49+'Aug 7'!$E$49+'Aug 8'!$E$49+'Aug 9'!$E$49+'Aug 10'!$E$49+'Aug 11'!$E$49+'Aug 12'!$E$49+'Aug 13'!$E$49+'Aug 14'!$E$49+'Aug 15'!$E$49+'Aug 16'!$E$49+'Aug 17'!$E$49+'Aug 18'!$E$49+'Aug 19'!$E$49+'Aug 20'!$E$49+'Aug 21'!$E$49+'Aug 22'!$E$49+'Aug 23'!$E$49+'Aug 24'!$E$49+'Aug 25'!$E$49+'Aug 26'!$E$49+'Aug 27'!$E$49+'Aug 28'!$E$49+'Aug 29'!$E$49+'Aug 30'!$E$49+'Aug 31'!$E$49 -> 0

Sheet Deal Explorer
A1: DEAL EXPLORER | C1: DEAL EXPLORER — AUGUST 2026
C3: Every deal in the month, one filterable ledger · set criteria below, then filter the ✓ column (Data → Reapply)
B4: Salesperson (SP1 or SP2) | D4: Type | E4: Status | G4: Cert? | H4: Min Gross | I4: Search text
B6: ="Showing "&COUNTIF(A8:A1092,"✓")&" of "&SUMPRODUCT(($C$8:$C$1092<>"")*($C$8:$C$1092<>0))&" deals booked this month" -> Showing 0 of 0 deals booked this month
A7: ✓ | B7: Date | C7: Deal# | D7: Stock | E7: Customer | F7: Type | G7: SP1 | H7: SP2 | I7: Vehicle | J7: Gross | K7: Status | L7: Cert
A8: =IF(OR(C8="",C8=0),"",IF(AND(OR($B$5="",G8=$B$5,H8=$B$5),OR($D$5="",F8=$D$5),OR($E$5="",K8=$E$5),OR($G$5="",L8=$G$5),OR($H$5="",N(J8)>=$H$5),OR($I$5="",ISNUMBER(SEARCH($I$5,C8&" "&D8&" "&E8&" "&I8)))),"✓","")) | B8: 46235 | C8: ='Aug 1'!$D$8 -> 0 | D8: ='Aug 1'!$B$8 -> 0 | E8: ='Aug 1'!$E$8 -> 0 | F8: ='Aug 1'!$A$8 -> 0 | G8: ='Aug 1'!$F$8 -> 0 | H8: ='Aug 1'!$G$8 -> 0 | I8: ='Aug 1'!$M$8 | J8: ='Aug 1'!$S$8 | K8: ='Aug 1'!$AG$8 -> 0 | L8: ='Aug 1'!$N$8 -> 0
A9: =IF(OR(C9="",C9=0),"",IF(AND(OR($B$5="",G9=$B$5,H9=$B$5),OR($D$5="",F9=$D$5),OR($E$5="",K9=$E$5),OR($G$5="",L9=$G$5),OR($H$5="",N(J9)>=$H$5),OR($I$5="",ISNUMBER(SEARCH($I$5,C9&" "&D9&" "&E9&" "&I9)))),"✓","")) | B9: 46235 | C9: ='Aug 1'!$D$9 -> 0 | D9: ='Aug 1'!$B$9 -> 0 | E9: ='Aug 1'!$E$9 -> 0 | F9: ='Aug 1'!$A$9 -> 0 | G9: ='Aug 1'!$F$9 -> 0 | H9: ='Aug 1'!$G$9 -> 0 | I9: ='Aug 1'!$M$9 | J9: ='Aug 1'!$S$9 | K9: ='Aug 1'!$AG$9 -> 0 | L9: ='Aug 1'!$N$9 -> 0
A10: =IF(OR(C10="",C10=0),"",IF(AND(OR($B$5="",G10=$B$5,H10=$B$5),OR($D$5="",F10=$D$5),OR($E$5="",K10=$E$5),OR($G$5="",L10=$G$5),OR($H$5="",N(J10)>=$H$5),OR($I$5="",ISNUMBER(SEARCH($I$5,C10&" "&D10&" "&E10&" "&I10)))),"✓","")) | B10: 46235 | C10: ='Aug 1'!$D$10 -> 0 | D10: ='Aug 1'!$B$10 -> 0 | E10: ='Aug 1'!$E$10 -> 0 | F10: ='Aug 1'!$A$10 -> 0 | G10: ='Aug 1'!$F$10 -> 0 | H10: ='Aug 1'!$G$10 -> 0 | I10: ='Aug 1'!$M$10 | J10: ='Aug 1'!$S$10 | K10: ='Aug 1'!$AG$10 -> 0 | L10: ='Aug 1'!$N$10 -> 0
A11: =IF(OR(C11="",C11=0),"",IF(AND(OR($B$5="",G11=$B$5,H11=$B$5),OR($D$5="",F11=$D$5),OR($E$5="",K11=$E$5),OR($G$5="",L11=$G$5),OR($H$5="",N(J11)>=$H$5),OR($I$5="",ISNUMBER(SEARCH($I$5,C11&" "&D11&" "&E11&" "&I11)))),"✓","")) | B11: 46235 | C11: ='Aug 1'!$D$11 -> 0 | D11: ='Aug 1'!$B$11 -> 0 | E11: ='Aug 1'!$E$11 -> 0 | F11: ='Aug 1'!$A$11 -> 0 | G11: ='Aug 1'!$F$11 -> 0 | H11: ='Aug 1'!$G$11 -> 0 | I11: ='Aug 1'!$M$11 | J11: ='Aug 1'!$S$11 | K11: ='Aug 1'!$AG$11 -> 0 | L11: ='Aug 1'!$N$11 -> 0
A12: =IF(OR(C12="",C12=0),"",IF(AND(OR($B$5="",G12=$B$5,H12=$B$5),OR($D$5="",F12=$D$5),OR($E$5="",K12=$E$5),OR($G$5="",L12=$G$5),OR($H$5="",N(J12)>=$H$5),OR($I$5="",ISNUMBER(SEARCH($I$5,C12&" "&D12&" "&E12&" "&I12)))),"✓","")) | B12: 46235 | C12: ='Aug 1'!$D$12 -> 0 | D12: ='Aug 1'!$B$12 -> 0 | E12: ='Aug 1'!$E$12 -> 0 | F12: ='Aug 1'!$A$12 -> 0 | G12: ='Aug 1'!$F$12 -> 0 | H12: ='Aug 1'!$G$12 -> 0 | I12: ='Aug 1'!$M$12 | J12: ='Aug 1'!$S$12 | K12: ='Aug 1'!$AG$12 -> 0 | L12: ='Aug 1'!$N$12 -> 0
A13: =IF(OR(C13="",C13=0),"",IF(AND(OR($B$5="",G13=$B$5,H13=$B$5),OR($D$5="",F13=$D$5),OR($E$5="",K13=$E$5),OR($G$5="",L13=$G$5),OR($H$5="",N(J13)>=$H$5),OR($I$5="",ISNUMBER(SEARCH($I$5,C13&" "&D13&" "&E13&" "&I13)))),"✓","")) | B13: 46235 | C13: ='Aug 1'!$D$13 -> 0 | D13: ='Aug 1'!$B$13 -> 0 | E13: ='Aug 1'!$E$13 -> 0 | F13: ='Aug 1'!$A$13 -> 0 | G13: ='Aug 1'!$F$13 -> 0 | H13: ='Aug 1'!$G$13 -> 0 | I13: ='Aug 1'!$M$13 | J13: ='Aug 1'!$S$13 | K13: ='Aug 1'!$AG$13 -> 0 | L13: ='Aug 1'!$N$13 -> 0
A14: =IF(OR(C14="",C14=0),"",IF(AND(OR($B$5="",G14=$B$5,H14=$B$5),OR($D$5="",F14=$D$5),OR($E$5="",K14=$E$5),OR($G$5="",L14=$G$5),OR($H$5="",N(J14)>=$H$5),OR($I$5="",ISNUMBER(SEARCH($I$5,C14&" "&D14&" "&E14&" "&I14)))),"✓","")) | B14: 46235 | C14: ='Aug 1'!$D$14 -> 0 | D14: ='Aug 1'!$B$14 -> 0 | E14: ='Aug 1'!$E$14 -> 0 | F14: ='Aug 1'!$A$14 -> 0 | G14: ='Aug 1'!$F$14 -> 0 | H14: ='Aug 1'!$G$14 -> 0 | I14: ='Aug 1'!$M$14 | J14: ='Aug 1'!$S$14 | K14: ='Aug 1'!$AG$14 -> 0 | L14: ='Aug 1'!$N$14 -> 0
A15: =IF(OR(C15="",C15=0),"",IF(AND(OR($B$5="",G15=$B$5,H15=$B$5),OR($D$5="",F15=$D$5),OR($E$5="",K15=$E$5),OR($G$5="",L15=$G$5),OR($H$5="",N(J15)>=$H$5),OR($I$5="",ISNUMBER(SEARCH($I$5,C15&" "&D15&" "&E15&" "&I15)))),"✓","")) | B15: 46235 | C15: ='Aug 1'!$D$15 -> 0 | D15: ='Aug 1'!$B$15 -> 0 | E15: ='Aug 1'!$E$15 -> 0 | F15: ='Aug 1'!$A$15 -> 0 | G15: ='Aug 1'!$F$15 -> 0 | H15: ='Aug 1'!$G$15 -> 0 | I15: ='Aug 1'!$M$15 | J15: ='Aug 1'!$S$15 | K15: ='Aug 1'!$AG$15 -> 0 | L15: ='Aug 1'!$N$15 -> 0
A16: =IF(OR(C16="",C16=0),"",IF(AND(OR($B$5="",G16=$B$5,H16=$B$5),OR($D$5="",F16=$D$5),OR($E$5="",K16=$E$5),OR($G$5="",L16=$G$5),OR($H$5="",N(J16)>=$H$5),OR($I$5="",ISNUMBER(SEARCH($I$5,C16&" "&D16&" "&E16&" "&I16)))),"✓","")) | B16: 46235 | C16: ='Aug 1'!$D$16 -> 0 | D16: ='Aug 1'!$B$16 -> 0 | E16: ='Aug 1'!$E$16 -> 0 | F16: ='Aug 1'!$A$16 -> 0 | G16: ='Aug 1'!$F$16 -> 0 | H16: ='Aug 1'!$G$16 -> 0 | I16: ='Aug 1'!$M$16 | J16: ='Aug 1'!$S$16 | K16: ='Aug 1'!$AG$16 -> 0 | L16: ='Aug 1'!$N$16 -> 0
A17: =IF(OR(C17="",C17=0),"",IF(AND(OR($B$5="",G17=$B$5,H17=$B$5),OR($D$5="",F17=$D$5),OR($E$5="",K17=$E$5),OR($G$5="",L17=$G$5),OR($H$5="",N(J17)>=$H$5),OR($I$5="",ISNUMBER(SEARCH($I$5,C17&" "&D17&" "&E17&" "&I17)))),"✓","")) | B17: 46235 | C17: ='Aug 1'!$D$17 -> 0 | D17: ='Aug 1'!$B$17 -> 0 | E17: ='Aug 1'!$E$17 -> 0 | F17: ='Aug 1'!$A$17 -> 0 | G17: ='Aug 1'!$F$17 -> 0 | H17: ='Aug 1'!$G$17 -> 0 | I17: ='Aug 1'!$M$17 | J17: ='Aug 1'!$S$17 | K17: ='Aug 1'!$AG$17 -> 0 | L17: ='Aug 1'!$N$17 -> 0
A18: =IF(OR(C18="",C18=0),"",IF(AND(OR($B$5="",G18=$B$5,H18=$B$5),OR($D$5="",F18=$D$5),OR($E$5="",K18=$E$5),OR($G$5="",L18=$G$5),OR($H$5="",N(J18)>=$H$5),OR($I$5="",ISNUMBER(SEARCH($I$5,C18&" "&D18&" "&E18&" "&I18)))),"✓","")) | B18: 46235 | C18: ='Aug 1'!$D$18 -> 0 | D18: ='Aug 1'!$B$18 -> 0 | E18: ='Aug 1'!$E$18 -> 0 | F18: ='Aug 1'!$A$18 -> 0 | G18: ='Aug 1'!$F$18 -> 0 | H18: ='Aug 1'!$G$18 -> 0 | I18: ='Aug 1'!$M$18 | J18: ='Aug 1'!$S$18 | K18: ='Aug 1'!$AG$18 -> 0 | L18: ='Aug 1'!$N$18 -> 0
A19: =IF(OR(C19="",C19=0),"",IF(AND(OR($B$5="",G19=$B$5,H19=$B$5),OR($D$5="",F19=$D$5),OR($E$5="",K19=$E$5),OR($G$5="",L19=$G$5),OR($H$5="",N(J19)>=$H$5),OR($I$5="",ISNUMBER(SEARCH($I$5,C19&" "&D19&" "&E19&" "&I19)))),"✓","")) | B19: 46235 | C19: ='Aug 1'!$D$19 -> 0 | D19: ='Aug 1'!$B$19 -> 0 | E19: ='Aug 1'!$E$19 -> 0 | F19: ='Aug 1'!$A$19 -> 0 | G19: ='Aug 1'!$F$19 -> 0 | H19: ='Aug 1'!$G$19 -> 0 | I19: ='Aug 1'!$M$19 | J19: ='Aug 1'!$S$19 | K19: ='Aug 1'!$AG$19 -> 0 | L19: ='Aug 1'!$N$19 -> 0
A20: =IF(OR(C20="",C20=0),"",IF(AND(OR($B$5="",G20=$B$5,H20=$B$5),OR($D$5="",F20=$D$5),OR($E$5="",K20=$E$5),OR($G$5="",L20=$G$5),OR($H$5="",N(J20)>=$H$5),OR($I$5="",ISNUMBER(SEARCH($I$5,C20&" "&D20&" "&E20&" "&I20)))),"✓","")) | B20: 46235 | C20: ='Aug 1'!$D$20 -> 0 | D20: ='Aug 1'!$B$20 -> 0 | E20: ='Aug 1'!$E$20 -> 0 | F20: ='Aug 1'!$A$20 -> 0 | G20: ='Aug 1'!$F$20 -> 0 | H20: ='Aug 1'!$G$20 -> 0 | I20: ='Aug 1'!$M$20 | J20: ='Aug 1'!$S$20 | K20: ='Aug 1'!$AG$20 -> 0 | L20: ='Aug 1'!$N$20 -> 0
A21: =IF(OR(C21="",C21=0),"",IF(AND(OR($B$5="",G21=$B$5,H21=$B$5),OR($D$5="",F21=$D$5),OR($E$5="",K21=$E$5),OR($G$5="",L21=$G$5),OR($H$5="",N(J21)>=$H$5),OR($I$5="",ISNUMBER(SEARCH($I$5,C21&" "&D21&" "&E21&" "&I21)))),"✓","")) | B21: 46235 | C21: ='Aug 1'!$D$21 -> 0 | D21: ='Aug 1'!$B$21 -> 0 | E21: ='Aug 1'!$E$21 -> 0 | F21: ='Aug 1'!$A$21 -> 0 | G21: ='Aug 1'!$F$21 -> 0 | H21: ='Aug 1'!$G$21 -> 0 | I21: ='Aug 1'!$M$21 | J21: ='Aug 1'!$S$21 | K21: ='Aug 1'!$AG$21 -> 0 | L21: ='Aug 1'!$N$21 -> 0
A22: =IF(OR(C22="",C22=0),"",IF(AND(OR($B$5="",G22=$B$5,H22=$B$5),OR($D$5="",F22=$D$5),OR($E$5="",K22=$E$5),OR($G$5="",L22=$G$5),OR($H$5="",N(J22)>=$H$5),OR($I$5="",ISNUMBER(SEARCH($I$5,C22&" "&D22&" "&E22&" "&I22)))),"✓","")) | B22: 46235 | C22: ='Aug 1'!$D$22 -> 0 | D22: ='Aug 1'!$B$22 -> 0 | E22: ='Aug 1'!$E$22 -> 0 | F22: ='Aug 1'!$A$22 -> 0 | G22: ='Aug 1'!$F$22 -> 0 | H22: ='Aug 1'!$G$22 -> 0 | I22: ='Aug 1'!$M$22 | J22: ='Aug 1'!$S$22 | K22: ='Aug 1'!$AG$22 -> 0 | L22: ='Aug 1'!$N$22 -> 0
A23: =IF(OR(C23="",C23=0),"",IF(AND(OR($B$5="",G23=$B$5,H23=$B$5),OR($D$5="",F23=$D$5),OR($E$5="",K23=$E$5),OR($G$5="",L23=$G$5),OR($H$5="",N(J23)>=$H$5),OR($I$5="",ISNUMBER(SEARCH($I$5,C23&" "&D23&" "&E23&" "&I23)))),"✓","")) | B23: 46235 | C23: ='Aug 1'!$D$23 -> 0 | D23: ='Aug 1'!$B$23 -> 0 | E23: ='Aug 1'!$E$23 -> 0 | F23: ='Aug 1'!$A$23 -> 0 | G23: ='Aug 1'!$F$23 -> 0 | H23: ='Aug 1'!$G$23 -> 0 | I23: ='Aug 1'!$M$23 | J23: ='Aug 1'!$S$23 | K23: ='Aug 1'!$AG$23 -> 0 | L23: ='Aug 1'!$N$23 -> 0
A24: =IF(OR(C24="",C24=0),"",IF(AND(OR($B$5="",G24=$B$5,H24=$B$5),OR($D$5="",F24=$D$5),OR($E$5="",K24=$E$5),OR($G$5="",L24=$G$5),OR($H$5="",N(J24)>=$H$5),OR($I$5="",ISNUMBER(SEARCH($I$5,C24&" "&D24&" "&E24&" "&I24)))),"✓","")) | B24: 46235 | C24: ='Aug 1'!$D$24 -> 0 | D24: ='Aug 1'!$B$24 -> 0 | E24: ='Aug 1'!$E$24 -> 0 | F24: ='Aug 1'!$A$24 -> 0 | G24: ='Aug 1'!$F$24 -> 0 | H24: ='Aug 1'!$G$24 -> 0 | I24: ='Aug 1'!$M$24 | J24: ='Aug 1'!$S$24 | K24: ='Aug 1'!$AG$24 -> 0 | L24: ='Aug 1'!$N$24 -> 0
A25: =IF(OR(C25="",C25=0),"",IF(AND(OR($B$5="",G25=$B$5,H25=$B$5),OR($D$5="",F25=$D$5),OR($E$5="",K25=$E$5),OR($G$5="",L25=$G$5),OR($H$5="",N(J25)>=$H$5),OR($I$5="",ISNUMBER(SEARCH($I$5,C25&" "&D25&" "&E25&" "&I25)))),"✓","")) | B25: 46235 | C25: ='Aug 1'!$D$25 -> 0 | D25: ='Aug 1'!$B$25 -> 0 | E25: ='Aug 1'!$E$25 -> 0 | F25: ='Aug 1'!$A$25 -> 0 | G25: ='Aug 1'!$F$25 -> 0 | H25: ='Aug 1'!$G$25 -> 0 | I25: ='Aug 1'!$M$25 | J25: ='Aug 1'!$S$25 | K25: ='Aug 1'!$AG$25 -> 0 | L25: ='Aug 1'!$N$25 -> 0
A26: =IF(OR(C26="",C26=0),"",IF(AND(OR($B$5="",G26=$B$5,H26=$B$5),OR($D$5="",F26=$D$5),OR($E$5="",K26=$E$5),OR($G$5="",L26=$G$5),OR($H$5="",N(J26)>=$H$5),OR($I$5="",ISNUMBER(SEARCH($I$5,C26&" "&D26&" "&E26&" "&I26)))),"✓","")) | B26: 46235 | C26: ='Aug 1'!$D$26 -> 0 | D26: ='Aug 1'!$B$26 -> 0 | E26: ='Aug 1'!$E$26 -> 0 | F26: ='Aug 1'!$A$26 -> 0 | G26: ='Aug 1'!$F$26 -> 0 | H26: ='Aug 1'!$G$26 -> 0 | I26: ='Aug 1'!$M$26 | J26: ='Aug 1'!$S$26 | K26: ='Aug 1'!$AG$26 -> 0 | L26: ='Aug 1'!$N$26 -> 0
A27: =IF(OR(C27="",C27=0),"",IF(AND(OR($B$5="",G27=$B$5,H27=$B$5),OR($D$5="",F27=$D$5),OR($E$5="",K27=$E$5),OR($G$5="",L27=$G$5),OR($H$5="",N(J27)>=$H$5),OR($I$5="",ISNUMBER(SEARCH($I$5,C27&" "&D27&" "&E27&" "&I27)))),"✓","")) | B27: 46235 | C27: ='Aug 1'!$D$27 -> 0 | D27: ='Aug 1'!$B$27 -> 0 | E27: ='Aug 1'!$E$27 -> 0 | F27: ='Aug 1'!$A$27 -> 0 | G27: ='Aug 1'!$F$27 -> 0 | H27: ='Aug 1'!$G$27 -> 0 | I27: ='Aug 1'!$M$27 | J27: ='Aug 1'!$S$27 | K27: ='Aug 1'!$AG$27 -> 0 | L27: ='Aug 1'!$N$27 -> 0
A28: =IF(OR(C28="",C28=0),"",IF(AND(OR($B$5="",G28=$B$5,H28=$B$5),OR($D$5="",F28=$D$5),OR($E$5="",K28=$E$5),OR($G$5="",L28=$G$5),OR($H$5="",N(J28)>=$H$5),OR($I$5="",ISNUMBER(SEARCH($I$5,C28&" "&D28&" "&E28&" "&I28)))),"✓","")) | B28: 46235 | C28: ='Aug 1'!$D$28 -> 0 | D28: ='Aug 1'!$B$28 -> 0 | E28: ='Aug 1'!$E$28 -> 0 | F28: ='Aug 1'!$A$28 -> 0 | G28: ='Aug 1'!$F$28 -> 0 | H28: ='Aug 1'!$G$28 -> 0 | I28: ='Aug 1'!$M$28 | J28: ='Aug 1'!$S$28 | K28: ='Aug 1'!$AG$28 -> 0 | L28: ='Aug 1'!$N$28 -> 0
A29: =IF(OR(C29="",C29=0),"",IF(AND(OR($B$5="",G29=$B$5,H29=$B$5),OR($D$5="",F29=$D$5),OR($E$5="",K29=$E$5),OR($G$5="",L29=$G$5),OR($H$5="",N(J29)>=$H$5),OR($I$5="",ISNUMBER(SEARCH($I$5,C29&" "&D29&" "&E29&" "&I29)))),"✓","")) | B29: 46235 | C29: ='Aug 1'!$D$29 -> 0 | D29: ='Aug 1'!$B$29 -> 0 | E29: ='Aug 1'!$E$29 -> 0 | F29: ='Aug 1'!$A$29 -> 0 | G29: ='Aug 1'!$F$29 -> 0 | H29: ='Aug 1'!$G$29 -> 0 | I29: ='Aug 1'!$M$29 | J29: ='Aug 1'!$S$29 | K29: ='Aug 1'!$AG$29 -> 0 | L29: ='Aug 1'!$N$29 -> 0
A30: =IF(OR(C30="",C30=0),"",IF(AND(OR($B$5="",G30=$B$5,H30=$B$5),OR($D$5="",F30=$D$5),OR($E$5="",K30=$E$5),OR($G$5="",L30=$G$5),OR($H$5="",N(J30)>=$H$5),OR($I$5="",ISNUMBER(SEARCH($I$5,C30&" "&D30&" "&E30&" "&I30)))),"✓","")) | B30: 46235 | C30: ='Aug 1'!$D$30 -> 0 | D30: ='Aug 1'!$B$30 -> 0 | E30: ='Aug 1'!$E$30 -> 0 | F30: ='Aug 1'!$A$30 -> 0 | G30: ='Aug 1'!$F$30 -> 0 | H30: ='Aug 1'!$G$30 -> 0 | I30: ='Aug 1'!$M$30 | J30: ='Aug 1'!$S$30 | K30: ='Aug 1'!$AG$30 -> 0 | L30: ='Aug 1'!$N$30 -> 0
A31: =IF(OR(C31="",C31=0),"",IF(AND(OR($B$5="",G31=$B$5,H31=$B$5),OR($D$5="",F31=$D$5),OR($E$5="",K31=$E$5),OR($G$5="",L31=$G$5),OR($H$5="",N(J31)>=$H$5),OR($I$5="",ISNUMBER(SEARCH($I$5,C31&" "&D31&" "&E31&" "&I31)))),"✓","")) | B31: 46235 | C31: ='Aug 1'!$D$31 -> 0 | D31: ='Aug 1'!$B$31 -> 0 | E31: ='Aug 1'!$E$31 -> 0 | F31: ='Aug 1'!$A$31 -> 0 | G31: ='Aug 1'!$F$31 -> 0 | H31: ='Aug 1'!$G$31 -> 0 | I31: ='Aug 1'!$M$31 | J31: ='Aug 1'!$S$31 | K31: ='Aug 1'!$AG$31 -> 0 | L31: ='Aug 1'!$N$31 -> 0
A32: =IF(OR(C32="",C32=0),"",IF(AND(OR($B$5="",G32=$B$5,H32=$B$5),OR($D$5="",F32=$D$5),OR($E$5="",K32=$E$5),OR($G$5="",L32=$G$5),OR($H$5="",N(J32)>=$H$5),OR($I$5="",ISNUMBER(SEARCH($I$5,C32&" "&D32&" "&E32&" "&I32)))),"✓","")) | B32: 46235 | C32: ='Aug 1'!$D$32 -> 0 | D32: ='Aug 1'!$B$32 -> 0 | E32: ='Aug 1'!$E$32 -> 0 | F32: ='Aug 1'!$A$32 -> 0 | G32: ='Aug 1'!$F$32 -> 0 | H32: ='Aug 1'!$G$32 -> 0 | I32: ='Aug 1'!$M$32 | J32: ='Aug 1'!$S$32 | K32: ='Aug 1'!$AG$32 -> 0 | L32: ='Aug 1'!$N$32 -> 0
A33: =IF(OR(C33="",C33=0),"",IF(AND(OR($B$5="",G33=$B$5,H33=$B$5),OR($D$5="",F33=$D$5),OR($E$5="",K33=$E$5),OR($G$5="",L33=$G$5),OR($H$5="",N(J33)>=$H$5),OR($I$5="",ISNUMBER(SEARCH($I$5,C33&" "&D33&" "&E33&" "&I33)))),"✓","")) | B33: 46235 | C33: ='Aug 1'!$D$33 -> 0 | D33: ='Aug 1'!$B$33 -> 0 | E33: ='Aug 1'!$E$33 -> 0 | F33: ='Aug 1'!$A$33 -> 0 | G33: ='Aug 1'!$F$33 -> 0 | H33: ='Aug 1'!$G$33 -> 0 | I33: ='Aug 1'!$M$33 | J33: ='Aug 1'!$S$33 | K33: ='Aug 1'!$AG$33 -> 0 | L33: ='Aug 1'!$N$33 -> 0
A34: =IF(OR(C34="",C34=0),"",IF(AND(OR($B$5="",G34=$B$5,H34=$B$5),OR($D$5="",F34=$D$5),OR($E$5="",K34=$E$5),OR($G$5="",L34=$G$5),OR($H$5="",N(J34)>=$H$5),OR($I$5="",ISNUMBER(SEARCH($I$5,C34&" "&D34&" "&E34&" "&I34)))),"✓","")) | B34: 46235 | C34: ='Aug 1'!$D$34 -> 0 | D34: ='Aug 1'!$B$34 -> 0 | E34: ='Aug 1'!$E$34 -> 0 | F34: ='Aug 1'!$A$34 -> 0 | G34: ='Aug 1'!$F$34 -> 0 | H34: ='Aug 1'!$G$34 -> 0 | I34: ='Aug 1'!$M$34 | J34: ='Aug 1'!$S$34 | K34: ='Aug 1'!$AG$34 -> 0 | L34: ='Aug 1'!$N$34 -> 0
A35: =IF(OR(C35="",C35=0),"",IF(AND(OR($B$5="",G35=$B$5,H35=$B$5),OR($D$5="",F35=$D$5),OR($E$5="",K35=$E$5),OR($G$5="",L35=$G$5),OR($H$5="",N(J35)>=$H$5),OR($I$5="",ISNUMBER(SEARCH($I$5,C35&" "&D35&" "&E35&" "&I35)))),"✓","")) | B35: 46235 | C35: ='Aug 1'!$D$35 -> 0 | D35: ='Aug 1'!$B$35 -> 0 | E35: ='Aug 1'!$E$35 -> 0 | F35: ='Aug 1'!$A$35 -> 0 | G35: ='Aug 1'!$F$35 -> 0 | H35: ='Aug 1'!$G$35 -> 0 | I35: ='Aug 1'!$M$35 | J35: ='Aug 1'!$S$35 | K35: ='Aug 1'!$AG$35 -> 0 | L35: ='Aug 1'!$N$35 -> 0
A36: =IF(OR(C36="",C36=0),"",IF(AND(OR($B$5="",G36=$B$5,H36=$B$5),OR($D$5="",F36=$D$5),OR($E$5="",K36=$E$5),OR($G$5="",L36=$G$5),OR($H$5="",N(J36)>=$H$5),OR($I$5="",ISNUMBER(SEARCH($I$5,C36&" "&D36&" "&E36&" "&I36)))),"✓","")) | B36: 46235 | C36: ='Aug 1'!$D$36 -> 0 | D36: ='Aug 1'!$B$36 -> 0 | E36: ='Aug 1'!$E$36 -> 0 | F36: ='Aug 1'!$A$36 -> 0 | G36: ='Aug 1'!$F$36 -> 0 | H36: ='Aug 1'!$G$36 -> 0 | I36: ='Aug 1'!$M$36 | J36: ='Aug 1'!$S$36 | K36: ='Aug 1'!$AG$36 -> 0 | L36: ='Aug 1'!$N$36 -> 0
A37: =IF(OR(C37="",C37=0),"",IF(AND(OR($B$5="",G37=$B$5,H37=$B$5),OR($D$5="",F37=$D$5),OR($E$5="",K37=$E$5),OR($G$5="",L37=$G$5),OR($H$5="",N(J37)>=$H$5),OR($I$5="",ISNUMBER(SEARCH($I$5,C37&" "&D37&" "&E37&" "&I37)))),"✓","")) | B37: 46235 | C37: ='Aug 1'!$D$37 -> 0 | D37: ='Aug 1'!$B$37 -> 0 | E37: ='Aug 1'!$E$37 -> 0 | F37: ='Aug 1'!$A$37 -> 0 | G37: ='Aug 1'!$F$37 -> 0 | H37: ='Aug 1'!$G$37 -> 0 | I37: ='Aug 1'!$M$37 | J37: ='Aug 1'!$S$37 | K37: ='Aug 1'!$AG$37 -> 0 | L37: ='Aug 1'!$N$37 -> 0
A38: =IF(OR(C38="",C38=0),"",IF(AND(OR($B$5="",G38=$B$5,H38=$B$5),OR($D$5="",F38=$D$5),OR($E$5="",K38=$E$5),OR($G$5="",L38=$G$5),OR($H$5="",N(J38)>=$H$5),OR($I$5="",ISNUMBER(SEARCH($I$5,C38&" "&D38&" "&E38&" "&I38)))),"✓","")) | B38: 46235 | C38: ='Aug 1'!$D$38 -> 0 | D38: ='Aug 1'!$B$38 -> 0 | E38: ='Aug 1'!$E$38 -> 0 | F38: ='Aug 1'!$A$38 -> 0 | G38: ='Aug 1'!$F$38 -> 0 | H38: ='Aug 1'!$G$38 -> 0 | I38: ='Aug 1'!$M$38 | J38: ='Aug 1'!$S$38 | K38: ='Aug 1'!$AG$38 -> 0 | L38: ='Aug 1'!$N$38 -> 0
A39: =IF(OR(C39="",C39=0),"",IF(AND(OR($B$5="",G39=$B$5,H39=$B$5),OR($D$5="",F39=$D$5),OR($E$5="",K39=$E$5),OR($G$5="",L39=$G$5),OR($H$5="",N(J39)>=$H$5),OR($I$5="",ISNUMBER(SEARCH($I$5,C39&" "&D39&" "&E39&" "&I39)))),"✓","")) | B39: 46235 | C39: ='Aug 1'!$D$39 -> 0 | D39: ='Aug 1'!$B$39 -> 0 | E39: ='Aug 1'!$E$39 -> 0 | F39: ='Aug 1'!$A$39 -> 0 | G39: ='Aug 1'!$F$39 -> 0 | H39: ='Aug 1'!$G$39 -> 0 | I39: ='Aug 1'!$M$39 | J39: ='Aug 1'!$S$39 | K39: ='Aug 1'!$AG$39 -> 0 | L39: ='Aug 1'!$N$39 -> 0
A40: =IF(OR(C40="",C40=0),"",IF(AND(OR($B$5="",G40=$B$5,H40=$B$5),OR($D$5="",F40=$D$5),OR($E$5="",K40=$E$5),OR($G$5="",L40=$G$5),OR($H$5="",N(J40)>=$H$5),OR($I$5="",ISNUMBER(SEARCH($I$5,C40&" "&D40&" "&E40&" "&I40)))),"✓","")) | B40: 46235 | C40: ='Aug 1'!$D$40 -> 0 | D40: ='Aug 1'!$B$40 -> 0 | E40: ='Aug 1'!$E$40 -> 0 | F40: ='Aug 1'!$A$40 -> 0 | G40: ='Aug 1'!$F$40 -> 0 | H40: ='Aug 1'!$G$40 -> 0 | I40: ='Aug 1'!$M$40 | J40: ='Aug 1'!$S$40 | K40: ='Aug 1'!$AG$40 -> 0 | L40: ='Aug 1'!$N$40 -> 0
A41: =IF(OR(C41="",C41=0),"",IF(AND(OR($B$5="",G41=$B$5,H41=$B$5),OR($D$5="",F41=$D$5),OR($E$5="",K41=$E$5),OR($G$5="",L41=$G$5),OR($H$5="",N(J41)>=$H$5),OR($I$5="",ISNUMBER(SEARCH($I$5,C41&" "&D41&" "&E41&" "&I41)))),"✓","")) | B41: 46235 | C41: ='Aug 1'!$D$41 -> 0 | D41: ='Aug 1'!$B$41 -> 0 | E41: ='Aug 1'!$E$41 -> 0 | F41: ='Aug 1'!$A$41 -> 0 | G41: ='Aug 1'!$F$41 -> 0 | H41: ='Aug 1'!$G$41 -> 0 | I41: ='Aug 1'!$M$41 | J41: ='Aug 1'!$S$41 | K41: ='Aug 1'!$AG$41 -> 0 | L41: ='Aug 1'!$N$41 -> 0
A42: =IF(OR(C42="",C42=0),"",IF(AND(OR($B$5="",G42=$B$5,H42=$B$5),OR($D$5="",F42=$D$5),OR($E$5="",K42=$E$5),OR($G$5="",L42=$G$5),OR($H$5="",N(J42)>=$H$5),OR($I$5="",ISNUMBER(SEARCH($I$5,C42&" "&D42&" "&E42&" "&I42)))),"✓","")) | B42: 46235 | C42: ='Aug 1'!$D$42 -> 0 | D42: ='Aug 1'!$B$42 -> 0 | E42: ='Aug 1'!$E$42 -> 0 | F42: ='Aug 1'!$A$42 -> 0 | G42: ='Aug 1'!$F$42 -> 0 | H42: ='Aug 1'!$G$42 -> 0 | I42: ='Aug 1'!$M$42 | J42: ='Aug 1'!$S$42 | K42: ='Aug 1'!$AG$42 -> 0 | L42: ='Aug 1'!$N$42 -> 0
A43: =IF(OR(C43="",C43=0),"",IF(AND(OR($B$5="",G43=$B$5,H43=$B$5),OR($D$5="",F43=$D$5),OR($E$5="",K43=$E$5),OR($G$5="",L43=$G$5),OR($H$5="",N(J43)>=$H$5),OR($I$5="",ISNUMBER(SEARCH($I$5,C43&" "&D43&" "&E43&" "&I43)))),"✓","")) | B43: 46236 | C43: ='Aug 2'!$D$8 -> 0 | D43: ='Aug 2'!$B$8 -> 0 | E43: ='Aug 2'!$E$8 -> 0 | F43: ='Aug 2'!$A$8 -> 0 | G43: ='Aug 2'!$F$8 -> 0 | H43: ='Aug 2'!$G$8 -> 0 | I43: ='Aug 2'!$M$8 | J43: ='Aug 2'!$S$8 | K43: ='Aug 2'!$AG$8 -> 0 | L43: ='Aug 2'!$N$8 -> 0
A44: =IF(OR(C44="",C44=0),"",IF(AND(OR($B$5="",G44=$B$5,H44=$B$5),OR($D$5="",F44=$D$5),OR($E$5="",K44=$E$5),OR($G$5="",L44=$G$5),OR($H$5="",N(J44)>=$H$5),OR($I$5="",ISNUMBER(SEARCH($I$5,C44&" "&D44&" "&E44&" "&I44)))),"✓","")) | B44: 46236 | C44: ='Aug 2'!$D$9 -> 0 | D44: ='Aug 2'!$B$9 -> 0 | E44: ='Aug 2'!$E$9 -> 0 | F44: ='Aug 2'!$A$9 -> 0 | G44: ='Aug 2'!$F$9 -> 0 | H44: ='Aug 2'!$G$9 -> 0 | I44: ='Aug 2'!$M$9 | J44: ='Aug 2'!$S$9 | K44: ='Aug 2'!$AG$9 -> 0 | L44: ='Aug 2'!$N$9 -> 0
A45: =IF(OR(C45="",C45=0),"",IF(AND(OR($B$5="",G45=$B$5,H45=$B$5),OR($D$5="",F45=$D$5),OR($E$5="",K45=$E$5),OR($G$5="",L45=$G$5),OR($H$5="",N(J45)>=$H$5),OR($I$5="",ISNUMBER(SEARCH($I$5,C45&" "&D45&" "&E45&" "&I45)))),"✓","")) | B45: 46236 | C45: ='Aug 2'!$D$10 -> 0 | D45: ='Aug 2'!$B$10 -> 0 | E45: ='Aug 2'!$E$10 -> 0 | F45: ='Aug 2'!$A$10 -> 0 | G45: ='Aug 2'!$F$10 -> 0 | H45: ='Aug 2'!$G$10 -> 0 | I45: ='Aug 2'!$M$10 | J45: ='Aug 2'!$S$10 | K45: ='Aug 2'!$AG$10 -> 0 | L45: ='Aug 2'!$N$10 -> 0
A46: =IF(OR(C46="",C46=0),"",IF(AND(OR($B$5="",G46=$B$5,H46=$B$5),OR($D$5="",F46=$D$5),OR($E$5="",K46=$E$5),OR($G$5="",L46=$G$5),OR($H$5="",N(J46)>=$H$5),OR($I$5="",ISNUMBER(SEARCH($I$5,C46&" "&D46&" "&E46&" "&I46)))),"✓","")) | B46: 46236 | C46: ='Aug 2'!$D$11 -> 0 | D46: ='Aug 2'!$B$11 -> 0 | E46: ='Aug 2'!$E$11 -> 0 | F46: ='Aug 2'!$A$11 -> 0 | G46: ='Aug 2'!$F$11 -> 0 | H46: ='Aug 2'!$G$11 -> 0 | I46: ='Aug 2'!$M$11 | J46: ='Aug 2'!$S$11 | K46: ='Aug 2'!$AG$11 -> 0 | L46: ='Aug 2'!$N$11 -> 0
A47: =IF(OR(C47="",C47=0),"",IF(AND(OR($B$5="",G47=$B$5,H47=$B$5),OR($D$5="",F47=$D$5),OR($E$5="",K47=$E$5),OR($G$5="",L47=$G$5),OR($H$5="",N(J47)>=$H$5),OR($I$5="",ISNUMBER(SEARCH($I$5,C47&" "&D47&" "&E47&" "&I47)))),"✓","")) | B47: 46236 | C47: ='Aug 2'!$D$12 -> 0 | D47: ='Aug 2'!$B$12 -> 0 | E47: ='Aug 2'!$E$12 -> 0 | F47: ='Aug 2'!$A$12 -> 0 | G47: ='Aug 2'!$F$12 -> 0 | H47: ='Aug 2'!$G$12 -> 0 | I47: ='Aug 2'!$M$12 | J47: ='Aug 2'!$S$12 | K47: ='Aug 2'!$AG$12 -> 0 | L47: ='Aug 2'!$N$12 -> 0
A48: =IF(OR(C48="",C48=0),"",IF(AND(OR($B$5="",G48=$B$5,H48=$B$5),OR($D$5="",F48=$D$5),OR($E$5="",K48=$E$5),OR($G$5="",L48=$G$5),OR($H$5="",N(J48)>=$H$5),OR($I$5="",ISNUMBER(SEARCH($I$5,C48&" "&D48&" "&E48&" "&I48)))),"✓","")) | B48: 46236 | C48: ='Aug 2'!$D$13 -> 0 | D48: ='Aug 2'!$B$13 -> 0 | E48: ='Aug 2'!$E$13 -> 0 | F48: ='Aug 2'!$A$13 -> 0 | G48: ='Aug 2'!$F$13 -> 0 | H48: ='Aug 2'!$G$13 -> 0 | I48: ='Aug 2'!$M$13 | J48: ='Aug 2'!$S$13 | K48: ='Aug 2'!$AG$13 -> 0 | L48: ='Aug 2'!$N$13 -> 0
A49: =IF(OR(C49="",C49=0),"",IF(AND(OR($B$5="",G49=$B$5,H49=$B$5),OR($D$5="",F49=$D$5),OR($E$5="",K49=$E$5),OR($G$5="",L49=$G$5),OR($H$5="",N(J49)>=$H$5),OR($I$5="",ISNUMBER(SEARCH($I$5,C49&" "&D49&" "&E49&" "&I49)))),"✓","")) | B49: 46236 | C49: ='Aug 2'!$D$14 -> 0 | D49: ='Aug 2'!$B$14 -> 0 | E49: ='Aug 2'!$E$14 -> 0 | F49: ='Aug 2'!$A$14 -> 0 | G49: ='Aug 2'!$F$14 -> 0 | H49: ='Aug 2'!$G$14 -> 0 | I49: ='Aug 2'!$M$14 | J49: ='Aug 2'!$S$14 | K49: ='Aug 2'!$AG$14 -> 0 | L49: ='Aug 2'!$N$14 -> 0
A50: =IF(OR(C50="",C50=0),"",IF(AND(OR($B$5="",G50=$B$5,H50=$B$5),OR($D$5="",F50=$D$5),OR($E$5="",K50=$E$5),OR($G$5="",L50=$G$5),OR($H$5="",N(J50)>=$H$5),OR($I$5="",ISNUMBER(SEARCH($I$5,C50&" "&D50&" "&E50&" "&I50)))),"✓","")) | B50: 46236 | C50: ='Aug 2'!$D$15 -> 0 | D50: ='Aug 2'!$B$15 -> 0 | E50: ='Aug 2'!$E$15 -> 0 | F50: ='Aug 2'!$A$15 -> 0 | G50: ='Aug 2'!$F$15 -> 0 | H50: ='Aug 2'!$G$15 -> 0 | I50: ='Aug 2'!$M$15 | J50: ='Aug 2'!$S$15 | K50: ='Aug 2'!$AG$15 -> 0 | L50: ='Aug 2'!$N$15 -> 0
A51: =IF(OR(C51="",C51=0),"",IF(AND(OR($B$5="",G51=$B$5,H51=$B$5),OR($D$5="",F51=$D$5),OR($E$5="",K51=$E$5),OR($G$5="",L51=$G$5),OR($H$5="",N(J51)>=$H$5),OR($I$5="",ISNUMBER(SEARCH($I$5,C51&" "&D51&" "&E51&" "&I51)))),"✓","")) | B51: 46236 | C51: ='Aug 2'!$D$16 -> 0 | D51: ='Aug 2'!$B$16 -> 0 | E51: ='Aug 2'!$E$16 -> 0 | F51: ='Aug 2'!$A$16 -> 0 | G51: ='Aug 2'!$F$16 -> 0 | H51: ='Aug 2'!$G$16 -> 0 | I51: ='Aug 2'!$M$16 | J51: ='Aug 2'!$S$16 | K51: ='Aug 2'!$AG$16 -> 0 | L51: ='Aug 2'!$N$16 -> 0
A52: =IF(OR(C52="",C52=0),"",IF(AND(OR($B$5="",G52=$B$5,H52=$B$5),OR($D$5="",F52=$D$5),OR($E$5="",K52=$E$5),OR($G$5="",L52=$G$5),OR($H$5="",N(J52)>=$H$5),OR($I$5="",ISNUMBER(SEARCH($I$5,C52&" "&D52&" "&E52&" "&I52)))),"✓","")) | B52: 46236 | C52: ='Aug 2'!$D$17 -> 0 | D52: ='Aug 2'!$B$17 -> 0 | E52: ='Aug 2'!$E$17 -> 0 | F52: ='Aug 2'!$A$17 -> 0 | G52: ='Aug 2'!$F$17 -> 0 | H52: ='Aug 2'!$G$17 -> 0 | I52: ='Aug 2'!$M$17 | J52: ='Aug 2'!$S$17 | K52: ='Aug 2'!$AG$17 -> 0 | L52: ='Aug 2'!$N$17 -> 0
A53: =IF(OR(C53="",C53=0),"",IF(AND(OR($B$5="",G53=$B$5,H53=$B$5),OR($D$5="",F53=$D$5),OR($E$5="",K53=$E$5),OR($G$5="",L53=$G$5),OR($H$5="",N(J53)>=$H$5),OR($I$5="",ISNUMBER(SEARCH($I$5,C53&" "&D53&" "&E53&" "&I53)))),"✓","")) | B53: 46236 | C53: ='Aug 2'!$D$18 -> 0 | D53: ='Aug 2'!$B$18 -> 0 | E53: ='Aug 2'!$E$18 -> 0 | F53: ='Aug 2'!$A$18 -> 0 | G53: ='Aug 2'!$F$18 -> 0 | H53: ='Aug 2'!$G$18 -> 0 | I53: ='Aug 2'!$M$18 | J53: ='Aug 2'!$S$18 | K53: ='Aug 2'!$AG$18 -> 0 | L53: ='Aug 2'!$N$18 -> 0
A54: =IF(OR(C54="",C54=0),"",IF(AND(OR($B$5="",G54=$B$5,H54=$B$5),OR($D$5="",F54=$D$5),OR($E$5="",K54=$E$5),OR($G$5="",L54=$G$5),OR($H$5="",N(J54)>=$H$5),OR($I$5="",ISNUMBER(SEARCH($I$5,C54&" "&D54&" "&E54&" "&I54)))),"✓","")) | B54: 46236 | C54: ='Aug 2'!$D$19 -> 0 | D54: ='Aug 2'!$B$19 -> 0 | E54: ='Aug 2'!$E$19 -> 0 | F54: ='Aug 2'!$A$19 -> 0 | G54: ='Aug 2'!$F$19 -> 0 | H54: ='Aug 2'!$G$19 -> 0 | I54: ='Aug 2'!$M$19 | J54: ='Aug 2'!$S$19 | K54: ='Aug 2'!$AG$19 -> 0 | L54: ='Aug 2'!$N$19 -> 0
A55: =IF(OR(C55="",C55=0),"",IF(AND(OR($B$5="",G55=$B$5,H55=$B$5),OR($D$5="",F55=$D$5),OR($E$5="",K55=$E$5),OR($G$5="",L55=$G$5),OR($H$5="",N(J55)>=$H$5),OR($I$5="",ISNUMBER(SEARCH($I$5,C55&" "&D55&" "&E55&" "&I55)))),"✓","")) | B55: 46236 | C55: ='Aug 2'!$D$20 -> 0 | D55: ='Aug 2'!$B$20 -> 0 | E55: ='Aug 2'!$E$20 -> 0 | F55: ='Aug 2'!$A$20 -> 0 | G55: ='Aug 2'!$F$20 -> 0 | H55: ='Aug 2'!$G$20 -> 0 | I55: ='Aug 2'!$M$20 | J55: ='Aug 2'!$S$20 | K55: ='Aug 2'!$AG$20 -> 0 | L55: ='Aug 2'!$N$20 -> 0
A56: =IF(OR(C56="",C56=0),"",IF(AND(OR($B$5="",G56=$B$5,H56=$B$5),OR($D$5="",F56=$D$5),OR($E$5="",K56=$E$5),OR($G$5="",L56=$G$5),OR($H$5="",N(J56)>=$H$5),OR($I$5="",ISNUMBER(SEARCH($I$5,C56&" "&D56&" "&E56&" "&I56)))),"✓","")) | B56: 46236 | C56: ='Aug 2'!$D$21 -> 0 | D56: ='Aug 2'!$B$21 -> 0 | E56: ='Aug 2'!$E$21 -> 0 | F56: ='Aug 2'!$A$21 -> 0 | G56: ='Aug 2'!$F$21 -> 0 | H56: ='Aug 2'!$G$21 -> 0 | I56: ='Aug 2'!$M$21 | J56: ='Aug 2'!$S$21 | K56: ='Aug 2'!$AG$21 -> 0 | L56: ='Aug 2'!$N$21 -> 0
A57: =IF(OR(C57="",C57=0),"",IF(AND(OR($B$5="",G57=$B$5,H57=$B$5),OR($D$5="",F57=$D$5),OR($E$5="",K57=$E$5),OR($G$5="",L57=$G$5),OR($H$5="",N(J57)>=$H$5),OR($I$5="",ISNUMBER(SEARCH($I$5,C57&" "&D57&" "&E57&" "&I57)))),"✓","")) | B57: 46236 | C57: ='Aug 2'!$D$22 -> 0 | D57: ='Aug 2'!$B$22 -> 0 | E57: ='Aug 2'!$E$22 -> 0 | F57: ='Aug 2'!$A$22 -> 0 | G57: ='Aug 2'!$F$22 -> 0 | H57: ='Aug 2'!$G$22 -> 0 | I57: ='Aug 2'!$M$22 | J57: ='Aug 2'!$S$22 | K57: ='Aug 2'!$AG$22 -> 0 | L57: ='Aug 2'!$N$22 -> 0
A58: =IF(OR(C58="",C58=0),"",IF(AND(OR($B$5="",G58=$B$5,H58=$B$5),OR($D$5="",F58=$D$5),OR($E$5="",K58=$E$5),OR($G$5="",L58=$G$5),OR($H$5="",N(J58)>=$H$5),OR($I$5="",ISNUMBER(SEARCH($I$5,C58&" "&D58&" "&E58&" "&I58)))),"✓","")) | B58: 46236 | C58: ='Aug 2'!$D$23 -> 0 | D58: ='Aug 2'!$B$23 -> 0 | E58: ='Aug 2'!$E$23 -> 0 | F58: ='Aug 2'!$A$23 -> 0 | G58: ='Aug 2'!$F$23 -> 0 | H58: ='Aug 2'!$G$23 -> 0 | I58: ='Aug 2'!$M$23 | J58: ='Aug 2'!$S$23 | K58: ='Aug 2'!$AG$23 -> 0 | L58: ='Aug 2'!$N$23 -> 0
A59: =IF(OR(C59="",C59=0),"",IF(AND(OR($B$5="",G59=$B$5,H59=$B$5),OR($D$5="",F59=$D$5),OR($E$5="",K59=$E$5),OR($G$5="",L59=$G$5),OR($H$5="",N(J59)>=$H$5),OR($I$5="",ISNUMBER(SEARCH($I$5,C59&" "&D59&" "&E59&" "&I59)))),"✓","")) | B59: 46236 | C59: ='Aug 2'!$D$24 -> 0 | D59: ='Aug 2'!$B$24 -> 0 | E59: ='Aug 2'!$E$24 -> 0 | F59: ='Aug 2'!$A$24 -> 0 | G59: ='Aug 2'!$F$24 -> 0 | H59: ='Aug 2'!$G$24 -> 0 | I59: ='Aug 2'!$M$24 | J59: ='Aug 2'!$S$24 | K59: ='Aug 2'!$AG$24 -> 0 | L59: ='Aug 2'!$N$24 -> 0
A60: =IF(OR(C60="",C60=0),"",IF(AND(OR($B$5="",G60=$B$5,H60=$B$5),OR($D$5="",F60=$D$5),OR($E$5="",K60=$E$5),OR($G$5="",L60=$G$5),OR($H$5="",N(J60)>=$H$5),OR($I$5="",ISNUMBER(SEARCH($I$5,C60&" "&D60&" "&E60&" "&I60)))),"✓","")) | B60: 46236 | C60: ='Aug 2'!$D$25 -> 0 | D60: ='Aug 2'!$B$25 -> 0 | E60: ='Aug 2'!$E$25 -> 0 | F60: ='Aug 2'!$A$25 -> 0 | G60: ='Aug 2'!$F$25 -> 0 | H60: ='Aug 2'!$G$25 -> 0 | I60: ='Aug 2'!$M$25 | J60: ='Aug 2'!$S$25 | K60: ='Aug 2'!$AG$25 -> 0 | L60: ='Aug 2'!$N$25 -> 0
A61: =IF(OR(C61="",C61=0),"",IF(AND(OR($B$5="",G61=$B$5,H61=$B$5),OR($D$5="",F61=$D$5),OR($E$5="",K61=$E$5),OR($G$5="",L61=$G$5),OR($H$5="",N(J61)>=$H$5),OR($I$5="",ISNUMBER(SEARCH($I$5,C61&" "&D61&" "&E61&" "&I61)))),"✓","")) | B61: 46236 | C61: ='Aug 2'!$D$26 -> 0 | D61: ='Aug 2'!$B$26 -> 0 | E61: ='Aug 2'!$E$26 -> 0 | F61: ='Aug 2'!$A$26 -> 0 | G61: ='Aug 2'!$F$26 -> 0 | H61: ='Aug 2'!$G$26 -> 0 | I61: ='Aug 2'!$M$26 | J61: ='Aug 2'!$S$26 | K61: ='Aug 2'!$AG$26 -> 0 | L61: ='Aug 2'!$N$26 -> 0
A62: =IF(OR(C62="",C62=0),"",IF(AND(OR($B$5="",G62=$B$5,H62=$B$5),OR($D$5="",F62=$D$5),OR($E$5="",K62=$E$5),OR($G$5="",L62=$G$5),OR($H$5="",N(J62)>=$H$5),OR($I$5="",ISNUMBER(SEARCH($I$5,C62&" "&D62&" "&E62&" "&I62)))),"✓","")) | B62: 46236 | C62: ='Aug 2'!$D$27 -> 0 | D62: ='Aug 2'!$B$27 -> 0 | E62: ='Aug 2'!$E$27 -> 0 | F62: ='Aug 2'!$A$27 -> 0 | G62: ='Aug 2'!$F$27 -> 0 | H62: ='Aug 2'!$G$27 -> 0 | I62: ='Aug 2'!$M$27 | J62: ='Aug 2'!$S$27 | K62: ='Aug 2'!$AG$27 -> 0 | L62: ='Aug 2'!$N$27 -> 0
A63: =IF(OR(C63="",C63=0),"",IF(AND(OR($B$5="",G63=$B$5,H63=$B$5),OR($D$5="",F63=$D$5),OR($E$5="",K63=$E$5),OR($G$5="",L63=$G$5),OR($H$5="",N(J63)>=$H$5),OR($I$5="",ISNUMBER(SEARCH($I$5,C63&" "&D63&" "&E63&" "&I63)))),"✓","")) | B63: 46236 | C63: ='Aug 2'!$D$28 -> 0 | D63: ='Aug 2'!$B$28 -> 0 | E63: ='Aug 2'!$E$28 -> 0 | F63: ='Aug 2'!$A$28 -> 0 | G63: ='Aug 2'!$F$28 -> 0 | H63: ='Aug 2'!$G$28 -> 0 | I63: ='Aug 2'!$M$28 | J63: ='Aug 2'!$S$28 | K63: ='Aug 2'!$AG$28 -> 0 | L63: ='Aug 2'!$N$28 -> 0
A64: =IF(OR(C64="",C64=0),"",IF(AND(OR($B$5="",G64=$B$5,H64=$B$5),OR($D$5="",F64=$D$5),OR($E$5="",K64=$E$5),OR($G$5="",L64=$G$5),OR($H$5="",N(J64)>=$H$5),OR($I$5="",ISNUMBER(SEARCH($I$5,C64&" "&D64&" "&E64&" "&I64)))),"✓","")) | B64: 46236 | C64: ='Aug 2'!$D$29 -> 0 | D64: ='Aug 2'!$B$29 -> 0 | E64: ='Aug 2'!$E$29 -> 0 | F64: ='Aug 2'!$A$29 -> 0 | G64: ='Aug 2'!$F$29 -> 0 | H64: ='Aug 2'!$G$29 -> 0 | I64: ='Aug 2'!$M$29 | J64: ='Aug 2'!$S$29 | K64: ='Aug 2'!$AG$29 -> 0 | L64: ='Aug 2'!$N$29 -> 0
A65: =IF(OR(C65="",C65=0),"",IF(AND(OR($B$5="",G65=$B$5,H65=$B$5),OR($D$5="",F65=$D$5),OR($E$5="",K65=$E$5),OR($G$5="",L65=$G$5),OR($H$5="",N(J65)>=$H$5),OR($I$5="",ISNUMBER(SEARCH($I$5,C65&" "&D65&" "&E65&" "&I65)))),"✓","")) | B65: 46236 | C65: ='Aug 2'!$D$30 -> 0 | D65: ='Aug 2'!$B$30 -> 0 | E65: ='Aug 2'!$E$30 -> 0 | F65: ='Aug 2'!$A$30 -> 0 | G65: ='Aug 2'!$F$30 -> 0 | H65: ='Aug 2'!$G$30 -> 0 | I65: ='Aug 2'!$M$30 | J65: ='Aug 2'!$S$30 | K65: ='Aug 2'!$AG$30 -> 0 | L65: ='Aug 2'!$N$30 -> 0
A66: =IF(OR(C66="",C66=0),"",IF(AND(OR($B$5="",G66=$B$5,H66=$B$5),OR($D$5="",F66=$D$5),OR($E$5="",K66=$E$5),OR($G$5="",L66=$G$5),OR($H$5="",N(J66)>=$H$5),OR($I$5="",ISNUMBER(SEARCH($I$5,C66&" "&D66&" "&E66&" "&I66)))),"✓","")) | B66: 46236 | C66: ='Aug 2'!$D$31 -> 0 | D66: ='Aug 2'!$B$31 -> 0 | E66: ='Aug 2'!$E$31 -> 0 | F66: ='Aug 2'!$A$31 -> 0 | G66: ='Aug 2'!$F$31 -> 0 | H66: ='Aug 2'!$G$31 -> 0 | I66: ='Aug 2'!$M$31 | J66: ='Aug 2'!$S$31 | K66: ='Aug 2'!$AG$31 -> 0 | L66: ='Aug 2'!$N$31 -> 0
A67: =IF(OR(C67="",C67=0),"",IF(AND(OR($B$5="",G67=$B$5,H67=$B$5),OR($D$5="",F67=$D$5),OR($E$5="",K67=$E$5),OR($G$5="",L67=$G$5),OR($H$5="",N(J67)>=$H$5),OR($I$5="",ISNUMBER(SEARCH($I$5,C67&" "&D67&" "&E67&" "&I67)))),"✓","")) | B67: 46236 | C67: ='Aug 2'!$D$32 -> 0 | D67: ='Aug 2'!$B$32 -> 0 | E67: ='Aug 2'!$E$32 -> 0 | F67: ='Aug 2'!$A$32 -> 0 | G67: ='Aug 2'!$F$32 -> 0 | H67: ='Aug 2'!$G$32 -> 0 | I67: ='Aug 2'!$M$32 | J67: ='Aug 2'!$S$32 | K67: ='Aug 2'!$AG$32 -> 0 | L67: ='Aug 2'!$N$32 -> 0
A68: =IF(OR(C68="",C68=0),"",IF(AND(OR($B$5="",G68=$B$5,H68=$B$5),OR($D$5="",F68=$D$5),OR($E$5="",K68=$E$5),OR($G$5="",L68=$G$5),OR($H$5="",N(J68)>=$H$5),OR($I$5="",ISNUMBER(SEARCH($I$5,C68&" "&D68&" "&E68&" "&I68)))),"✓","")) | B68: 46236 | C68: ='Aug 2'!$D$33 -> 0 | D68: ='Aug 2'!$B$33 -> 0 | E68: ='Aug 2'!$E$33 -> 0 | F68: ='Aug 2'!$A$33 -> 0 | G68: ='Aug 2'!$F$33 -> 0 | H68: ='Aug 2'!$G$33 -> 0 | I68: ='Aug 2'!$M$33 | J68: ='Aug 2'!$S$33 | K68: ='Aug 2'!$AG$33 -> 0 | L68: ='Aug 2'!$N$33 -> 0
A69: =IF(OR(C69="",C69=0),"",IF(AND(OR($B$5="",G69=$B$5,H69=$B$5),OR($D$5="",F69=$D$5),OR($E$5="",K69=$E$5),OR($G$5="",L69=$G$5),OR($H$5="",N(J69)>=$H$5),OR($I$5="",ISNUMBER(SEARCH($I$5,C69&" "&D69&" "&E69&" "&I69)))),"✓","")) | B69: 46236 | C69: ='Aug 2'!$D$34 -> 0 | D69: ='Aug 2'!$B$34 -> 0 | E69: ='Aug 2'!$E$34 -> 0 | F69: ='Aug 2'!$A$34 -> 0 | G69: ='Aug 2'!$F$34 -> 0 | H69: ='Aug 2'!$G$34 -> 0 | I69: ='Aug 2'!$M$34 | J69: ='Aug 2'!$S$34 | K69: ='Aug 2'!$AG$34 -> 0 | L69: ='Aug 2'!$N$34 -> 0
A70: =IF(OR(C70="",C70=0),"",IF(AND(OR($B$5="",G70=$B$5,H70=$B$5),OR($D$5="",F70=$D$5),OR($E$5="",K70=$E$5),OR($G$5="",L70=$G$5),OR($H$5="",N(J70)>=$H$5),OR($I$5="",ISNUMBER(SEARCH($I$5,C70&" "&D70&" "&E70&" "&I70)))),"✓","")) | B70: 46236 | C70: ='Aug 2'!$D$35 -> 0 | D70: ='Aug 2'!$B$35 -> 0 | E70: ='Aug 2'!$E$35 -> 0 | F70: ='Aug 2'!$A$35 -> 0 | G70: ='Aug 2'!$F$35 -> 0 | H70: ='Aug 2'!$G$35 -> 0 | I70: ='Aug 2'!$M$35 | J70: ='Aug 2'!$S$35 | K70: ='Aug 2'!$AG$35 -> 0 | L70: ='Aug 2'!$N$35 -> 0
A71: =IF(OR(C71="",C71=0),"",IF(AND(OR($B$5="",G71=$B$5,H71=$B$5),OR($D$5="",F71=$D$5),OR($E$5="",K71=$E$5),OR($G$5="",L71=$G$5),OR($H$5="",N(J71)>=$H$5),OR($I$5="",ISNUMBER(SEARCH($I$5,C71&" "&D71&" "&E71&" "&I71)))),"✓","")) | B71: 46236 | C71: ='Aug 2'!$D$36 -> 0 | D71: ='Aug 2'!$B$36 -> 0 | E71: ='Aug 2'!$E$36 -> 0 | F71: ='Aug 2'!$A$36 -> 0 | G71: ='Aug 2'!$F$36 -> 0 | H71: ='Aug 2'!$G$36 -> 0 | I71: ='Aug 2'!$M$36 | J71: ='Aug 2'!$S$36 | K71: ='Aug 2'!$AG$36 -> 0 | L71: ='Aug 2'!$N$36 -> 0
A72: =IF(OR(C72="",C72=0),"",IF(AND(OR($B$5="",G72=$B$5,H72=$B$5),OR($D$5="",F72=$D$5),OR($E$5="",K72=$E$5),OR($G$5="",L72=$G$5),OR($H$5="",N(J72)>=$H$5),OR($I$5="",ISNUMBER(SEARCH($I$5,C72&" "&D72&" "&E72&" "&I72)))),"✓","")) | B72: 46236 | C72: ='Aug 2'!$D$37 -> 0 | D72: ='Aug 2'!$B$37 -> 0 | E72: ='Aug 2'!$E$37 -> 0 | F72: ='Aug 2'!$A$37 -> 0 | G72: ='Aug 2'!$F$37 -> 0 | H72: ='Aug 2'!$G$37 -> 0 | I72: ='Aug 2'!$M$37 | J72: ='Aug 2'!$S$37 | K72: ='Aug 2'!$AG$37 -> 0 | L72: ='Aug 2'!$N$37 -> 0
A73: =IF(OR(C73="",C73=0),"",IF(AND(OR($B$5="",G73=$B$5,H73=$B$5),OR($D$5="",F73=$D$5),OR($E$5="",K73=$E$5),OR($G$5="",L73=$G$5),OR($H$5="",N(J73)>=$H$5),OR($I$5="",ISNUMBER(SEARCH($I$5,C73&" "&D73&" "&E73&" "&I73)))),"✓","")) | B73: 46236 | C73: ='Aug 2'!$D$38 -> 0 | D73: ='Aug 2'!$B$38 -> 0 | E73: ='Aug 2'!$E$38 -> 0 | F73: ='Aug 2'!$A$38 -> 0 | G73: ='Aug 2'!$F$38 -> 0 | H73: ='Aug 2'!$G$38 -> 0 | I73: ='Aug 2'!$M$38 | J73: ='Aug 2'!$S$38 | K73: ='Aug 2'!$AG$38 -> 0 | L73: ='Aug 2'!$N$38 -> 0
A74: =IF(OR(C74="",C74=0),"",IF(AND(OR($B$5="",G74=$B$5,H74=$B$5),OR($D$5="",F74=$D$5),OR($E$5="",K74=$E$5),OR($G$5="",L74=$G$5),OR($H$5="",N(J74)>=$H$5),OR($I$5="",ISNUMBER(SEARCH($I$5,C74&" "&D74&" "&E74&" "&I74)))),"✓","")) | B74: 46236 | C74: ='Aug 2'!$D$39 -> 0 | D74: ='Aug 2'!$B$39 -> 0 | E74: ='Aug 2'!$E$39 -> 0 | F74: ='Aug 2'!$A$39 -> 0 | G74: ='Aug 2'!$F$39 -> 0 | H74: ='Aug 2'!$G$39 -> 0 | I74: ='Aug 2'!$M$39 | J74: ='Aug 2'!$S$39 | K74: ='Aug 2'!$AG$39 -> 0 | L74: ='Aug 2'!$N$39 -> 0
A75: =IF(OR(C75="",C75=0),"",IF(AND(OR($B$5="",G75=$B$5,H75=$B$5),OR($D$5="",F75=$D$5),OR($E$5="",K75=$E$5),OR($G$5="",L75=$G$5),OR($H$5="",N(J75)>=$H$5),OR($I$5="",ISNUMBER(SEARCH($I$5,C75&" "&D75&" "&E75&" "&I75)))),"✓","")) | B75: 46236 | C75: ='Aug 2'!$D$40 -> 0 | D75: ='Aug 2'!$B$40 -> 0 | E75: ='Aug 2'!$E$40 -> 0 | F75: ='Aug 2'!$A$40 -> 0 | G75: ='Aug 2'!$F$40 -> 0 | H75: ='Aug 2'!$G$40 -> 0 | I75: ='Aug 2'!$M$40 | J75: ='Aug 2'!$S$40 | K75: ='Aug 2'!$AG$40 -> 0 | L75: ='Aug 2'!$N$40 -> 0
A76: =IF(OR(C76="",C76=0),"",IF(AND(OR($B$5="",G76=$B$5,H76=$B$5),OR($D$5="",F76=$D$5),OR($E$5="",K76=$E$5),OR($G$5="",L76=$G$5),OR($H$5="",N(J76)>=$H$5),OR($I$5="",ISNUMBER(SEARCH($I$5,C76&" "&D76&" "&E76&" "&I76)))),"✓","")) | B76: 46236 | C76: ='Aug 2'!$D$41 -> 0 | D76: ='Aug 2'!$B$41 -> 0 | E76: ='Aug 2'!$E$41 -> 0 | F76: ='Aug 2'!$A$41 -> 0 | G76: ='Aug 2'!$F$41 -> 0 | H76: ='Aug 2'!$G$41 -> 0 | I76: ='Aug 2'!$M$41 | J76: ='Aug 2'!$S$41 | K76: ='Aug 2'!$AG$41 -> 0 | L76: ='Aug 2'!$N$41 -> 0
A77: =IF(OR(C77="",C77=0),"",IF(AND(OR($B$5="",G77=$B$5,H77=$B$5),OR($D$5="",F77=$D$5),OR($E$5="",K77=$E$5),OR($G$5="",L77=$G$5),OR($H$5="",N(J77)>=$H$5),OR($I$5="",ISNUMBER(SEARCH($I$5,C77&" "&D77&" "&E77&" "&I77)))),"✓","")) | B77: 46236 | C77: ='Aug 2'!$D$42 -> 0 | D77: ='Aug 2'!$B$42 -> 0 | E77: ='Aug 2'!$E$42 -> 0 | F77: ='Aug 2'!$A$42 -> 0 | G77: ='Aug 2'!$F$42 -> 0 | H77: ='Aug 2'!$G$42 -> 0 | I77: ='Aug 2'!$M$42 | J77: ='Aug 2'!$S$42 | K77: ='Aug 2'!$AG$42 -> 0 | L77: ='Aug 2'!$N$42 -> 0
A78: =IF(OR(C78="",C78=0),"",IF(AND(OR($B$5="",G78=$B$5,H78=$B$5),OR($D$5="",F78=$D$5),OR($E$5="",K78=$E$5),OR($G$5="",L78=$G$5),OR($H$5="",N(J78)>=$H$5),OR($I$5="",ISNUMBER(SEARCH($I$5,C78&" "&D78&" "&E78&" "&I78)))),"✓","")) | B78: 46237 | C78: ='Aug 3'!$D$8 -> 0 | D78: ='Aug 3'!$B$8 -> 0 | E78: ='Aug 3'!$E$8 -> 0 | F78: ='Aug 3'!$A$8 -> 0 | G78: ='Aug 3'!$F$8 -> 0 | H78: ='Aug 3'!$G$8 -> 0 | I78: ='Aug 3'!$M$8 | J78: ='Aug 3'!$S$8 | K78: ='Aug 3'!$AG$8 -> 0 | L78: ='Aug 3'!$N$8 -> 0
A79: =IF(OR(C79="",C79=0),"",IF(AND(OR($B$5="",G79=$B$5,H79=$B$5),OR($D$5="",F79=$D$5),OR($E$5="",K79=$E$5),OR($G$5="",L79=$G$5),OR($H$5="",N(J79)>=$H$5),OR($I$5="",ISNUMBER(SEARCH($I$5,C79&" "&D79&" "&E79&" "&I79)))),"✓","")) | B79: 46237 | C79: ='Aug 3'!$D$9 -> 0 | D79: ='Aug 3'!$B$9 -> 0 | E79: ='Aug 3'!$E$9 -> 0 | F79: ='Aug 3'!$A$9 -> 0 | G79: ='Aug 3'!$F$9 -> 0 | H79: ='Aug 3'!$G$9 -> 0 | I79: ='Aug 3'!$M$9 | J79: ='Aug 3'!$S$9 | K79: ='Aug 3'!$AG$9 -> 0 | L79: ='Aug 3'!$N$9 -> 0
A80: =IF(OR(C80="",C80=0),"",IF(AND(OR($B$5="",G80=$B$5,H80=$B$5),OR($D$5="",F80=$D$5),OR($E$5="",K80=$E$5),OR($G$5="",L80=$G$5),OR($H$5="",N(J80)>=$H$5),OR($I$5="",ISNUMBER(SEARCH($I$5,C80&" "&D80&" "&E80&" "&I80)))),"✓","")) | B80: 46237 | C80: ='Aug 3'!$D$10 -> 0 | D80: ='Aug 3'!$B$10 -> 0 | E80: ='Aug 3'!$E$10 -> 0 | F80: ='Aug 3'!$A$10 -> 0 | G80: ='Aug 3'!$F$10 -> 0 | H80: ='Aug 3'!$G$10 -> 0 | I80: ='Aug 3'!$M$10 | J80: ='Aug 3'!$S$10 | K80: ='Aug 3'!$AG$10 -> 0 | L80: ='Aug 3'!$N$10 -> 0
A81: =IF(OR(C81="",C81=0),"",IF(AND(OR($B$5="",G81=$B$5,H81=$B$5),OR($D$5="",F81=$D$5),OR($E$5="",K81=$E$5),OR($G$5="",L81=$G$5),OR($H$5="",N(J81)>=$H$5),OR($I$5="",ISNUMBER(SEARCH($I$5,C81&" "&D81&" "&E81&" "&I81)))),"✓","")) | B81: 46237 | C81: ='Aug 3'!$D$11 -> 0 | D81: ='Aug 3'!$B$11 -> 0 | E81: ='Aug 3'!$E$11 -> 0 | F81: ='Aug 3'!$A$11 -> 0 | G81: ='Aug 3'!$F$11 -> 0 | H81: ='Aug 3'!$G$11 -> 0 | I81: ='Aug 3'!$M$11 | J81: ='Aug 3'!$S$11 | K81: ='Aug 3'!$AG$11 -> 0 | L81: ='Aug 3'!$N$11 -> 0
A82: =IF(OR(C82="",C82=0),"",IF(AND(OR($B$5="",G82=$B$5,H82=$B$5),OR($D$5="",F82=$D$5),OR($E$5="",K82=$E$5),OR($G$5="",L82=$G$5),OR($H$5="",N(J82)>=$H$5),OR($I$5="",ISNUMBER(SEARCH($I$5,C82&" "&D82&" "&E82&" "&I82)))),"✓","")) | B82: 46237 | C82: ='Aug 3'!$D$12 -> 0 | D82: ='Aug 3'!$B$12 -> 0 | E82: ='Aug 3'!$E$12 -> 0 | F82: ='Aug 3'!$A$12 -> 0 | G82: ='Aug 3'!$F$12 -> 0 | H82: ='Aug 3'!$G$12 -> 0 | I82: ='Aug 3'!$M$12 | J82: ='Aug 3'!$S$12 | K82: ='Aug 3'!$AG$12 -> 0 | L82: ='Aug 3'!$N$12 -> 0
A83: =IF(OR(C83="",C83=0),"",IF(AND(OR($B$5="",G83=$B$5,H83=$B$5),OR($D$5="",F83=$D$5),OR($E$5="",K83=$E$5),OR($G$5="",L83=$G$5),OR($H$5="",N(J83)>=$H$5),OR($I$5="",ISNUMBER(SEARCH($I$5,C83&" "&D83&" "&E83&" "&I83)))),"✓","")) | B83: 46237 | C83: ='Aug 3'!$D$13 -> 0 | D83: ='Aug 3'!$B$13 -> 0 | E83: ='Aug 3'!$E$13 -> 0 | F83: ='Aug 3'!$A$13 -> 0 | G83: ='Aug 3'!$F$13 -> 0 | H83: ='Aug 3'!$G$13 -> 0 | I83: ='Aug 3'!$M$13 | J83: ='Aug 3'!$S$13 | K83: ='Aug 3'!$AG$13 -> 0 | L83: ='Aug 3'!$N$13 -> 0
A84: =IF(OR(C84="",C84=0),"",IF(AND(OR($B$5="",G84=$B$5,H84=$B$5),OR($D$5="",F84=$D$5),OR($E$5="",K84=$E$5),OR($G$5="",L84=$G$5),OR($H$5="",N(J84)>=$H$5),OR($I$5="",ISNUMBER(SEARCH($I$5,C84&" "&D84&" "&E84&" "&I84)))),"✓","")) | B84: 46237 | C84: ='Aug 3'!$D$14 -> 0 | D84: ='Aug 3'!$B$14 -> 0 | E84: ='Aug 3'!$E$14 -> 0 | F84: ='Aug 3'!$A$14 -> 0 | G84: ='Aug 3'!$F$14 -> 0 | H84: ='Aug 3'!$G$14 -> 0 | I84: ='Aug 3'!$M$14 | J84: ='Aug 3'!$S$14 | K84: ='Aug 3'!$AG$14 -> 0 | L84: ='Aug 3'!$N$14 -> 0
A85: =IF(OR(C85="",C85=0),"",IF(AND(OR($B$5="",G85=$B$5,H85=$B$5),OR($D$5="",F85=$D$5),OR($E$5="",K85=$E$5),OR($G$5="",L85=$G$5),OR($H$5="",N(J85)>=$H$5),OR($I$5="",ISNUMBER(SEARCH($I$5,C85&" "&D85&" "&E85&" "&I85)))),"✓","")) | B85: 46237 | C85: ='Aug 3'!$D$15 -> 0 | D85: ='Aug 3'!$B$15 -> 0 | E85: ='Aug 3'!$E$15 -> 0 | F85: ='Aug 3'!$A$15 -> 0 | G85: ='Aug 3'!$F$15 -> 0 | H85: ='Aug 3'!$G$15 -> 0 | I85: ='Aug 3'!$M$15 | J85: ='Aug 3'!$S$15 | K85: ='Aug 3'!$AG$15 -> 0 | L85: ='Aug 3'!$N$15 -> 0
A86: =IF(OR(C86="",C86=0),"",IF(AND(OR($B$5="",G86=$B$5,H86=$B$5),OR($D$5="",F86=$D$5),OR($E$5="",K86=$E$5),OR($G$5="",L86=$G$5),OR($H$5="",N(J86)>=$H$5),OR($I$5="",ISNUMBER(SEARCH($I$5,C86&" "&D86&" "&E86&" "&I86)))),"✓","")) | B86: 46237 | C86: ='Aug 3'!$D$16 -> 0 | D86: ='Aug 3'!$B$16 -> 0 | E86: ='Aug 3'!$E$16 -> 0 | F86: ='Aug 3'!$A$16 -> 0 | G86: ='Aug 3'!$F$16 -> 0 | H86: ='Aug 3'!$G$16 -> 0 | I86: ='Aug 3'!$M$16 | J86: ='Aug 3'!$S$16 | K86: ='Aug 3'!$AG$16 -> 0 | L86: ='Aug 3'!$N$16 -> 0
A87: =IF(OR(C87="",C87=0),"",IF(AND(OR($B$5="",G87=$B$5,H87=$B$5),OR($D$5="",F87=$D$5),OR($E$5="",K87=$E$5),OR($G$5="",L87=$G$5),OR($H$5="",N(J87)>=$H$5),OR($I$5="",ISNUMBER(SEARCH($I$5,C87&" "&D87&" "&E87&" "&I87)))),"✓","")) | B87: 46237 | C87: ='Aug 3'!$D$17 -> 0 | D87: ='Aug 3'!$B$17 -> 0 | E87: ='Aug 3'!$E$17 -> 0 | F87: ='Aug 3'!$A$17 -> 0 | G87: ='Aug 3'!$F$17 -> 0 | H87: ='Aug 3'!$G$17 -> 0 | I87: ='Aug 3'!$M$17 | J87: ='Aug 3'!$S$17 | K87: ='Aug 3'!$AG$17 -> 0 | L87: ='Aug 3'!$N$17 -> 0
A88: =IF(OR(C88="",C88=0),"",IF(AND(OR($B$5="",G88=$B$5,H88=$B$5),OR($D$5="",F88=$D$5),OR($E$5="",K88=$E$5),OR($G$5="",L88=$G$5),OR($H$5="",N(J88)>=$H$5),OR($I$5="",ISNUMBER(SEARCH($I$5,C88&" "&D88&" "&E88&" "&I88)))),"✓","")) | B88: 46237 | C88: ='Aug 3'!$D$18 -> 0 | D88: ='Aug 3'!$B$18 -> 0 | E88: ='Aug 3'!$E$18 -> 0 | F88: ='Aug 3'!$A$18 -> 0 | G88: ='Aug 3'!$F$18 -> 0 | H88: ='Aug 3'!$G$18 -> 0 | I88: ='Aug 3'!$M$18 | J88: ='Aug 3'!$S$18 | K88: ='Aug 3'!$AG$18 -> 0 | L88: ='Aug 3'!$N$18 -> 0
A89: =IF(OR(C89="",C89=0),"",IF(AND(OR($B$5="",G89=$B$5,H89=$B$5),OR($D$5="",F89=$D$5),OR($E$5="",K89=$E$5),OR($G$5="",L89=$G$5),OR($H$5="",N(J89)>=$H$5),OR($I$5="",ISNUMBER(SEARCH($I$5,C89&" "&D89&" "&E89&" "&I89)))),"✓","")) | B89: 46237 | C89: ='Aug 3'!$D$19 -> 0 | D89: ='Aug 3'!$B$19 -> 0 | E89: ='Aug 3'!$E$19 -> 0 | F89: ='Aug 3'!$A$19 -> 0 | G89: ='Aug 3'!$F$19 -> 0 | H89: ='Aug 3'!$G$19 -> 0 | I89: ='Aug 3'!$M$19 | J89: ='Aug 3'!$S$19 | K89: ='Aug 3'!$AG$19 -> 0 | L89: ='Aug 3'!$N$19 -> 0
A90: =IF(OR(C90="",C90=0),"",IF(AND(OR($B$5="",G90=$B$5,H90=$B$5),OR($D$5="",F90=$D$5),OR($E$5="",K90=$E$5),OR($G$5="",L90=$G$5),OR($H$5="",N(J90)>=$H$5),OR($I$5="",ISNUMBER(SEARCH($I$5,C90&" "&D90&" "&E90&" "&I90)))),"✓","")) | B90: 46237 | C90: ='Aug 3'!$D$20 -> 0 | D90: ='Aug 3'!$B$20 -> 0 | E90: ='Aug 3'!$E$20 -> 0 | F90: ='Aug 3'!$A$20 -> 0 | G90: ='Aug 3'!$F$20 -> 0 | H90: ='Aug 3'!$G$20 -> 0 | I90: ='Aug 3'!$M$20 | J90: ='Aug 3'!$S$20 | K90: ='Aug 3'!$AG$20 -> 0 | L90: ='Aug 3'!$N$20 -> 0
A91: =IF(OR(C91="",C91=0),"",IF(AND(OR($B$5="",G91=$B$5,H91=$B$5),OR($D$5="",F91=$D$5),OR($E$5="",K91=$E$5),OR($G$5="",L91=$G$5),OR($H$5="",N(J91)>=$H$5),OR($I$5="",ISNUMBER(SEARCH($I$5,C91&" "&D91&" "&E91&" "&I91)))),"✓","")) | B91: 46237 | C91: ='Aug 3'!$D$21 -> 0 | D91: ='Aug 3'!$B$21 -> 0 | E91: ='Aug 3'!$E$21 -> 0 | F91: ='Aug 3'!$A$21 -> 0 | G91: ='Aug 3'!$F$21 -> 0 | H91: ='Aug 3'!$G$21 -> 0 | I91: ='Aug 3'!$M$21 | J91: ='Aug 3'!$S$21 | K91: ='Aug 3'!$AG$21 -> 0 | L91: ='Aug 3'!$N$21 -> 0
A92: =IF(OR(C92="",C92=0),"",IF(AND(OR($B$5="",G92=$B$5,H92=$B$5),OR($D$5="",F92=$D$5),OR($E$5="",K92=$E$5),OR($G$5="",L92=$G$5),OR($H$5="",N(J92)>=$H$5),OR($I$5="",ISNUMBER(SEARCH($I$5,C92&" "&D92&" "&E92&" "&I92)))),"✓","")) | B92: 46237 | C92: ='Aug 3'!$D$22 -> 0 | D92: ='Aug 3'!$B$22 -> 0 | E92: ='Aug 3'!$E$22 -> 0 | F92: ='Aug 3'!$A$22 -> 0 | G92: ='Aug 3'!$F$22 -> 0 | H92: ='Aug 3'!$G$22 -> 0 | I92: ='Aug 3'!$M$22 | J92: ='Aug 3'!$S$22 | K92: ='Aug 3'!$AG$22 -> 0 | L92: ='Aug 3'!$N$22 -> 0
A93: =IF(OR(C93="",C93=0),"",IF(AND(OR($B$5="",G93=$B$5,H93=$B$5),OR($D$5="",F93=$D$5),OR($E$5="",K93=$E$5),OR($G$5="",L93=$G$5),OR($H$5="",N(J93)>=$H$5),OR($I$5="",ISNUMBER(SEARCH($I$5,C93&" "&D93&" "&E93&" "&I93)))),"✓","")) | B93: 46237 | C93: ='Aug 3'!$D$23 -> 0 | D93: ='Aug 3'!$B$23 -> 0 | E93: ='Aug 3'!$E$23 -> 0 | F93: ='Aug 3'!$A$23 -> 0 | G93: ='Aug 3'!$F$23 -> 0 | H93: ='Aug 3'!$G$23 -> 0 | I93: ='Aug 3'!$M$23 | J93: ='Aug 3'!$S$23 | K93: ='Aug 3'!$AG$23 -> 0 | L93: ='Aug 3'!$N$23 -> 0
A94: =IF(OR(C94="",C94=0),"",IF(AND(OR($B$5="",G94=$B$5,H94=$B$5),OR($D$5="",F94=$D$5),OR($E$5="",K94=$E$5),OR($G$5="",L94=$G$5),OR($H$5="",N(J94)>=$H$5),OR($I$5="",ISNUMBER(SEARCH($I$5,C94&" "&D94&" "&E94&" "&I94)))),"✓","")) | B94: 46237 | C94: ='Aug 3'!$D$24 -> 0 | D94: ='Aug 3'!$B$24 -> 0 | E94: ='Aug 3'!$E$24 -> 0 | F94: ='Aug 3'!$A$24 -> 0 | G94: ='Aug 3'!$F$24 -> 0 | H94: ='Aug 3'!$G$24 -> 0 | I94: ='Aug 3'!$M$24 | J94: ='Aug 3'!$S$24 | K94: ='Aug 3'!$AG$24 -> 0 | L94: ='Aug 3'!$N$24 -> 0
A95: =IF(OR(C95="",C95=0),"",IF(AND(OR($B$5="",G95=$B$5,H95=$B$5),OR($D$5="",F95=$D$5),OR($E$5="",K95=$E$5),OR($G$5="",L95=$G$5),OR($H$5="",N(J95)>=$H$5),OR($I$5="",ISNUMBER(SEARCH($I$5,C95&" "&D95&" "&E95&" "&I95)))),"✓","")) | B95: 46237 | C95: ='Aug 3'!$D$25 -> 0 | D95: ='Aug 3'!$B$25 -> 0 | E95: ='Aug 3'!$E$25 -> 0 | F95: ='Aug 3'!$A$25 -> 0 | G95: ='Aug 3'!$F$25 -> 0 | H95: ='Aug 3'!$G$25 -> 0 | I95: ='Aug 3'!$M$25 | J95: ='Aug 3'!$S$25 | K95: ='Aug 3'!$AG$25 -> 0 | L95: ='Aug 3'!$N$25 -> 0
A96: =IF(OR(C96="",C96=0),"",IF(AND(OR($B$5="",G96=$B$5,H96=$B$5),OR($D$5="",F96=$D$5),OR($E$5="",K96=$E$5),OR($G$5="",L96=$G$5),OR($H$5="",N(J96)>=$H$5),OR($I$5="",ISNUMBER(SEARCH($I$5,C96&" "&D96&" "&E96&" "&I96)))),"✓","")) | B96: 46237 | C96: ='Aug 3'!$D$26 -> 0 | D96: ='Aug 3'!$B$26 -> 0 | E96: ='Aug 3'!$E$26 -> 0 | F96: ='Aug 3'!$A$26 -> 0 | G96: ='Aug 3'!$F$26 -> 0 | H96: ='Aug 3'!$G$26 -> 0 | I96: ='Aug 3'!$M$26 | J96: ='Aug 3'!$S$26 | K96: ='Aug 3'!$AG$26 -> 0 | L96: ='Aug 3'!$N$26 -> 0
A97: =IF(OR(C97="",C97=0),"",IF(AND(OR($B$5="",G97=$B$5,H97=$B$5),OR($D$5="",F97=$D$5),OR($E$5="",K97=$E$5),OR($G$5="",L97=$G$5),OR($H$5="",N(J97)>=$H$5),OR($I$5="",ISNUMBER(SEARCH($I$5,C97&" "&D97&" "&E97&" "&I97)))),"✓","")) | B97: 46237 | C97: ='Aug 3'!$D$27 -> 0 | D97: ='Aug 3'!$B$27 -> 0 | E97: ='Aug 3'!$E$27 -> 0 | F97: ='Aug 3'!$A$27 -> 0 | G97: ='Aug 3'!$F$27 -> 0 | H97: ='Aug 3'!$G$27 -> 0 | I97: ='Aug 3'!$M$27 | J97: ='Aug 3'!$S$27 | K97: ='Aug 3'!$AG$27 -> 0 | L97: ='Aug 3'!$N$27 -> 0
A98: =IF(OR(C98="",C98=0),"",IF(AND(OR($B$5="",G98=$B$5,H98=$B$5),OR($D$5="",F98=$D$5),OR($E$5="",K98=$E$5),OR($G$5="",L98=$G$5),OR($H$5="",N(J98)>=$H$5),OR($I$5="",ISNUMBER(SEARCH($I$5,C98&" "&D98&" "&E98&" "&I98)))),"✓","")) | B98: 46237 | C98: ='Aug 3'!$D$28 -> 0 | D98: ='Aug 3'!$B$28 -> 0 | E98: ='Aug 3'!$E$28 -> 0 | F98: ='Aug 3'!$A$28 -> 0 | G98: ='Aug 3'!$F$28 -> 0 | H98: ='Aug 3'!$G$28 -> 0 | I98: ='Aug 3'!$M$28 | J98: ='Aug 3'!$S$28 | K98: ='Aug 3'!$AG$28 -> 0 | L98: ='Aug 3'!$N$28 -> 0
A99: =IF(OR(C99="",C99=0),"",IF(AND(OR($B$5="",G99=$B$5,H99=$B$5),OR($D$5="",F99=$D$5),OR($E$5="",K99=$E$5),OR($G$5="",L99=$G$5),OR($H$5="",N(J99)>=$H$5),OR($I$5="",ISNUMBER(SEARCH($I$5,C99&" "&D99&" "&E99&" "&I99)))),"✓","")) | B99: 46237 | C99: ='Aug 3'!$D$29 -> 0 | D99: ='Aug 3'!$B$29 -> 0 | E99: ='Aug 3'!$E$29 -> 0 | F99: ='Aug 3'!$A$29 -> 0 | G99: ='Aug 3'!$F$29 -> 0 | H99: ='Aug 3'!$G$29 -> 0 | I99: ='Aug 3'!$M$29 | J99: ='Aug 3'!$S$29 | K99: ='Aug 3'!$AG$29 -> 0 | L99: ='Aug 3'!$N$29 -> 0
A100: =IF(OR(C100="",C100=0),"",IF(AND(OR($B$5="",G100=$B$5,H100=$B$5),OR($D$5="",F100=$D$5),OR($E$5="",K100=$E$5),OR($G$5="",L100=$G$5),OR($H$5="",N(J100)>=$H$5),OR($I$5="",ISNUMBER(SEARCH($I$5,C100&" "&D100&" "&E100&" "&I100)))),"✓","")) | B100: 46237 | C100: ='Aug 3'!$D$30 -> 0 | D100: ='Aug 3'!$B$30 -> 0 | E100: ='Aug 3'!$E$30 -> 0 | F100: ='Aug 3'!$A$30 -> 0 | G100: ='Aug 3'!$F$30 -> 0 | H100: ='Aug 3'!$G$30 -> 0 | I100: ='Aug 3'!$M$30 | J100: ='Aug 3'!$S$30 | K100: ='Aug 3'!$AG$30 -> 0 | L100: ='Aug 3'!$N$30 -> 0
A101: =IF(OR(C101="",C101=0),"",IF(AND(OR($B$5="",G101=$B$5,H101=$B$5),OR($D$5="",F101=$D$5),OR($E$5="",K101=$E$5),OR($G$5="",L101=$G$5),OR($H$5="",N(J101)>=$H$5),OR($I$5="",ISNUMBER(SEARCH($I$5,C101&" "&D101&" "&E101&" "&I101)))),"✓","")) | B101: 46237 | C101: ='Aug 3'!$D$31 -> 0 | D101: ='Aug 3'!$B$31 -> 0 | E101: ='Aug 3'!$E$31 -> 0 | F101: ='Aug 3'!$A$31 -> 0 | G101: ='Aug 3'!$F$31 -> 0 | H101: ='Aug 3'!$G$31 -> 0 | I101: ='Aug 3'!$M$31 | J101: ='Aug 3'!$S$31 | K101: ='Aug 3'!$AG$31 -> 0 | L101: ='Aug 3'!$N$31 -> 0
A102: =IF(OR(C102="",C102=0),"",IF(AND(OR($B$5="",G102=$B$5,H102=$B$5),OR($D$5="",F102=$D$5),OR($E$5="",K102=$E$5),OR($G$5="",L102=$G$5),OR($H$5="",N(J102)>=$H$5),OR($I$5="",ISNUMBER(SEARCH($I$5,C102&" "&D102&" "&E102&" "&I102)))),"✓","")) | B102: 46237 | C102: ='Aug 3'!$D$32 -> 0 | D102: ='Aug 3'!$B$32 -> 0 | E102: ='Aug 3'!$E$32 -> 0 | F102: ='Aug 3'!$A$32 -> 0 | G102: ='Aug 3'!$F$32 -> 0 | H102: ='Aug 3'!$G$32 -> 0 | I102: ='Aug 3'!$M$32 | J102: ='Aug 3'!$S$32 | K102: ='Aug 3'!$AG$32 -> 0 | L102: ='Aug 3'!$N$32 -> 0
...

Sheet Commissions
A1: COMMISSIONS | D1: COMMISSIONS — AUGUST 2026 | N1: =" as of "&TEXT(TODAY(),"ddd mmm d") -> as of Sun Aug 2
D3: Retro pay — final monthly units set the tier for every deal · qualifying = delivered · split = ½ flat · product $ to SP1 · draws entered by payroll | T3: COMMISSIONS AGG
T4: ='Staff & Lists'!A5 -> FEDY ALI | U4: =SUMPRODUCT(('Aug 1'!$F$8:$F$42=$T4)*'Aug 1'!$AJ$8:$AJ$42+('Aug 1'!$G$8:$G$42=$T4)*'Aug 1'!$AK$8:$AK$42) -> 0 | V4: =SUMPRODUCT(('Aug 2'!$F$8:$F$42=$T4)*'Aug 2'!$AJ$8:$AJ$42+('Aug 2'!$G$8:$G$42=$T4)*'Aug 2'!$AK$8:$AK$42) -> 0 | W4: =SUMPRODUCT(('Aug 3'!$F$8:$F$42=$T4)*'Aug 3'!$AJ$8:$AJ$42+('Aug 3'!$G$8:$G$42=$T4)*'Aug 3'!$AK$8:$AK$42) -> 0 | X4: =SUMPRODUCT(('Aug 4'!$F$8:$F$42=$T4)*'Aug 4'!$AJ$8:$AJ$42+('Aug 4'!$G$8:$G$42=$T4)*'Aug 4'!$AK$8:$AK$42) -> 0 | Y4: =SUMPRODUCT(('Aug 5'!$F$8:$F$42=$T4)*'Aug 5'!$AJ$8:$AJ$42+('Aug 5'!$G$8:$G$42=$T4)*'Aug 5'!$AK$8:$AK$42) -> 0 | Z4: =SUMPRODUCT(('Aug 6'!$F$8:$F$42=$T4)*'Aug 6'!$AJ$8:$AJ$42+('Aug 6'!$G$8:$G$42=$T4)*'Aug 6'!$AK$8:$AK$42) -> 0 | AA4: =SUMPRODUCT(('Aug 7'!$F$8:$F$42=$T4)*'Aug 7'!$AJ$8:$AJ$42+('Aug 7'!$G$8:$G$42=$T4)*'Aug 7'!$AK$8:$AK$42) -> 0 | AB4: =SUMPRODUCT(('Aug 8'!$F$8:$F$42=$T4)*'Aug 8'!$AJ$8:$AJ$42+('Aug 8'!$G$8:$G$42=$T4)*'Aug 8'!$AK$8:$AK$42) -> 0 | AC4: =SUMPRODUCT(('Aug 9'!$F$8:$F$42=$T4)*'Aug 9'!$AJ$8:$AJ$42+('Aug 9'!$G$8:$G$42=$T4)*'Aug 9'!$AK$8:$AK$42) -> 0 | AD4: =SUMPRODUCT(('Aug 10'!$F$8:$F$42=$T4)*'Aug 10'!$AJ$8:$AJ$42+('Aug 10'!$G$8:$G$42=$T4)*'Aug 10'!$AK$8:$AK$42) -> 0 | AE4: =SUMPRODUCT(('Aug 11'!$F$8:$F$42=$T4)*'Aug 11'!$AJ$8:$AJ$42+('Aug 11'!$G$8:$G$42=$T4)*'Aug 11'!$AK$8:$AK$42) -> 0 | AF4: =SUMPRODUCT(('Aug 12'!$F$8:$F$42=$T4)*'Aug 12'!$AJ$8:$AJ$42+('Aug 12'!$G$8:$G$42=$T4)*'Aug 12'!$AK$8:$AK$42) -> 0 | AG4: =SUMPRODUCT(('Aug 13'!$F$8:$F$42=$T4)*'Aug 13'!$AJ$8:$AJ$42+('Aug 13'!$G$8:$G$42=$T4)*'Aug 13'!$AK$8:$AK$42) -> 0 | AH4: =SUMPRODUCT(('Aug 14'!$F$8:$F$42=$T4)*'Aug 14'!$AJ$8:$AJ$42+('Aug 14'!$G$8:$G$42=$T4)*'Aug 14'!$AK$8:$AK$42) -> 0 | AI4: =SUMPRODUCT(('Aug 15'!$F$8:$F$42=$T4)*'Aug 15'!$AJ$8:$AJ$42+('Aug 15'!$G$8:$G$42=$T4)*'Aug 15'!$AK$8:$AK$42) -> 0 | AJ4: =SUMPRODUCT(('Aug 16'!$F$8:$F$42=$T4)*'Aug 16'!$AJ$8:$AJ$42+('Aug 16'!$G$8:$G$42=$T4)*'Aug 16'!$AK$8:$AK$42) -> 0 | AK4: =SUMPRODUCT(('Aug 17'!$F$8:$F$42=$T4)*'Aug 17'!$AJ$8:$AJ$42+('Aug 17'!$G$8:$G$42=$T4)*'Aug 17'!$AK$8:$AK$42) -> 0 | AL4: =SUMPRODUCT(('Aug 18'!$F$8:$F$42=$T4)*'Aug 18'!$AJ$8:$AJ$42+('Aug 18'!$G$8:$G$42=$T4)*'Aug 18'!$AK$8:$AK$42) -> 0 | AM4: =SUMPRODUCT(('Aug 19'!$F$8:$F$42=$T4)*'Aug 19'!$AJ$8:$AJ$42+('Aug 19'!$G$8:$G$42=$T4)*'Aug 19'!$AK$8:$AK$42) -> 0 | AN4: =SUMPRODUCT(('Aug 20'!$F$8:$F$42=$T4)*'Aug 20'!$AJ$8:$AJ$42+('Aug 20'!$G$8:$G$42=$T4)*'Aug 20'!$AK$8:$AK$42) -> 0 | AO4: =SUMPRODUCT(('Aug 21'!$F$8:$F$42=$T4)*'Aug 21'!$AJ$8:$AJ$42+('Aug 21'!$G$8:$G$42=$T4)*'Aug 21'!$AK$8:$AK$42) -> 0 | AP4: =SUMPRODUCT(('Aug 22'!$F$8:$F$42=$T4)*'Aug 22'!$AJ$8:$AJ$42+('Aug 22'!$G$8:$G$42=$T4)*'Aug 22'!$AK$8:$AK$42) -> 0 | AQ4: =SUMPRODUCT(('Aug 23'!$F$8:$F$42=$T4)*'Aug 23'!$AJ$8:$AJ$42+('Aug 23'!$G$8:$G$42=$T4)*'Aug 23'!$AK$8:$AK$42) -> 0 | AR4: =SUMPRODUCT(('Aug 24'!$F$8:$F$42=$T4)*'Aug 24'!$AJ$8:$AJ$42+('Aug 24'!$G$8:$G$42=$T4)*'Aug 24'!$AK$8:$AK$42) -> 0 | AS4: =SUMPRODUCT(('Aug 25'!$F$8:$F$42=$T4)*'Aug 25'!$AJ$8:$AJ$42+('Aug 25'!$G$8:$G$42=$T4)*'Aug 25'!$AK$8:$AK$42) -> 0 | AT4: =SUMPRODUCT(('Aug 26'!$F$8:$F$42=$T4)*'Aug 26'!$AJ$8:$AJ$42+('Aug 26'!$G$8:$G$42=$T4)*'Aug 26'!$AK$8:$AK$42) -> 0 | AU4: =SUMPRODUCT(('Aug 27'!$F$8:$F$42=$T4)*'Aug 27'!$AJ$8:$AJ$42+('Aug 27'!$G$8:$G$42=$T4)*'Aug 27'!$AK$8:$AK$42) -> 0 | AV4: =SUMPRODUCT(('Aug 28'!$F$8:$F$42=$T4)*'Aug 28'!$AJ$8:$AJ$42+('Aug 28'!$G$8:$G$42=$T4)*'Aug 28'!$AK$8:$AK$42) -> 0 | AW4: =SUMPRODUCT(('Aug 29'!$F$8:$F$42=$T4)*'Aug 29'!$AJ$8:$AJ$42+('Aug 29'!$G$8:$G$42=$T4)*'Aug 29'!$AK$8:$AK$42) -> 0 | AX4: =SUMPRODUCT(('Aug 30'!$F$8:$F$42=$T4)*'Aug 30'!$AJ$8:$AJ$42+('Aug 30'!$G$8:$G$42=$T4)*'Aug 30'!$AK$8:$AK$42) -> 0 | AY4: =SUMPRODUCT(('Aug 31'!$F$8:$F$42=$T4)*'Aug 31'!$AJ$8:$AJ$42+('Aug 31'!$G$8:$G$42=$T4)*'Aug 31'!$AK$8:$AK$42) -> 0 | BA4: =SUM(U4:AD4) -> 0 | BB4: =MATCH(BD4,'Pay Plan'!$C$6:$C$12,1) -> 1 | BC4: =SUMPRODUCT(('Aug 1'!$F$8:$F$42=$T4)*'Aug 1'!$AI$8:$AI$42*(('Aug 1'!$AM$8:$AM$42="Y")+('Aug 1'!$AN$8:$AN$42="Y")+('Aug 1'!$AO$8:$AO$42="Y")))+SUMPRODUCT(('Aug 2'!$F$8:$F$42=$T4)*'Aug 2'!$AI$8:$AI$42*(('Aug 2'!$AM$8:$AM$42="Y")+('Aug 2'!$AN$8:$AN$42="Y")+('Aug 2'!$AO$8:$AO$42="Y")))+SUMPRODUCT(('Aug 3'!$F$8:$F$42=$T4)*'Aug 3'!$AI$8:$AI$42*(('Aug 3'!$AM$8:$AM$42="Y")+('Aug 3'!$AN$8:$AN$42="Y")+('Aug 3'!$AO$8:$AO$42="Y")))+SUMPRODUCT(('Aug 4'!$F$8:$F$42=$T4)*'Aug 4'!$AI$8:$AI$42*(('Aug 4'!$AM$8:$AM$42="Y")+('Aug 4'!$AN$8:$AN$42="Y")+('Aug 4'!$AO$8:$AO$42="Y")))+SUMPRODUCT(('Aug 5'!$F$8:$F$42=$T4)*'Aug 5'!$AI$8:$AI$42*(('Aug 5'!$AM$8:$AM$42="Y")+('Aug 5'!$AN$8:$AN$42="Y")+('Aug 5'!$AO$8:$AO$42="Y")))+SUMPRODUCT(('Aug 6'!$F$8:$F$42=$T4)*'Aug 6'!$AI$8:$AI$42*(('Aug 6'!$AM$8:$AM$42="Y")+('Aug 6'!$AN$8:$AN$42="Y")+('Aug 6'!$AO$8:$AO$42="Y")))+SUMPRODUCT(('Aug 7'!$F$8:$F$42=$T4)*'Aug 7'!$AI$8:$AI$42*(('Aug 7'!$AM$8:$AM$42="Y")+('Aug 7'!$AN$8:$AN$42="Y")+('Aug 7'!$AO$8:$AO$42="Y")))+SUMPRODUCT(('Aug 8'!$F$8:$F$42=$T4)*'Aug 8'!$AI$8:$AI$42*(('Aug 8'!$AM$8:$AM$42="Y")+('Aug 8'!$AN$8:$AN$42="Y")+('Aug 8'!$AO$8:$AO$42="Y")))+SUMPRODUCT(('Aug 9'!$F$8:$F$42=$T4)*'Aug 9'!$AI$8:$AI$42*(('Aug 9'!$AM$8:$AM$42="Y")+('Aug 9'!$AN$8:$AN$42="Y")+('Aug 9'!$AO$8:$AO$42="Y")))+SUMPRODUCT(('Aug 10'!$F$8:$F$42=$T4)*'Aug 10'!$AI$8:$AI$42*(('Aug 10'!$AM$8:$AM$42="Y")+('Aug 10'!$AN$8:$AN$42="Y")+('Aug 10'!$AO$8:$AO$42="Y")))+SUMPRODUCT(('Aug 11'!$F$8:$F$42=$T4)*'Aug 11'!$AI$8:$AI$42*(('Aug 11'!$AM$8:$AM$42="Y")+('Aug 11'!$AN$8:$AN$42="Y")+('Aug 11'!$AO$8:$AO$42="Y")))+SUMPRODUCT(('Aug 12'!$F$8:$F$42=$T4)*'Aug 12'!$AI$8:$AI$42*(('Aug 12'!$AM$8:$AM$42="Y")+('Aug 12'!$AN$8:$AN$42="Y")+('Aug 12'!$AO$8:$AO$42="Y")))+SUMPRODUCT(('Aug 13'!$F$8:$F$42=$T4)*'Aug 13'!$AI$8:$AI$42*(('Aug 13'!$AM$8:$AM$42="Y")+('Aug 13'!$AN$8:$AN$42="Y")+('Aug 13'!$AO$8:$AO$42="Y")))+SUMPRODUCT(('Aug 14'!$F$8:$F$42=$T4)*'Aug 14'!$AI$8:$AI$42*(('Aug 14'!$AM$8:$AM$42="Y")+('Aug 14'!$AN$8:$AN$42="Y")+('Aug 14'!$AO$8:$AO$42="Y")))+SUMPRODUCT(('Aug 15'!$F$8:$F$42=$T4)*'Aug 15'!$AI$8:$AI$42*(('Aug 15'!$AM$8:$AM$42="Y")+('Aug 15'!$AN$8:$AN$42="Y")+('Aug 15'!$AO$8:$AO$42="Y")))+SUMPRODUCT(('Aug 16'!$F$8:$F$42=$T4)*'Aug 16'!$AI$8:$AI$42*(('Aug 16'!$AM$8:$AM$42="Y")+('Aug 16'!$AN$8:$AN$42="Y")+('Aug 16'!$AO$8:$AO$42="Y")))+SUMPRODUCT(('Aug 17'!$F$8:$F$42=$T4)*'Aug 17'!$AI$8:$AI$42*(('Aug 17'!$AM$8:$AM$42="Y")+('Aug 17'!$AN$8:$AN$42="Y")+('Aug 17'!$AO$8:$AO$42="Y")))+SUMPRODUCT(('Aug 18'!$F$8:$F$42=$T4)*'Aug 18'!$AI$8:$AI$42*(('Aug 18'!$AM$8:$AM$42="Y")+('Aug 18'!$AN$8:$AN$42="Y")+('Aug 18'!$AO$8:$AO$42="Y")))+SUMPRODUCT(('Aug 19'!$F$8:$F$42=$T4)*'Aug 19'!$AI$8:$AI$42*(('Aug 19'!$AM$8:$AM$42="Y")+('Aug 19'!$AN$8:$AN$42="Y")+('Aug 19'!$AO$8:$AO$42="Y")))+SUMPRODUCT(('Aug 20'!$F$8:$F$42=$T4)*'Aug 20'!$AI$8:$AI$42*(('Aug 20'!$AM$8:$AM$42="Y")+('Aug 20'!$AN$8:$AN$42="Y")+('Aug 20'!$AO$8:$AO$42="Y")))+SUMPRODUCT(('Aug 21'!$F$8:$F$42=$T4)*'Aug 21'!$AI$8:$AI$42*(('Aug 21'!$AM$8:$AM$42="Y")+('Aug 21'!$AN$8:$AN$42="Y")+('Aug 21'!$AO$8:$AO$42="Y")))+SUMPRODUCT(('Aug 22'!$F$8:$F$42=$T4)*'Aug 22'!$AI$8:$AI$42*(('Aug 22'!$AM$8:$AM$42="Y")+('Aug 22'!$AN$8:$AN$42="Y")+('Aug 22'!$AO$8:$AO$42="Y")))+SUMPRODUCT(('Aug 23'!$F$8:$F$42=$T4)*'Aug 23'!$AI$8:$AI$42*(('Aug 23'!$AM$8:$AM$42="Y")+('Aug 23'!$AN$8:$AN$42="Y")+('Aug 23'!$AO$8:$AO$42="Y")))+SUMPRODUCT(('Aug 24'!$F$8:$F$42=$T4)*'Aug 24'!$AI$8:$AI$42*(('Aug 24'!$AM$8:$AM$42="Y")+('Aug 24'!$AN$8:$AN$42="Y")+('Aug 24'!$AO$8:$AO$42="Y")))+SUMPRODUCT(('Aug 25'!$F$8:$F$42=$T4)*'Aug 25'!$AI$8:$AI$42*(('Aug 25'!$AM$8:$AM$42="Y")+('Aug 25'!$AN$8:$AN$42="Y")+('Aug 25'!$AO$8:$AO$42="Y")))+SUMPRODUCT(('Aug 26'!$F$8:$F$42=$T4)*'Aug 26'!$AI$8:$AI$42*(('Aug 26'!$AM$8:$AM$42="Y")+('Aug 26'!$AN$8:$AN$42="Y")+('Aug 26'!$AO$8:$AO$42="Y")))+SUMPRODUCT(('Aug 27'!$F$8:$F$42=$T4)*'Aug 27'!$AI$8:$AI$42*(('Aug 27'!$AM$8:$AM$42="Y")+('Aug 27'!$AN$8:$AN$42="Y")+('Aug 27'!$AO$8:$AO$42="Y")))+SUMPRODUCT(('Aug 28'!$F$8:$F$42=$T4)*'Aug 28'!$AI$8:$AI$42*(('Aug 28'!$AM$8:$AM$42="Y")+('Aug 28'!$AN$8:$AN$42="Y")+('Aug 28'!$AO$8:$AO$42="Y")))+SUMPRODUCT(('Aug 29'!$F$8:$F$42=$T4)*'Aug 29'!$AI$8:$AI$42*(('Aug 29'!$AM$8:$AM$42="Y")+('Aug 29'!$AN$8:$AN$42="Y")+('Aug 29'!$AO$8:$AO$42="Y")))+SUMPRODUCT(('Aug 30'!$F$8:$F$42=$T4)*'Aug 30'!$AI$8:$AI$42*(('Aug 30'!$AM$8:$AM$42="Y")+('Aug 30'!$AN$8:$AN$42="Y")+('Aug 30'!$AO$8:$AO$42="Y")))+SUMPRODUCT(('Aug 31'!$F$8:$F$42=$T4)*'Aug 31'!$AI$8:$AI$42*(('Aug 31'!$AM$8:$AM$42="Y")+('Aug 31'!$AN$8:$AN$42="Y")+('Aug 31'!$AO$8:$AO$42="Y"))) -> 0 | BD4: =SUM(U4:AY4) -> 0 | BE4: =SUM(U23:AY23) -> 0 | BF4: =SUM(U42:AY42) -> 0 | BH4: ='Aug 1'!$G$46+'Aug 2'!$G$46+'Aug 3'!$G$46+'Aug 4'!$G$46+'Aug 5'!$G$46+'Aug 6'!$G$46+'Aug 7'!$G$46+'Aug 8'!$G$46+'Aug 9'!$G$46+'Aug 10'!$G$46+'Aug 11'!$G$46+'Aug 12'!$G$46+'Aug 13'!$G$46+'Aug 14'!$G$46+'Aug 15'!$G$46+'Aug 16'!$G$46+'Aug 17'!$G$46+'Aug 18'!$G$46+'Aug 19'!$G$46+'Aug 20'!$G$46+'Aug 21'!$G$46+'Aug 22'!$G$46+'Aug 23'!$G$46+'Aug 24'!$G$46+'Aug 25'!$G$46+'Aug 26'!$G$46+'Aug 27'!$G$46+'Aug 28'!$G$46+'Aug 29'!$G$46+'Aug 30'!$G$46+'Aug 31'!$G$46 -> 0
T5: ='Staff & Lists'!A6 -> CHAD EMBRY | U5: =SUMPRODUCT(('Aug 1'!$F$8:$F$42=$T5)*'Aug 1'!$AJ$8:$AJ$42+('Aug 1'!$G$8:$G$42=$T5)*'Aug 1'!$AK$8:$AK$42) -> 0 | V5: =SUMPRODUCT(('Aug 2'!$F$8:$F$42=$T5)*'Aug 2'!$AJ$8:$AJ$42+('Aug 2'!$G$8:$G$42=$T5)*'Aug 2'!$AK$8:$AK$42) -> 0 | W5: =SUMPRODUCT(('Aug 3'!$F$8:$F$42=$T5)*'Aug 3'!$AJ$8:$AJ$42+('Aug 3'!$G$8:$G$42=$T5)*'Aug 3'!$AK$8:$AK$42) -> 0 | X5: =SUMPRODUCT(('Aug 4'!$F$8:$F$42=$T5)*'Aug 4'!$AJ$8:$AJ$42+('Aug 4'!$G$8:$G$42=$T5)*'Aug 4'!$AK$8:$AK$42) -> 0 | Y5: =SUMPRODUCT(('Aug 5'!$F$8:$F$42=$T5)*'Aug 5'!$AJ$8:$AJ$42+('Aug 5'!$G$8:$G$42=$T5)*'Aug 5'!$AK$8:$AK$42) -> 0 | Z5: =SUMPRODUCT(('Aug 6'!$F$8:$F$42=$T5)*'Aug 6'!$AJ$8:$AJ$42+('Aug 6'!$G$8:$G$42=$T5)*'Aug 6'!$AK$8:$AK$42) -> 0 | AA5: =SUMPRODUCT(('Aug 7'!$F$8:$F$42=$T5)*'Aug 7'!$AJ$8:$AJ$42+('Aug 7'!$G$8:$G$42=$T5)*'Aug 7'!$AK$8:$AK$42) -> 0 | AB5: =SUMPRODUCT(('Aug 8'!$F$8:$F$42=$T5)*'Aug 8'!$AJ$8:$AJ$42+('Aug 8'!$G$8:$G$42=$T5)*'Aug 8'!$AK$8:$AK$42) -> 0 | AC5: =SUMPRODUCT(('Aug 9'!$F$8:$F$42=$T5)*'Aug 9'!$AJ$8:$AJ$42+('Aug 9'!$G$8:$G$42=$T5)*'Aug 9'!$AK$8:$AK$42) -> 0 | AD5: =SUMPRODUCT(('Aug 10'!$F$8:$F$42=$T5)*'Aug 10'!$AJ$8:$AJ$42+('Aug 10'!$G$8:$G$42=$T5)*'Aug 10'!$AK$8:$AK$42) -> 0 | AE5: =SUMPRODUCT(('Aug 11'!$F$8:$F$42=$T5)*'Aug 11'!$AJ$8:$AJ$42+('Aug 11'!$G$8:$G$42=$T5)*'Aug 11'!$AK$8:$AK$42) -> 0 | AF5: =SUMPRODUCT(('Aug 12'!$F$8:$F$42=$T5)*'Aug 12'!$AJ$8:$AJ$42+('Aug 12'!$G$8:$G$42=$T5)*'Aug 12'!$AK$8:$AK$42) -> 0 | AG5: =SUMPRODUCT(('Aug 13'!$F$8:$F$42=$T5)*'Aug 13'!$AJ$8:$AJ$42+('Aug 13'!$G$8:$G$42=$T5)*'Aug 13'!$AK$8:$AK$42) -> 0 | AH5: =SUMPRODUCT(('Aug 14'!$F$8:$F$42=$T5)*'Aug 14'!$AJ$8:$AJ$42+('Aug 14'!$G$8:$G$42=$T5)*'Aug 14'!$AK$8:$AK$42) -> 0 | AI5: =SUMPRODUCT(('Aug 15'!$F$8:$F$42=$T5)*'Aug 15'!$AJ$8:$AJ$42+('Aug 15'!$G$8:$G$42=$T5)*'Aug 15'!$AK$8:$AK$42) -> 0 | AJ5: =SUMPRODUCT(('Aug 16'!$F$8:$F$42=$T5)*'Aug 16'!$AJ$8:$AJ$42+('Aug 16'!$G$8:$G$42=$T5)*'Aug 16'!$AK$8:$AK$42) -> 0 | AK5: =SUMPRODUCT(('Aug 17'!$F$8:$F$42=$T5)*'Aug 17'!$AJ$8:$AJ$42+('Aug 17'!$G$8:$G$42=$T5)*'Aug 17'!$AK$8:$AK$42) -> 0 | AL5: =SUMPRODUCT(('Aug 18'!$F$8:$F$42=$T5)*'Aug 18'!$AJ$8:$AJ$42+('Aug 18'!$G$8:$G$42=$T5)*'Aug 18'!$AK$8:$AK$42) -> 0 | AM5: =SUMPRODUCT(('Aug 19'!$F$8:$F$42=$T5)*'Aug 19'!$AJ$8:$AJ$42+('Aug 19'!$G$8:$G$42=$T5)*'Aug 19'!$AK$8:$AK$42) -> 0 | AN5: =SUMPRODUCT(('Aug 20'!$F$8:$F$42=$T5)*'Aug 20'!$AJ$8:$AJ$42+('Aug 20'!$G$8:$G$42=$T5)*'Aug 20'!$AK$8:$AK$42) -> 0 | AO5: =SUMPRODUCT(('Aug 21'!$F$8:$F$42=$T5)*'Aug 21'!$AJ$8:$AJ$42+('Aug 21'!$G$8:$G$42=$T5)*'Aug 21'!$AK$8:$AK$42) -> 0 | AP5: =SUMPRODUCT(('Aug 22'!$F$8:$F$42=$T5)*'Aug 22'!$AJ$8:$AJ$42+('Aug 22'!$G$8:$G$42=$T5)*'Aug 22'!$AK$8:$AK$42) -> 0 | AQ5: =SUMPRODUCT(('Aug 23'!$F$8:$F$42=$T5)*'Aug 23'!$AJ$8:$AJ$42+('Aug 23'!$G$8:$G$42=$T5)*'Aug 23'!$AK$8:$AK$42) -> 0 | AR5: =SUMPRODUCT(('Aug 24'!$F$8:$F$42=$T5)*'Aug 24'!$AJ$8:$AJ$42+('Aug 24'!$G$8:$G$42=$T5)*'Aug 24'!$AK$8:$AK$42) -> 0 | AS5: =SUMPRODUCT(('Aug 25'!$F$8:$F$42=$T5)*'Aug 25'!$AJ$8:$AJ$42+('Aug 25'!$G$8:$G$42=$T5)*'Aug 25'!$AK$8:$AK$42) -> 0 | AT5: =SUMPRODUCT(('Aug 26'!$F$8:$F$42=$T5)*'Aug 26'!$AJ$8:$AJ$42+('Aug 26'!$G$8:$G$42=$T5)*'Aug 26'!$AK$8:$AK$42) -> 0 | AU5: =SUMPRODUCT(('Aug 27'!$F$8:$F$42=$T5)*'Aug 27'!$AJ$8:$AJ$42+('Aug 27'!$G$8:$G$42=$T5)*'Aug 27'!$AK$8:$AK$42) -> 0 | AV5: =SUMPRODUCT(('Aug 28'!$F$8:$F$42=$T5)*'Aug 28'!$AJ$8:$AJ$42+('Aug 28'!$G$8:$G$42=$T5)*'Aug 28'!$AK$8:$AK$42) -> 0 | AW5: =SUMPRODUCT(('Aug 29'!$F$8:$F$42=$T5)*'Aug 29'!$AJ$8:$AJ$42+('Aug 29'!$G$8:$G$42=$T5)*'Aug 29'!$AK$8:$AK$42) -> 0 | AX5: =SUMPRODUCT(('Aug 30'!$F$8:$F$42=$T5)*'Aug 30'!$AJ$8:$AJ$42+('Aug 30'!$G$8:$G$42=$T5)*'Aug 30'!$AK$8:$AK$42) -> 0 | AY5: =SUMPRODUCT(('Aug 31'!$F$8:$F$42=$T5)*'Aug 31'!$AJ$8:$AJ$42+('Aug 31'!$G$8:$G$42=$T5)*'Aug 31'!$AK$8:$AK$42) -> 0 | BA5: =SUM(U5:AD5) -> 0 | BB5: =MATCH(BD5,'Pay Plan'!$C$6:$C$12,1) -> 1 | BC5: =SUMPRODUCT(('Aug 1'!$F$8:$F$42=$T5)*'Aug 1'!$AI$8:$AI$42*(('Aug 1'!$AM$8:$AM$42="Y")+('Aug 1'!$AN$8:$AN$42="Y")+('Aug 1'!$AO$8:$AO$42="Y")))+SUMPRODUCT(('Aug 2'!$F$8:$F$42=$T5)*'Aug 2'!$AI$8:$AI$42*(('Aug 2'!$AM$8:$AM$42="Y")+('Aug 2'!$AN$8:$AN$42="Y")+('Aug 2'!$AO$8:$AO$42="Y")))+SUMPRODUCT(('Aug 3'!$F$8:$F$42=$T5)*'Aug 3'!$AI$8:$AI$42*(('Aug 3'!$AM$8:$AM$42="Y")+('Aug 3'!$AN$8:$AN$42="Y")+('Aug 3'!$AO$8:$AO$42="Y")))+SUMPRODUCT(('Aug 4'!$F$8:$F$42=$T5)*'Aug 4'!$AI$8:$AI$42*(('Aug 4'!$AM$8:$AM$42="Y")+('Aug 4'!$AN$8:$AN$42="Y")+('Aug 4'!$AO$8:$AO$42="Y")))+SUMPRODUCT(('Aug 5'!$F$8:$F$42=$T5)*'Aug 5'!$AI$8:$AI$42*(('Aug 5'!$AM$8:$AM$42="Y")+('Aug 5'!$AN$8:$AN$42="Y")+('Aug 5'!$AO$8:$AO$42="Y")))+SUMPRODUCT(('Aug 6'!$F$8:$F$42=$T5)*'Aug 6'!$AI$8:$AI$42*(('Aug 6'!$AM$8:$AM$42="Y")+('Aug 6'!$AN$8:$AN$42="Y")+('Aug 6'!$AO$8:$AO$42="Y")))+SUMPRODUCT(('Aug 7'!$F$8:$F$42=$T5)*'Aug 7'!$AI$8:$AI$42*(('Aug 7'!$AM$8:$AM$42="Y")+('Aug 7'!$AN$8:$AN$42="Y")+('Aug 7'!$AO$8:$AO$42="Y")))+SUMPRODUCT(('Aug 8'!$F$8:$F$42=$T5)*'Aug 8'!$AI$8:$AI$42*(('Aug 8'!$AM$8:$AM$42="Y")+('Aug 8'!$AN$8:$AN$42="Y")+('Aug 8'!$AO$8:$AO$42="Y")))+SUMPRODUCT(('Aug 9'!$F$8:$F$42=$T5)*'Aug 9'!$AI$8:$AI$42*(('Aug 9'!$AM$8:$AM$42="Y")+('Aug 9'!$AN$8:$AN$42="Y")+('Aug 9'!$AO$8:$AO$42="Y")))+SUMPRODUCT(('Aug 10'!$F$8:$F$42=$T5)*'Aug 10'!$AI$8:$AI$42*(('Aug 10'!$AM$8:$AM$42="Y")+('Aug 10'!$AN$8:$AN$42="Y")+('Aug 10'!$AO$8:$AO$42="Y")))+SUMPRODUCT(('Aug 11'!$F$8:$F$42=$T5)*'Aug 11'!$AI$8:$AI$42*(('Aug 11'!$AM$8:$AM$42="Y")+('Aug 11'!$AN$8:$AN$42="Y")+('Aug 11'!$AO$8:$AO$42="Y")))+SUMPRODUCT(('Aug 12'!$F$8:$F$42=$T5)*'Aug 12'!$AI$8:$AI$42*(('Aug 12'!$AM$8:$AM$42="Y")+('Aug 12'!$AN$8:$AN$42="Y")+('Aug 12'!$AO$8:$AO$42="Y")))+SUMPRODUCT(('Aug 13'!$F$8:$F$42=$T5)*'Aug 13'!$AI$8:$AI$42*(('Aug 13'!$AM$8:$AM$42="Y")+('Aug 13'!$AN$8:$AN$42="Y")+('Aug 13'!$AO$8:$AO$42="Y")))+SUMPRODUCT(('Aug 14'!$F$8:$F$42=$T5)*'Aug 14'!$AI$8:$AI$42*(('Aug 14'!$AM$8:$AM$42="Y")+('Aug 14'!$AN$8:$AN$42="Y")+('Aug 14'!$AO$8:$AO$42="Y")))+SUMPRODUCT(('Aug 15'!$F$8:$F$42=$T5)*'Aug 15'!$AI$8:$AI$42*(('Aug 15'!$AM$8:$AM$42="Y")+('Aug 15'!$AN$8:$AN$42="Y")+('Aug 15'!$AO$8:$AO$42="Y")))+SUMPRODUCT(('Aug 16'!$F$8:$F$42=$T5)*'Aug 16'!$AI$8:$AI$42*(('Aug 16'!$AM$8:$AM$42="Y")+('Aug 16'!$AN$8:$AN$42="Y")+('Aug 16'!$AO$8:$AO$42="Y")))+SUMPRODUCT(('Aug 17'!$F$8:$F$42=$T5)*'Aug 17'!$AI$8:$AI$42*(('Aug 17'!$AM$8:$AM$42="Y")+('Aug 17'!$AN$8:$AN$42="Y")+('Aug 17'!$AO$8:$AO$42="Y")))+SUMPRODUCT(('Aug 18'!$F$8:$F$42=$T5)*'Aug 18'!$AI$8:$AI$42*(('Aug 18'!$AM$8:$AM$42="Y")+('Aug 18'!$AN$8:$AN$42="Y")+('Aug 18'!$AO$8:$AO$42="Y")))+SUMPRODUCT(('Aug 19'!$F$8:$F$42=$T5)*'Aug 19'!$AI$8:$AI$42*(('Aug 19'!$AM$8:$AM$42="Y")+('Aug 19'!$AN$8:$AN$42="Y")+('Aug 19'!$AO$8:$AO$42="Y")))+SUMPRODUCT(('Aug 20'!$F$8:$F$42=$T5)*'Aug 20'!$AI$8:$AI$42*(('Aug 20'!$AM$8:$AM$42="Y")+('Aug 20'!$AN$8:$AN$42="Y")+('Aug 20'!$AO$8:$AO$42="Y")))+SUMPRODUCT(('Aug 21'!$F$8:$F$42=$T5)*'Aug 21'!$AI$8:$AI$42*(('Aug 21'!$AM$8:$AM$42="Y")+('Aug 21'!$AN$8:$AN$42="Y")+('Aug 21'!$AO$8:$AO$42="Y")))+SUMPRODUCT(('Aug 22'!$F$8:$F$42=$T5)*'Aug 22'!$AI$8:$AI$42*(('Aug 22'!$AM$8:$AM$42="Y")+('Aug 22'!$AN$8:$AN$42="Y")+('Aug 22'!$AO$8:$AO$42="Y")))+SUMPRODUCT(('Aug 23'!$F$8:$F$42=$T5)*'Aug 23'!$AI$8:$AI$42*(('Aug 23'!$AM$8:$AM$42="Y")+('Aug 23'!$AN$8:$AN$42="Y")+('Aug 23'!$AO$8:$AO$42="Y")))+SUMPRODUCT(('Aug 24'!$F$8:$F$42=$T5)*'Aug 24'!$AI$8:$AI$42*(('Aug 24'!$AM$8:$AM$42="Y")+('Aug 24'!$AN$8:$AN$42="Y")+('Aug 24'!$AO$8:$AO$42="Y")))+SUMPRODUCT(('Aug 25'!$F$8:$F$42=$T5)*'Aug 25'!$AI$8:$AI$42*(('Aug 25'!$AM$8:$AM$42="Y")+('Aug 25'!$AN$8:$AN$42="Y")+('Aug 25'!$AO$8:$AO$42="Y")))+SUMPRODUCT(('Aug 26'!$F$8:$F$42=$T5)*'Aug 26'!$AI$8:$AI$42*(('Aug 26'!$AM$8:$AM$42="Y")+('Aug 26'!$AN$8:$AN$42="Y")+('Aug 26'!$AO$8:$AO$42="Y")))+SUMPRODUCT(('Aug 27'!$F$8:$F$42=$T5)*'Aug 27'!$AI$8:$AI$42*(('Aug 27'!$AM$8:$AM$42="Y")+('Aug 27'!$AN$8:$AN$42="Y")+('Aug 27'!$AO$8:$AO$42="Y")))+SUMPRODUCT(('Aug 28'!$F$8:$F$42=$T5)*'Aug 28'!$AI$8:$AI$42*(('Aug 28'!$AM$8:$AM$42="Y")+('Aug 28'!$AN$8:$AN$42="Y")+('Aug 28'!$AO$8:$AO$42="Y")))+SUMPRODUCT(('Aug 29'!$F$8:$F$42=$T5)*'Aug 29'!$AI$8:$AI$42*(('Aug 29'!$AM$8:$AM$42="Y")+('Aug 29'!$AN$8:$AN$42="Y")+('Aug 29'!$AO$8:$AO$42="Y")))+SUMPRODUCT(('Aug 30'!$F$8:$F$42=$T5)*'Aug 30'!$AI$8:$AI$42*(('Aug 30'!$AM$8:$AM$42="Y")+('Aug 30'!$AN$8:$AN$42="Y")+('Aug 30'!$AO$8:$AO$42="Y")))+SUMPRODUCT(('Aug 31'!$F$8:$F$42=$T5)*'Aug 31'!$AI$8:$AI$42*(('Aug 31'!$AM$8:$AM$42="Y")+('Aug 31'!$AN$8:$AN$42="Y")+('Aug 31'!$AO$8:$AO$42="Y"))) -> 0 | BD5: =SUM(U5:AY5) -> 0 | BE5: =SUM(U24:AY24) -> 0 | BF5: =SUM(U43:AY43) -> 0 | BH5: =SUMPRODUCT('Aug 1'!$AI$8:$AI$42*(('Aug 1'!$AM$8:$AM$42="Y")+('Aug 1'!$AN$8:$AN$42="Y")+('Aug 1'!$AO$8:$AO$42="Y")))+SUMPRODUCT('Aug 2'!$AI$8:$AI$42*(('Aug 2'!$AM$8:$AM$42="Y")+('Aug 2'!$AN$8:$AN$42="Y")+('Aug 2'!$AO$8:$AO$42="Y")))+SUMPRODUCT('Aug 3'!$AI$8:$AI$42*(('Aug 3'!$AM$8:$AM$42="Y")+('Aug 3'!$AN$8:$AN$42="Y")+('Aug 3'!$AO$8:$AO$42="Y")))+SUMPRODUCT('Aug 4'!$AI$8:$AI$42*(('Aug 4'!$AM$8:$AM$42="Y")+('Aug 4'!$AN$8:$AN$42="Y")+('Aug 4'!$AO$8:$AO$42="Y")))+SUMPRODUCT('Aug 5'!$AI$8:$AI$42*(('Aug 5'!$AM$8:$AM$42="Y")+('Aug 5'!$AN$8:$AN$42="Y")+('Aug 5'!$AO$8:$AO$42="Y")))+SUMPRODUCT('Aug 6'!$AI$8:$AI$42*(('Aug 6'!$AM$8:$AM$42="Y")+('Aug 6'!$AN$8:$AN$42="Y")+('Aug 6'!$AO$8:$AO$42="Y")))+SUMPRODUCT('Aug 7'!$AI$8:$AI$42*(('Aug 7'!$AM$8:$AM$42="Y")+('Aug 7'!$AN$8:$AN$42="Y")+('Aug 7'!$AO$8:$AO$42="Y")))+SUMPRODUCT('Aug 8'!$AI$8:$AI$42*(('Aug 8'!$AM$8:$AM$42="Y")+('Aug 8'!$AN$8:$AN$42="Y")+('Aug 8'!$AO$8:$AO$42="Y")))+SUMPRODUCT('Aug 9'!$AI$8:$AI$42*(('Aug 9'!$AM$8:$AM$42="Y")+('Aug 9'!$AN$8:$AN$42="Y")+('Aug 9'!$AO$8:$AO$42="Y")))+SUMPRODUCT('Aug 10'!$AI$8:$AI$42*(('Aug 10'!$AM$8:$AM$42="Y")+('Aug 10'!$AN$8:$AN$42="Y")+('Aug 10'!$AO$8:$AO$42="Y")))+SUMPRODUCT('Aug 11'!$AI$8:$AI$42*(('Aug 11'!$AM$8:$AM$42="Y")+('Aug 11'!$AN$8:$AN$42="Y")+('Aug 11'!$AO$8:$AO$42="Y")))+SUMPRODUCT('Aug 12'!$AI$8:$AI$42*(('Aug 12'!$AM$8:$AM$42="Y")+('Aug 12'!$AN$8:$AN$42="Y")+('Aug 12'!$AO$8:$AO$42="Y")))+SUMPRODUCT('Aug 13'!$AI$8:$AI$42*(('Aug 13'!$AM$8:$AM$42="Y")+('Aug 13'!$AN$8:$AN$42="Y")+('Aug 13'!$AO$8:$AO$42="Y")))+SUMPRODUCT('Aug 14'!$AI$8:$AI$42*(('Aug 14'!$AM$8:$AM$42="Y")+('Aug 14'!$AN$8:$AN$42="Y")+('Aug 14'!$AO$8:$AO$42="Y")))+SUMPRODUCT('Aug 15'!$AI$8:$AI$42*(('Aug 15'!$AM$8:$AM$42="Y")+('Aug 15'!$AN$8:$AN$42="Y")+('Aug 15'!$AO$8:$AO$42="Y")))+SUMPRODUCT('Aug 16'!$AI$8:$AI$42*(('Aug 16'!$AM$8:$AM$42="Y")+('Aug 16'!$AN$8:$AN$42="Y")+('Aug 16'!$AO$8:$AO$42="Y")))+SUMPRODUCT('Aug 17'!$AI$8:$AI$42*(('Aug 17'!$AM$8:$AM$42="Y")+('Aug 17'!$AN$8:$AN$42="Y")+('Aug 17'!$AO$8:$AO$42="Y")))+SUMPRODUCT('Aug 18'!$AI$8:$AI$42*(('Aug 18'!$AM$8:$AM$42="Y")+('Aug 18'!$AN$8:$AN$42="Y")+('Aug 18'!$AO$8:$AO$42="Y")))+SUMPRODUCT('Aug 19'!$AI$8:$AI$42*(('Aug 19'!$AM$8:$AM$42="Y")+('Aug 19'!$AN$8:$AN$42="Y")+('Aug 19'!$AO$8:$AO$42="Y")))+SUMPRODUCT('Aug 20'!$AI$8:$AI$42*(('Aug 20'!$AM$8:$AM$42="Y")+('Aug 20'!$AN$8:$AN$42="Y")+('Aug 20'!$AO$8:$AO$42="Y")))+SUMPRODUCT('Aug 21'!$AI$8:$AI$42*(('Aug 21'!$AM$8:$AM$42="Y")+('Aug 21'!$AN$8:$AN$42="Y")+('Aug 21'!$AO$8:$AO$42="Y")))+SUMPRODUCT('Aug 22'!$AI$8:$AI$42*(('Aug 22'!$AM$8:$AM$42="Y")+('Aug 22'!$AN$8:$AN$42="Y")+('Aug 22'!$AO$8:$AO$42="Y")))+SUMPRODUCT('Aug 23'!$AI$8:$AI$42*(('Aug 23'!$AM$8:$AM$42="Y")+('Aug 23'!$AN$8:$AN$42="Y")+('Aug 23'!$AO$8:$AO$42="Y")))+SUMPRODUCT('Aug 24'!$AI$8:$AI$42*(('Aug 24'!$AM$8:$AM$42="Y")+('Aug 24'!$AN$8:$AN$42="Y")+('Aug 24'!$AO$8:$AO$42="Y")))+SUMPRODUCT('Aug 25'!$AI$8:$AI$42*(('Aug 25'!$AM$8:$AM$42="Y")+('Aug 25'!$AN$8:$AN$42="Y")+('Aug 25'!$AO$8:$AO$42="Y")))+SUMPRODUCT('Aug 26'!$AI$8:$AI$42*(('Aug 26'!$AM$8:$AM$42="Y")+('Aug 26'!$AN$8:$AN$42="Y")+('Aug 26'!$AO$8:$AO$42="Y")))+SUMPRODUCT('Aug 27'!$AI$8:$AI$42*(('Aug 27'!$AM$8:$AM$42="Y")+('Aug 27'!$AN$8:$AN$42="Y")+('Aug 27'!$AO$8:$AO$42="Y")))+SUMPRODUCT('Aug 28'!$AI$8:$AI$42*(('Aug 28'!$AM$8:$AM$42="Y")+('Aug 28'!$AN$8:$AN$42="Y")+('Aug 28'!$AO$8:$AO$42="Y")))+SUMPRODUCT('Aug 29'!$AI$8:$AI$42*(('Aug 29'!$AM$8:$AM$42="Y")+('Aug 29'!$AN$8:$AN$42="Y")+('Aug 29'!$AO$8:$AO$42="Y")))+SUMPRODUCT('Aug 30'!$AI$8:$AI$42*(('Aug 30'!$AM$8:$AM$42="Y")+('Aug 30'!$AN$8:$AN$42="Y")+('Aug 30'!$AO$8:$AO$42="Y")))+SUMPRODUCT('Aug 31'!$AI$8:$AI$42*(('Aug 31'!$AM$8:$AM$42="Y")+('Aug 31'!$AN$8:$AN$42="Y")+('Aug 31'!$AO$8:$AO$42="Y"))) -> 0
A6: # | B6: Salesperson | C6: Units | D6: Gross | E6: PVR | F6: Tier | G6: Flat | H6: Unit Bon | I6: FastStrt | J6: Prod $ | K6: EARNINGS | N6: Draw | O6: BALANCE | T6: ='Staff & Lists'!A7 -> RICH AMMERMAN | U6: =SUMPRODUCT(('Aug 1'!$F$8:$F$42=$T6)*'Aug 1'!$AJ$8:$AJ$42+('Aug 1'!$G$8:$G$42=$T6)*'Aug 1'!$AK$8:$AK$42) -> 0 | V6: =SUMPRODUCT(('Aug 2'!$F$8:$F$42=$T6)*'Aug 2'!$AJ$8:$AJ$42+('Aug 2'!$G$8:$G$42=$T6)*'Aug 2'!$AK$8:$AK$42) -> 0 | W6: =SUMPRODUCT(('Aug 3'!$F$8:$F$42=$T6)*'Aug 3'!$AJ$8:$AJ$42+('Aug 3'!$G$8:$G$42=$T6)*'Aug 3'!$AK$8:$AK$42) -> 0 | X6: =SUMPRODUCT(('Aug 4'!$F$8:$F$42=$T6)*'Aug 4'!$AJ$8:$AJ$42+('Aug 4'!$G$8:$G$42=$T6)*'Aug 4'!$AK$8:$AK$42) -> 0 | Y6: =SUMPRODUCT(('Aug 5'!$F$8:$F$42=$T6)*'Aug 5'!$AJ$8:$AJ$42+('Aug 5'!$G$8:$G$42=$T6)*'Aug 5'!$AK$8:$AK$42) -> 0 | Z6: =SUMPRODUCT(('Aug 6'!$F$8:$F$42=$T6)*'Aug 6'!$AJ$8:$AJ$42+('Aug 6'!$G$8:$G$42=$T6)*'Aug 6'!$AK$8:$AK$42) -> 0 | AA6: =SUMPRODUCT(('Aug 7'!$F$8:$F$42=$T6)*'Aug 7'!$AJ$8:$AJ$42+('Aug 7'!$G$8:$G$42=$T6)*'Aug 7'!$AK$8:$AK$42) -> 0 | AB6: =SUMPRODUCT(('Aug 8'!$F$8:$F$42=$T6)*'Aug 8'!$AJ$8:$AJ$42+('Aug 8'!$G$8:$G$42=$T6)*'Aug 8'!$AK$8:$AK$42) -> 0 | AC6: =SUMPRODUCT(('Aug 9'!$F$8:$F$42=$T6)*'Aug 9'!$AJ$8:$AJ$42+('Aug 9'!$G$8:$G$42=$T6)*'Aug 9'!$AK$8:$AK$42) -> 0 | AD6: =SUMPRODUCT(('Aug 10'!$F$8:$F$42=$T6)*'Aug 10'!$AJ$8:$AJ$42+('Aug 10'!$G$8:$G$42=$T6)*'Aug 10'!$AK$8:$AK$42) -> 0 | AE6: =SUMPRODUCT(('Aug 11'!$F$8:$F$42=$T6)*'Aug 11'!$AJ$8:$AJ$42+('Aug 11'!$G$8:$G$42=$T6)*'Aug 11'!$AK$8:$AK$42) -> 0 | AF6: =SUMPRODUCT(('Aug 12'!$F$8:$F$42=$T6)*'Aug 12'!$AJ$8:$AJ$42+('Aug 12'!$G$8:$G$42=$T6)*'Aug 12'!$AK$8:$AK$42) -> 0 | AG6: =SUMPRODUCT(('Aug 13'!$F$8:$F$42=$T6)*'Aug 13'!$AJ$8:$AJ$42+('Aug 13'!$G$8:$G$42=$T6)*'Aug 13'!$AK$8:$AK$42) -> 0 | AH6: =SUMPRODUCT(('Aug 14'!$F$8:$F$42=$T6)*'Aug 14'!$AJ$8:$AJ$42+('Aug 14'!$G$8:$G$42=$T6)*'Aug 14'!$AK$8:$AK$42) -> 0 | AI6: =SUMPRODUCT(('Aug 15'!$F$8:$F$42=$T6)*'Aug 15'!$AJ$8:$AJ$42+('Aug 15'!$G$8:$G$42=$T6)*'Aug 15'!$AK$8:$AK$42) -> 0 | AJ6: =SUMPRODUCT(('Aug 16'!$F$8:$F$42=$T6)*'Aug 16'!$AJ$8:$AJ$42+('Aug 16'!$G$8:$G$42=$T6)*'Aug 16'!$AK$8:$AK$42) -> 0 | AK6: =SUMPRODUCT(('Aug 17'!$F$8:$F$42=$T6)*'Aug 17'!$AJ$8:$AJ$42+('Aug 17'!$G$8:$G$42=$T6)*'Aug 17'!$AK$8:$AK$42) -> 0 | AL6: =SUMPRODUCT(('Aug 18'!$F$8:$F$42=$T6)*'Aug 18'!$AJ$8:$AJ$42+('Aug 18'!$G$8:$G$42=$T6)*'Aug 18'!$AK$8:$AK$42) -> 0 | AM6: =SUMPRODUCT(('Aug 19'!$F$8:$F$42=$T6)*'Aug 19'!$AJ$8:$AJ$42+('Aug 19'!$G$8:$G$42=$T6)*'Aug 19'!$AK$8:$AK$42) -> 0 | AN6: =SUMPRODUCT(('Aug 20'!$F$8:$F$42=$T6)*'Aug 20'!$AJ$8:$AJ$42+('Aug 20'!$G$8:$G$42=$T6)*'Aug 20'!$AK$8:$AK$42) -> 0 | AO6: =SUMPRODUCT(('Aug 21'!$F$8:$F$42=$T6)*'Aug 21'!$AJ$8:$AJ$42+('Aug 21'!$G$8:$G$42=$T6)*'Aug 21'!$AK$8:$AK$42) -> 0 | AP6: =SUMPRODUCT(('Aug 22'!$F$8:$F$42=$T6)*'Aug 22'!$AJ$8:$AJ$42+('Aug 22'!$G$8:$G$42=$T6)*'Aug 22'!$AK$8:$AK$42) -> 0 | AQ6: =SUMPRODUCT(('Aug 23'!$F$8:$F$42=$T6)*'Aug 23'!$AJ$8:$AJ$42+('Aug 23'!$G$8:$G$42=$T6)*'Aug 23'!$AK$8:$AK$42) -> 0 | AR6: =SUMPRODUCT(('Aug 24'!$F$8:$F$42=$T6)*'Aug 24'!$AJ$8:$AJ$42+('Aug 24'!$G$8:$G$42=$T6)*'Aug 24'!$AK$8:$AK$42) -> 0 | AS6: =SUMPRODUCT(('Aug 25'!$F$8:$F$42=$T6)*'Aug 25'!$AJ$8:$AJ$42+('Aug 25'!$G$8:$G$42=$T6)*'Aug 25'!$AK$8:$AK$42) -> 0 | AT6: =SUMPRODUCT(('Aug 26'!$F$8:$F$42=$T6)*'Aug 26'!$AJ$8:$AJ$42+('Aug 26'!$G$8:$G$42=$T6)*'Aug 26'!$AK$8:$AK$42) -> 0 | AU6: =SUMPRODUCT(('Aug 27'!$F$8:$F$42=$T6)*'Aug 27'!$AJ$8:$AJ$42+('Aug 27'!$G$8:$G$42=$T6)*'Aug 27'!$AK$8:$AK$42) -> 0 | AV6: =SUMPRODUCT(('Aug 28'!$F$8:$F$42=$T6)*'Aug 28'!$AJ$8:$AJ$42+('Aug 28'!$G$8:$G$42=$T6)*'Aug 28'!$AK$8:$AK$42) -> 0 | AW6: =SUMPRODUCT(('Aug 29'!$F$8:$F$42=$T6)*'Aug 29'!$AJ$8:$AJ$42+('Aug 29'!$G$8:$G$42=$T6)*'Aug 29'!$AK$8:$AK$42) -> 0 | AX6: =SUMPRODUCT(('Aug 30'!$F$8:$F$42=$T6)*'Aug 30'!$AJ$8:$AJ$42+('Aug 30'!$G$8:$G$42=$T6)*'Aug 30'!$AK$8:$AK$42) -> 0 | AY6: =SUMPRODUCT(('Aug 31'!$F$8:$F$42=$T6)*'Aug 31'!$AJ$8:$AJ$42+('Aug 31'!$G$8:$G$42=$T6)*'Aug 31'!$AK$8:$AK$42) -> 0 | BA6: =SUM(U6:AD6) -> 0 | BB6: =MATCH(BD6,'Pay Plan'!$C$6:$C$12,1) -> 1 | BC6: =SUMPRODUCT(('Aug 1'!$F$8:$F$42=$T6)*'Aug 1'!$AI$8:$AI$42*(('Aug 1'!$AM$8:$AM$42="Y")+('Aug 1'!$AN$8:$AN$42="Y")+('Aug 1'!$AO$8:$AO$42="Y")))+SUMPRODUCT(('Aug 2'!$F$8:$F$42=$T6)*'Aug 2'!$AI$8:$AI$42*(('Aug 2'!$AM$8:$AM$42="Y")+('Aug 2'!$AN$8:$AN$42="Y")+('Aug 2'!$AO$8:$AO$42="Y")))+SUMPRODUCT(('Aug 3'!$F$8:$F$42=$T6)*'Aug 3'!$AI$8:$AI$42*(('Aug 3'!$AM$8:$AM$42="Y")+('Aug 3'!$AN$8:$AN$42="Y")+('Aug 3'!$AO$8:$AO$42="Y")))+SUMPRODUCT(('Aug 4'!$F$8:$F$42=$T6)*'Aug 4'!$AI$8:$AI$42*(('Aug 4'!$AM$8:$AM$42="Y")+('Aug 4'!$AN$8:$AN$42="Y")+('Aug 4'!$AO$8:$AO$42="Y")))+SUMPRODUCT(('Aug 5'!$F$8:$F$42=$T6)*'Aug 5'!$AI$8:$AI$42*(('Aug 5'!$AM$8:$AM$42="Y")+('Aug 5'!$AN$8:$AN$42="Y")+('Aug 5'!$AO$8:$AO$42="Y")))+SUMPRODUCT(('Aug 6'!$F$8:$F$42=$T6)*'Aug 6'!$AI$8:$AI$42*(('Aug 6'!$AM$8:$AM$42="Y")+('Aug 6'!$AN$8:$AN$42="Y")+('Aug 6'!$AO$8:$AO$42="Y")))+SUMPRODUCT(('Aug 7'!$F$8:$F$42=$T6)*'Aug 7'!$AI$8:$AI$42*(('Aug 7'!$AM$8:$AM$42="Y")+('Aug 7'!$AN$8:$AN$42="Y")+('Aug 7'!$AO$8:$AO$42="Y")))+SUMPRODUCT(('Aug 8'!$F$8:$F$42=$T6)*'Aug 8'!$AI$8:$AI$42*(('Aug 8'!$AM$8:$AM$42="Y")+('Aug 8'!$AN$8:$AN$42="Y")+('Aug 8'!$AO$8:$AO$42="Y")))+SUMPRODUCT(('Aug 9'!$F$8:$F$42=$T6)*'Aug 9'!$AI$8:$AI$42*(('Aug 9'!$AM$8:$AM$42="Y")+('Aug 9'!$AN$8:$AN$42="Y")+('Aug 9'!$AO$8:$AO$42="Y")))+SUMPRODUCT(('Aug 10'!$F$8:$F$42=$T6)*'Aug 10'!$AI$8:$AI$42*(('Aug 10'!$AM$8:$AM$42="Y")+('Aug 10'!$AN$8:$AN$42="Y")+('Aug 10'!$AO$8:$AO$42="Y")))+SUMPRODUCT(('Aug 11'!$F$8:$F$42=$T6)*'Aug 11'!$AI$8:$AI$42*(('Aug 11'!$AM$8:$AM$42="Y")+('Aug 11'!$AN$8:$AN$42="Y")+('Aug 11'!$AO$8:$AO$42="Y")))+SUMPRODUCT(('Aug 12'!$F$8:$F$42=$T6)*'Aug 12'!$AI$8:$AI$42*(('Aug 12'!$AM$8:$AM$42="Y")+('Aug 12'!$AN$8:$AN$42="Y")+('Aug 12'!$AO$8:$AO$42="Y")))+SUMPRODUCT(('Aug 13'!$F$8:$F$42=$T6)*'Aug 13'!$AI$8:$AI$42*(('Aug 13'!$AM$8:$AM$42="Y")+('Aug 13'!$AN$8:$AN$42="Y")+('Aug 13'!$AO$8:$AO$42="Y")))+SUMPRODUCT(('Aug 14'!$F$8:$F$42=$T6)*'Aug 14'!$AI$8:$AI$42*(('Aug 14'!$AM$8:$AM$42="Y")+('Aug 14'!$AN$8:$AN$42="Y")+('Aug 14'!$AO$8:$AO$42="Y")))+SUMPRODUCT(('Aug 15'!$F$8:$F$42=$T6)*'Aug 15'!$AI$8:$AI$42*(('Aug 15'!$AM$8:$AM$42="Y")+('Aug 15'!$AN$8:$AN$42="Y")+('Aug 15'!$AO$8:$AO$42="Y")))+SUMPRODUCT(('Aug 16'!$F$8:$F$42=$T6)*'Aug 16'!$AI$8:$AI$42*(('Aug 16'!$AM$8:$AM$42="Y")+('Aug 16'!$AN$8:$AN$42="Y")+('Aug 16'!$AO$8:$AO$42="Y")))+SUMPRODUCT(('Aug 17'!$F$8:$F$42=$T6)*'Aug 17'!$AI$8:$AI$42*(('Aug 17'!$AM$8:$AM$42="Y")+('Aug 17'!$AN$8:$AN$42="Y")+('Aug 17'!$AO$8:$AO$42="Y")))+SUMPRODUCT(('Aug 18'!$F$8:$F$42=$T6)*'Aug 18'!$AI$8:$AI$42*(('Aug 18'!$AM$8:$AM$42="Y")+('Aug 18'!$AN$8:$AN$42="Y")+('Aug 18'!$AO$8:$AO$42="Y")))+SUMPRODUCT(('Aug 19'!$F$8:$F$42=$T6)*'Aug 19'!$AI$8:$AI$42*(('Aug 19'!$AM$8:$AM$42="Y")+('Aug 19'!$AN$8:$AN$42="Y")+('Aug 19'!$AO$8:$AO$42="Y")))+SUMPRODUCT(('Aug 20'!$F$8:$F$42=$T6)*'Aug 20'!$AI$8:$AI$42*(('Aug 20'!$AM$8:$AM$42="Y")+('Aug 20'!$AN$8:$AN$42="Y")+('Aug 20'!$AO$8:$AO$42="Y")))+SUMPRODUCT(('Aug 21'!$F$8:$F$42=$T6)*'Aug 21'!$AI$8:$AI$42*(('Aug 21'!$AM$8:$AM$42="Y")+('Aug 21'!$AN$8:$AN$42="Y")+('Aug 21'!$AO$8:$AO$42="Y")))+SUMPRODUCT(('Aug 22'!$F$8:$F$42=$T6)*'Aug 22'!$AI$8:$AI$42*(('Aug 22'!$AM$8:$AM$42="Y")+('Aug 22'!$AN$8:$AN$42="Y")+('Aug 22'!$AO$8:$AO$42="Y")))+SUMPRODUCT(('Aug 23'!$F$8:$F$42=$T6)*'Aug 23'!$AI$8:$AI$42*(('Aug 23'!$AM$8:$AM$42="Y")+('Aug 23'!$AN$8:$AN$42="Y")+('Aug 23'!$AO$8:$AO$42="Y")))+SUMPRODUCT(('Aug 24'!$F$8:$F$42=$T6)*'Aug 24'!$AI$8:$AI$42*(('Aug 24'!$AM$8:$AM$42="Y")+('Aug 24'!$AN$8:$AN$42="Y")+('Aug 24'!$AO$8:$AO$42="Y")))+SUMPRODUCT(('Aug 25'!$F$8:$F$42=$T6)*'Aug 25'!$AI$8:$AI$42*(('Aug 25'!$AM$8:$AM$42="Y")+('Aug 25'!$AN$8:$AN$42="Y")+('Aug 25'!$AO$8:$AO$42="Y")))+SUMPRODUCT(('Aug 26'!$F$8:$F$42=$T6)*'Aug 26'!$AI$8:$AI$42*(('Aug 26'!$AM$8:$AM$42="Y")+('Aug 26'!$AN$8:$AN$42="Y")+('Aug 26'!$AO$8:$AO$42="Y")))+SUMPRODUCT(('Aug 27'!$F$8:$F$42=$T6)*'Aug 27'!$AI$8:$AI$42*(('Aug 27'!$AM$8:$AM$42="Y")+('Aug 27'!$AN$8:$AN$42="Y")+('Aug 27'!$AO$8:$AO$42="Y")))+SUMPRODUCT(('Aug 28'!$F$8:$F$42=$T6)*'Aug 28'!$AI$8:$AI$42*(('Aug 28'!$AM$8:$AM$42="Y")+('Aug 28'!$AN$8:$AN$42="Y")+('Aug 28'!$AO$8:$AO$42="Y")))+SUMPRODUCT(('Aug 29'!$F$8:$F$42=$T6)*'Aug 29'!$AI$8:$AI$42*(('Aug 29'!$AM$8:$AM$42="Y")+('Aug 29'!$AN$8:$AN$42="Y")+('Aug 29'!$AO$8:$AO$42="Y")))+SUMPRODUCT(('Aug 30'!$F$8:$F$42=$T6)*'Aug 30'!$AI$8:$AI$42*(('Aug 30'!$AM$8:$AM$42="Y")+('Aug 30'!$AN$8:$AN$42="Y")+('Aug 30'!$AO$8:$AO$42="Y")))+SUMPRODUCT(('Aug 31'!$F$8:$F$42=$T6)*'Aug 31'!$AI$8:$AI$42*(('Aug 31'!$AM$8:$AM$42="Y")+('Aug 31'!$AN$8:$AN$42="Y")+('Aug 31'!$AO$8:$AO$42="Y"))) -> 0 | BD6: =SUM(U6:AY6) -> 0 | BE6: =SUM(U25:AY25) -> 0 | BF6: =SUM(U44:AY44) -> 0 | BH6: =MIN(BF4:BF19) -> 0
A7: 1 | B7: =$T4 -> FEDY ALI | C7: =BD4 -> 0 | D7: =BE4 -> 0 | E7: =IF(BD4=0,"—",BE4/BD4) -> — | F7: =IF(BD4=0,"—",INDEX('Pay Plan'!$B$6:$B$12,BB4)) -> — | G7: =BF4 -> 0 | H7: =LOOKUP(BD4,'Pay Plan'!$B$15:$B$20,'Pay Plan'!$C$15:$C$20) -> 0 | I7: =LOOKUP(BA4,'Pay Plan'!$E$15:$E$19,'Pay Plan'!$F$15:$F$19) -> 0 | J7: =BC4*'Pay Plan'!$I$15 -> 0 | K7: =G7+H7+I7+J7 -> 0 | O7: =K7-N7 -> 0 | T7: ='Staff & Lists'!A8 -> GARRET SCHWETTMAN | U7: =SUMPRODUCT(('Aug 1'!$F$8:$F$42=$T7)*'Aug 1'!$AJ$8:$AJ$42+('Aug 1'!$G$8:$G$42=$T7)*'Aug 1'!$AK$8:$AK$42) -> 0 | V7: =SUMPRODUCT(('Aug 2'!$F$8:$F$42=$T7)*'Aug 2'!$AJ$8:$AJ$42+('Aug 2'!$G$8:$G$42=$T7)*'Aug 2'!$AK$8:$AK$42) -> 0 | W7: =SUMPRODUCT(('Aug 3'!$F$8:$F$42=$T7)*'Aug 3'!$AJ$8:$AJ$42+('Aug 3'!$G$8:$G$42=$T7)*'Aug 3'!$AK$8:$AK$42) -> 0 | X7: =SUMPRODUCT(('Aug 4'!$F$8:$F$42=$T7)*'Aug 4'!$AJ$8:$AJ$42+('Aug 4'!$G$8:$G$42=$T7)*'Aug 4'!$AK$8:$AK$42) -> 0 | Y7: =SUMPRODUCT(('Aug 5'!$F$8:$F$42=$T7)*'Aug 5'!$AJ$8:$AJ$42+('Aug 5'!$G$8:$G$42=$T7)*'Aug 5'!$AK$8:$AK$42) -> 0 | Z7: =SUMPRODUCT(('Aug 6'!$F$8:$F$42=$T7)*'Aug 6'!$AJ$8:$AJ$42+('Aug 6'!$G$8:$G$42=$T7)*'Aug 6'!$AK$8:$AK$42) -> 0 | AA7: =SUMPRODUCT(('Aug 7'!$F$8:$F$42=$T7)*'Aug 7'!$AJ$8:$AJ$42+('Aug 7'!$G$8:$G$42=$T7)*'Aug 7'!$AK$8:$AK$42) -> 0 | AB7: =SUMPRODUCT(('Aug 8'!$F$8:$F$42=$T7)*'Aug 8'!$AJ$8:$AJ$42+('Aug 8'!$G$8:$G$42=$T7)*'Aug 8'!$AK$8:$AK$42) -> 0 | AC7: =SUMPRODUCT(('Aug 9'!$F$8:$F$42=$T7)*'Aug 9'!$AJ$8:$AJ$42+('Aug 9'!$G$8:$G$42=$T7)*'Aug 9'!$AK$8:$AK$42) -> 0 | AD7: =SUMPRODUCT(('Aug 10'!$F$8:$F$42=$T7)*'Aug 10'!$AJ$8:$AJ$42+('Aug 10'!$G$8:$G$42=$T7)*'Aug 10'!$AK$8:$AK$42) -> 0 | AE7: =SUMPRODUCT(('Aug 11'!$F$8:$F$42=$T7)*'Aug 11'!$AJ$8:$AJ$42+('Aug 11'!$G$8:$G$42=$T7)*'Aug 11'!$AK$8:$AK$42) -> 0 | AF7: =SUMPRODUCT(('Aug 12'!$F$8:$F$42=$T7)*'Aug 12'!$AJ$8:$AJ$42+('Aug 12'!$G$8:$G$42=$T7)*'Aug 12'!$AK$8:$AK$42) -> 0 | AG7: =SUMPRODUCT(('Aug 13'!$F$8:$F$42=$T7)*'Aug 13'!$AJ$8:$AJ$42+('Aug 13'!$G$8:$G$42=$T7)*'Aug 13'!$AK$8:$AK$42) -> 0 | AH7: =SUMPRODUCT(('Aug 14'!$F$8:$F$42=$T7)*'Aug 14'!$AJ$8:$AJ$42+('Aug 14'!$G$8:$G$42=$T7)*'Aug 14'!$AK$8:$AK$42) -> 0 | AI7: =SUMPRODUCT(('Aug 15'!$F$8:$F$42=$T7)*'Aug 15'!$AJ$8:$AJ$42+('Aug 15'!$G$8:$G$42=$T7)*'Aug 15'!$AK$8:$AK$42) -> 0 | AJ7: =SUMPRODUCT(('Aug 16'!$F$8:$F$42=$T7)*'Aug 16'!$AJ$8:$AJ$42+('Aug 16'!$G$8:$G$42=$T7)*'Aug 16'!$AK$8:$AK$42) -> 0 | AK7: =SUMPRODUCT(('Aug 17'!$F$8:$F$42=$T7)*'Aug 17'!$AJ$8:$AJ$42+('Aug 17'!$G$8:$G$42=$T7)*'Aug 17'!$AK$8:$AK$42) -> 0 | AL7: =SUMPRODUCT(('Aug 18'!$F$8:$F$42=$T7)*'Aug 18'!$AJ$8:$AJ$42+('Aug 18'!$G$8:$G$42=$T7)*'Aug 18'!$AK$8:$AK$42) -> 0 | AM7: =SUMPRODUCT(('Aug 19'!$F$8:$F$42=$T7)*'Aug 19'!$AJ$8:$AJ$42+('Aug 19'!$G$8:$G$42=$T7)*'Aug 19'!$AK$8:$AK$42) -> 0 | AN7: =SUMPRODUCT(('Aug 20'!$F$8:$F$42=$T7)*'Aug 20'!$AJ$8:$AJ$42+('Aug 20'!$G$8:$G$42=$T7)*'Aug 20'!$AK$8:$AK$42) -> 0 | AO7: =SUMPRODUCT(('Aug 21'!$F$8:$F$42=$T7)*'Aug 21'!$AJ$8:$AJ$42+('Aug 21'!$G$8:$G$42=$T7)*'Aug 21'!$AK$8:$AK$42) -> 0 | AP7: =SUMPRODUCT(('Aug 22'!$F$8:$F$42=$T7)*'Aug 22'!$AJ$8:$AJ$42+('Aug 22'!$G$8:$G$42=$T7)*'Aug 22'!$AK$8:$AK$42) -> 0 | AQ7: =SUMPRODUCT(('Aug 23'!$F$8:$F$42=$T7)*'Aug 23'!$AJ$8:$AJ$42+('Aug 23'!$G$8:$G$42=$T7)*'Aug 23'!$AK$8:$AK$42) -> 0 | AR7: =SUMPRODUCT(('Aug 24'!$F$8:$F$42=$T7)*'Aug 24'!$AJ$8:$AJ$42+('Aug 24'!$G$8:$G$42=$T7)*'Aug 24'!$AK$8:$AK$42) -> 0 | AS7: =SUMPRODUCT(('Aug 25'!$F$8:$F$42=$T7)*'Aug 25'!$AJ$8:$AJ$42+('Aug 25'!$G$8:$G$42=$T7)*'Aug 25'!$AK$8:$AK$42) -> 0 | AT7: =SUMPRODUCT(('Aug 26'!$F$8:$F$42=$T7)*'Aug 26'!$AJ$8:$AJ$42+('Aug 26'!$G$8:$G$42=$T7)*'Aug 26'!$AK$8:$AK$42) -> 0 | AU7: =SUMPRODUCT(('Aug 27'!$F$8:$F$42=$T7)*'Aug 27'!$AJ$8:$AJ$42+('Aug 27'!$G$8:$G$42=$T7)*'Aug 27'!$AK$8:$AK$42) -> 0 | AV7: =SUMPRODUCT(('Aug 28'!$F$8:$F$42=$T7)*'Aug 28'!$AJ$8:$AJ$42+('Aug 28'!$G$8:$G$42=$T7)*'Aug 28'!$AK$8:$AK$42) -> 0 | AW7: =SUMPRODUCT(('Aug 29'!$F$8:$F$42=$T7)*'Aug 29'!$AJ$8:$AJ$42+('Aug 29'!$G$8:$G$42=$T7)*'Aug 29'!$AK$8:$AK$42) -> 0 | AX7: =SUMPRODUCT(('Aug 30'!$F$8:$F$42=$T7)*'Aug 30'!$AJ$8:$AJ$42+('Aug 30'!$G$8:$G$42=$T7)*'Aug 30'!$AK$8:$AK$42) -> 0 | AY7: =SUMPRODUCT(('Aug 31'!$F$8:$F$42=$T7)*'Aug 31'!$AJ$8:$AJ$42+('Aug 31'!$G$8:$G$42=$T7)*'Aug 31'!$AK$8:$AK$42) -> 0 | BA7: =SUM(U7:AD7) -> 0 | BB7: =MATCH(BD7,'Pay Plan'!$C$6:$C$12,1) -> 1 | BC7: =SUMPRODUCT(('Aug 1'!$F$8:$F$42=$T7)*'Aug 1'!$AI$8:$AI$42*(('Aug 1'!$AM$8:$AM$42="Y")+('Aug 1'!$AN$8:$AN$42="Y")+('Aug 1'!$AO$8:$AO$42="Y")))+SUMPRODUCT(('Aug 2'!$F$8:$F$42=$T7)*'Aug 2'!$AI$8:$AI$42*(('Aug 2'!$AM$8:$AM$42="Y")+('Aug 2'!$AN$8:$AN$42="Y")+('Aug 2'!$AO$8:$AO$42="Y")))+SUMPRODUCT(('Aug 3'!$F$8:$F$42=$T7)*'Aug 3'!$AI$8:$AI$42*(('Aug 3'!$AM$8:$AM$42="Y")+('Aug 3'!$AN$8:$AN$42="Y")+('Aug 3'!$AO$8:$AO$42="Y")))+SUMPRODUCT(('Aug 4'!$F$8:$F$42=$T7)*'Aug 4'!$AI$8:$AI$42*(('Aug 4'!$AM$8:$AM$42="Y")+('Aug 4'!$AN$8:$AN$42="Y")+('Aug 4'!$AO$8:$AO$42="Y")))+SUMPRODUCT(('Aug 5'!$F$8:$F$42=$T7)*'Aug 5'!$AI$8:$AI$42*(('Aug 5'!$AM$8:$AM$42="Y")+('Aug 5'!$AN$8:$AN$42="Y")+('Aug 5'!$AO$8:$AO$42="Y")))+SUMPRODUCT(('Aug 6'!$F$8:$F$42=$T7)*'Aug 6'!$AI$8:$AI$42*(('Aug 6'!$AM$8:$AM$42="Y")+('Aug 6'!$AN$8:$AN$42="Y")+('Aug 6'!$AO$8:$AO$42="Y")))+SUMPRODUCT(('Aug 7'!$F$8:$F$42=$T7)*'Aug 7'!$AI$8:$AI$42*(('Aug 7'!$AM$8:$AM$42="Y")+('Aug 7'!$AN$8:$AN$42="Y")+('Aug 7'!$AO$8:$AO$42="Y")))+SUMPRODUCT(('Aug 8'!$F$8:$F$42=$T7)*'Aug 8'!$AI$8:$AI$42*(('Aug 8'!$AM$8:$AM$42="Y")+('Aug 8'!$AN$8:$AN$42="Y")+('Aug 8'!$AO$8:$AO$42="Y")))+SUMPRODUCT(('Aug 9'!$F$8:$F$42=$T7)*'Aug 9'!$AI$8:$AI$42*(('Aug 9'!$AM$8:$AM$42="Y")+('Aug 9'!$AN$8:$AN$42="Y")+('Aug 9'!$AO$8:$AO$42="Y")))+SUMPRODUCT(('Aug 10'!$F$8:$F$42=$T7)*'Aug 10'!$AI$8:$AI$42*(('Aug 10'!$AM$8:$AM$42="Y")+('Aug 10'!$AN$8:$AN$42="Y")+('Aug 10'!$AO$8:$AO$42="Y")))+SUMPRODUCT(('Aug 11'!$F$8:$F$42=$T7)*'Aug 11'!$AI$8:$AI$42*(('Aug 11'!$AM$8:$AM$42="Y")+('Aug 11'!$AN$8:$AN$42="Y")+('Aug 11'!$AO$8:$AO$42="Y")))+SUMPRODUCT(('Aug 12'!$F$8:$F$42=$T7)*'Aug 12'!$AI$8:$AI$42*(('Aug 12'!$AM$8:$AM$42="Y")+('Aug 12'!$AN$8:$AN$42="Y")+('Aug 12'!$AO$8:$AO$42="Y")))+SUMPRODUCT(('Aug 13'!$F$8:$F$42=$T7)*'Aug 13'!$AI$8:$AI$42*(('Aug 13'!$AM$8:$AM$42="Y")+('Aug 13'!$AN$8:$AN$42="Y")+('Aug 13'!$AO$8:$AO$42="Y")))+SUMPRODUCT(('Aug 14'!$F$8:$F$42=$T7)*'Aug 14'!$AI$8:$AI$42*(('Aug 14'!$AM$8:$AM$42="Y")+('Aug 14'!$AN$8:$AN$42="Y")+('Aug 14'!$AO$8:$AO$42="Y")))+SUMPRODUCT(('Aug 15'!$F$8:$F$42=$T7)*'Aug 15'!$AI$8:$AI$42*(('Aug 15'!$AM$8:$AM$42="Y")+('Aug 15'!$AN$8:$AN$42="Y")+('Aug 15'!$AO$8:$AO$42="Y")))+SUMPRODUCT(('Aug 16'!$F$8:$F$42=$T7)*'Aug 16'!$AI$8:$AI$42*(('Aug 16'!$AM$8:$AM$42="Y")+('Aug 16'!$AN$8:$AN$42="Y")+('Aug 16'!$AO$8:$AO$42="Y")))+SUMPRODUCT(('Aug 17'!$F$8:$F$42=$T7)*'Aug 17'!$AI$8:$AI$42*(('Aug 17'!$AM$8:$AM$42="Y")+('Aug 17'!$AN$8:$AN$42="Y")+('Aug 17'!$AO$8:$AO$42="Y")))+SUMPRODUCT(('Aug 18'!$F$8:$F$42=$T7)*'Aug 18'!$AI$8:$AI$42*(('Aug 18'!$AM$8:$AM$42="Y")+('Aug 18'!$AN$8:$AN$42="Y")+('Aug 18'!$AO$8:$AO$42="Y")))+SUMPRODUCT(('Aug 19'!$F$8:$F$42=$T7)*'Aug 19'!$AI$8:$AI$42*(('Aug 19'!$AM$8:$AM$42="Y")+('Aug 19'!$AN$8:$AN$42="Y")+('Aug 19'!$AO$8:$AO$42="Y")))+SUMPRODUCT(('Aug 20'!$F$8:$F$42=$T7)*'Aug 20'!$AI$8:$AI$42*(('Aug 20'!$AM$8:$AM$42="Y")+('Aug 20'!$AN$8:$AN$42="Y")+('Aug 20'!$AO$8:$AO$42="Y")))+SUMPRODUCT(('Aug 21'!$F$8:$F$42=$T7)*'Aug 21'!$AI$8:$AI$42*(('Aug 21'!$AM$8:$AM$42="Y")+('Aug 21'!$AN$8:$AN$42="Y")+('Aug 21'!$AO$8:$AO$42="Y")))+SUMPRODUCT(('Aug 22'!$F$8:$F$42=$T7)*'Aug 22'!$AI$8:$AI$42*(('Aug 22'!$AM$8:$AM$42="Y")+('Aug 22'!$AN$8:$AN$42="Y")+('Aug 22'!$AO$8:$AO$42="Y")))+SUMPRODUCT(('Aug 23'!$F$8:$F$42=$T7)*'Aug 23'!$AI$8:$AI$42*(('Aug 23'!$AM$8:$AM$42="Y")+('Aug 23'!$AN$8:$AN$42="Y")+('Aug 23'!$AO$8:$AO$42="Y")))+SUMPRODUCT(('Aug 24'!$F$8:$F$42=$T7)*'Aug 24'!$AI$8:$AI$42*(('Aug 24'!$AM$8:$AM$42="Y")+('Aug 24'!$AN$8:$AN$42="Y")+('Aug 24'!$AO$8:$AO$42="Y")))+SUMPRODUCT(('Aug 25'!$F$8:$F$42=$T7)*'Aug 25'!$AI$8:$AI$42*(('Aug 25'!$AM$8:$AM$42="Y")+('Aug 25'!$AN$8:$AN$42="Y")+('Aug 25'!$AO$8:$AO$42="Y")))+SUMPRODUCT(('Aug 26'!$F$8:$F$42=$T7)*'Aug 26'!$AI$8:$AI$42*(('Aug 26'!$AM$8:$AM$42="Y")+('Aug 26'!$AN$8:$AN$42="Y")+('Aug 26'!$AO$8:$AO$42="Y")))+SUMPRODUCT(('Aug 27'!$F$8:$F$42=$T7)*'Aug 27'!$AI$8:$AI$42*(('Aug 27'!$AM$8:$AM$42="Y")+('Aug 27'!$AN$8:$AN$42="Y")+('Aug 27'!$AO$8:$AO$42="Y")))+SUMPRODUCT(('Aug 28'!$F$8:$F$42=$T7)*'Aug 28'!$AI$8:$AI$42*(('Aug 28'!$AM$8:$AM$42="Y")+('Aug 28'!$AN$8:$AN$42="Y")+('Aug 28'!$AO$8:$AO$42="Y")))+SUMPRODUCT(('Aug 29'!$F$8:$F$42=$T7)*'Aug 29'!$AI$8:$AI$42*(('Aug 29'!$AM$8:$AM$42="Y")+('Aug 29'!$AN$8:$AN$42="Y")+('Aug 29'!$AO$8:$AO$42="Y")))+SUMPRODUCT(('Aug 30'!$F$8:$F$42=$T7)*'Aug 30'!$AI$8:$AI$42*(('Aug 30'!$AM$8:$AM$42="Y")+('Aug 30'!$AN$8:$AN$42="Y")+('Aug 30'!$AO$8:$AO$42="Y")))+SUMPRODUCT(('Aug 31'!$F$8:$F$42=$T7)*'Aug 31'!$AI$8:$AI$42*(('Aug 31'!$AM$8:$AM$42="Y")+('Aug 31'!$AN$8:$AN$42="Y")+('Aug 31'!$AO$8:$AO$42="Y"))) -> 0 | BD7: =SUM(U7:AY7) -> 0 | BE7: =SUM(U26:AY26) -> 0 | BF7: =SUM(U45:AY45) -> 0 | BH7: =MIN(BD4:BD19) -> 0
A8: 2 | B8: =$T5 -> CHAD EMBRY | C8: =BD5 -> 0 | D8: =BE5 -> 0 | E8: =IF(BD5=0,"—",BE5/BD5) -> — | F8: =IF(BD5=0,"—",INDEX('Pay Plan'!$B$6:$B$12,BB5)) -> — | G8: =BF5 -> 0 | H8: =LOOKUP(BD5,'Pay Plan'!$B$15:$B$20,'Pay Plan'!$C$15:$C$20) -> 0 | I8: =LOOKUP(BA5,'Pay Plan'!$E$15:$E$19,'Pay Plan'!$F$15:$F$19) -> 0 | J8: =BC5*'Pay Plan'!$I$15 -> 0 | K8: =G8+H8+I8+J8 -> 0 | O8: =K8-N8 -> 0 | T8: ='Staff & Lists'!A9 -> MERCEDES CLARK | U8: =SUMPRODUCT(('Aug 1'!$F$8:$F$42=$T8)*'Aug 1'!$AJ$8:$AJ$42+('Aug 1'!$G$8:$G$42=$T8)*'Aug 1'!$AK$8:$AK$42) -> 0 | V8: =SUMPRODUCT(('Aug 2'!$F$8:$F$42=$T8)*'Aug 2'!$AJ$8:$AJ$42+('Aug 2'!$G$8:$G$42=$T8)*'Aug 2'!$AK$8:$AK$42) -> 0 | W8: =SUMPRODUCT(('Aug 3'!$F$8:$F$42=$T8)*'Aug 3'!$AJ$8:$AJ$42+('Aug 3'!$G$8:$G$42=$T8)*'Aug 3'!$AK$8:$AK$42) -> 0 | X8: =SUMPRODUCT(('Aug 4'!$F$8:$F$42=$T8)*'Aug 4'!$AJ$8:$AJ$42+('Aug 4'!$G$8:$G$42=$T8)*'Aug 4'!$AK$8:$AK$42) -> 0 | Y8: =SUMPRODUCT(('Aug 5'!$F$8:$F$42=$T8)*'Aug 5'!$AJ$8:$AJ$42+('Aug 5'!$G$8:$G$42=$T8)*'Aug 5'!$AK$8:$AK$42) -> 0 | Z8: =SUMPRODUCT(('Aug 6'!$F$8:$F$42=$T8)*'Aug 6'!$AJ$8:$AJ$42+('Aug 6'!$G$8:$G$42=$T8)*'Aug 6'!$AK$8:$AK$42) -> 0 | AA8: =SUMPRODUCT(('Aug 7'!$F$8:$F$42=$T8)*'Aug 7'!$AJ$8:$AJ$42+('Aug 7'!$G$8:$G$42=$T8)*'Aug 7'!$AK$8:$AK$42) -> 0 | AB8: =SUMPRODUCT(('Aug 8'!$F$8:$F$42=$T8)*'Aug 8'!$AJ$8:$AJ$42+('Aug 8'!$G$8:$G$42=$T8)*'Aug 8'!$AK$8:$AK$42) -> 0 | AC8: =SUMPRODUCT(('Aug 9'!$F$8:$F$42=$T8)*'Aug 9'!$AJ$8:$AJ$42+('Aug 9'!$G$8:$G$42=$T8)*'Aug 9'!$AK$8:$AK$42) -> 0 | AD8: =SUMPRODUCT(('Aug 10'!$F$8:$F$42=$T8)*'Aug 10'!$AJ$8:$AJ$42+('Aug 10'!$G$8:$G$42=$T8)*'Aug 10'!$AK$8:$AK$42) -> 0 | AE8: =SUMPRODUCT(('Aug 11'!$F$8:$F$42=$T8)*'Aug 11'!$AJ$8:$AJ$42+('Aug 11'!$G$8:$G$42=$T8)*'Aug 11'!$AK$8:$AK$42) -> 0 | AF8: =SUMPRODUCT(('Aug 12'!$F$8:$F$42=$T8)*'Aug 12'!$AJ$8:$AJ$42+('Aug 12'!$G$8:$G$42=$T8)*'Aug 12'!$AK$8:$AK$42) -> 0 | AG8: =SUMPRODUCT(('Aug 13'!$F$8:$F$42=$T8)*'Aug 13'!$AJ$8:$AJ$42+('Aug 13'!$G$8:$G$42=$T8)*'Aug 13'!$AK$8:$AK$42) -> 0 | AH8: =SUMPRODUCT(('Aug 14'!$F$8:$F$42=$T8)*'Aug 14'!$AJ$8:$AJ$42+('Aug 14'!$G$8:$G$42=$T8)*'Aug 14'!$AK$8:$AK$42) -> 0 | AI8: =SUMPRODUCT(('Aug 15'!$F$8:$F$42=$T8)*'Aug 15'!$AJ$8:$AJ$42+('Aug 15'!$G$8:$G$42=$T8)*'Aug 15'!$AK$8:$AK$42) -> 0 | AJ8: =SUMPRODUCT(('Aug 16'!$F$8:$F$42=$T8)*'Aug 16'!$AJ$8:$AJ$42+('Aug 16'!$G$8:$G$42=$T8)*'Aug 16'!$AK$8:$AK$42) -> 0 | AK8: =SUMPRODUCT(('Aug 17'!$F$8:$F$42=$T8)*'Aug 17'!$AJ$8:$AJ$42+('Aug 17'!$G$8:$G$42=$T8)*'Aug 17'!$AK$8:$AK$42) -> 0 | AL8: =SUMPRODUCT(('Aug 18'!$F$8:$F$42=$T8)*'Aug 18'!$AJ$8:$AJ$42+('Aug 18'!$G$8:$G$42=$T8)*'Aug 18'!$AK$8:$AK$42) -> 0 | AM8: =SUMPRODUCT(('Aug 19'!$F$8:$F$42=$T8)*'Aug 19'!$AJ$8:$AJ$42+('Aug 19'!$G$8:$G$42=$T8)*'Aug 19'!$AK$8:$AK$42) -> 0 | AN8: =SUMPRODUCT(('Aug 20'!$F$8:$F$42=$T8)*'Aug 20'!$AJ$8:$AJ$42+('Aug 20'!$G$8:$G$42=$T8)*'Aug 20'!$AK$8:$AK$42) -> 0 | AO8: =SUMPRODUCT(('Aug 21'!$F$8:$F$42=$T8)*'Aug 21'!$AJ$8:$AJ$42+('Aug 21'!$G$8:$G$42=$T8)*'Aug 21'!$AK$8:$AK$42) -> 0 | AP8: =SUMPRODUCT(('Aug 22'!$F$8:$F$42=$T8)*'Aug 22'!$AJ$8:$AJ$42+('Aug 22'!$G$8:$G$42=$T8)*'Aug 22'!$AK$8:$AK$42) -> 0 | AQ8: =SUMPRODUCT(('Aug 23'!$F$8:$F$42=$T8)*'Aug 23'!$AJ$8:$AJ$42+('Aug 23'!$G$8:$G$42=$T8)*'Aug 23'!$AK$8:$AK$42) -> 0 | AR8: =SUMPRODUCT(('Aug 24'!$F$8:$F$42=$T8)*'Aug 24'!$AJ$8:$AJ$42+('Aug 24'!$G$8:$G$42=$T8)*'Aug 24'!$AK$8:$AK$42) -> 0 | AS8: =SUMPRODUCT(('Aug 25'!$F$8:$F$42=$T8)*'Aug 25'!$AJ$8:$AJ$42+('Aug 25'!$G$8:$G$42=$T8)*'Aug 25'!$AK$8:$AK$42) -> 0 | AT8: =SUMPRODUCT(('Aug 26'!$F$8:$F$42=$T8)*'Aug 26'!$AJ$8:$AJ$42+('Aug 26'!$G$8:$G$42=$T8)*'Aug 26'!$AK$8:$AK$42) -> 0 | AU8: =SUMPRODUCT(('Aug 27'!$F$8:$F$42=$T8)*'Aug 27'!$AJ$8:$AJ$42+('Aug 27'!$G$8:$G$42=$T8)*'Aug 27'!$AK$8:$AK$42) -> 0 | AV8: =SUMPRODUCT(('Aug 28'!$F$8:$F$42=$T8)*'Aug 28'!$AJ$8:$AJ$42+('Aug 28'!$G$8:$G$42=$T8)*'Aug 28'!$AK$8:$AK$42) -> 0 | AW8: =SUMPRODUCT(('Aug 29'!$F$8:$F$42=$T8)*'Aug 29'!$AJ$8:$AJ$42+('Aug 29'!$G$8:$G$42=$T8)*'Aug 29'!$AK$8:$AK$42) -> 0 | AX8: =SUMPRODUCT(('Aug 30'!$F$8:$F$42=$T8)*'Aug 30'!$AJ$8:$AJ$42+('Aug 30'!$G$8:$G$42=$T8)*'Aug 30'!$AK$8:$AK$42) -> 0 | AY8: =SUMPRODUCT(('Aug 31'!$F$8:$F$42=$T8)*'Aug 31'!$AJ$8:$AJ$42+('Aug 31'!$G$8:$G$42=$T8)*'Aug 31'!$AK$8:$AK$42) -> 0 | BA8: =SUM(U8:AD8) -> 0 | BB8: =MATCH(BD8,'Pay Plan'!$C$6:$C$12,1) -> 1 | BC8: =SUMPRODUCT(('Aug 1'!$F$8:$F$42=$T8)*'Aug 1'!$AI$8:$AI$42*(('Aug 1'!$AM$8:$AM$42="Y")+('Aug 1'!$AN$8:$AN$42="Y")+('Aug 1'!$AO$8:$AO$42="Y")))+SUMPRODUCT(('Aug 2'!$F$8:$F$42=$T8)*'Aug 2'!$AI$8:$AI$42*(('Aug 2'!$AM$8:$AM$42="Y")+('Aug 2'!$AN$8:$AN$42="Y")+('Aug 2'!$AO$8:$AO$42="Y")))+SUMPRODUCT(('Aug 3'!$F$8:$F$42=$T8)*'Aug 3'!$AI$8:$AI$42*(('Aug 3'!$AM$8:$AM$42="Y")+('Aug 3'!$AN$8:$AN$42="Y")+('Aug 3'!$AO$8:$AO$42="Y")))+SUMPRODUCT(('Aug 4'!$F$8:$F$42=$T8)*'Aug 4'!$AI$8:$AI$42*(('Aug 4'!$AM$8:$AM$42="Y")+('Aug 4'!$AN$8:$AN$42="Y")+('Aug 4'!$AO$8:$AO$42="Y")))+SUMPRODUCT(('Aug 5'!$F$8:$F$42=$T8)*'Aug 5'!$AI$8:$AI$42*(('Aug 5'!$AM$8:$AM$42="Y")+('Aug 5'!$AN$8:$AN$42="Y")+('Aug 5'!$AO$8:$AO$42="Y")))+SUMPRODUCT(('Aug 6'!$F$8:$F$42=$T8)*'Aug 6'!$AI$8:$AI$42*(('Aug 6'!$AM$8:$AM$42="Y")+('Aug 6'!$AN$8:$AN$42="Y")+('Aug 6'!$AO$8:$AO$42="Y")))+SUMPRODUCT(('Aug 7'!$F$8:$F$42=$T8)*'Aug 7'!$AI$8:$AI$42*(('Aug 7'!$AM$8:$AM$42="Y")+('Aug 7'!$AN$8:$AN$42="Y")+('Aug 7'!$AO$8:$AO$42="Y")))+SUMPRODUCT(('Aug 8'!$F$8:$F$42=$T8)*'Aug 8'!$AI$8:$AI$42*(('Aug 8'!$AM$8:$AM$42="Y")+('Aug 8'!$AN$8:$AN$42="Y")+('Aug 8'!$AO$8:$AO$42="Y")))+SUMPRODUCT(('Aug 9'!$F$8:$F$42=$T8)*'Aug 9'!$AI$8:$AI$42*(('Aug 9'!$AM$8:$AM$42="Y")+('Aug 9'!$AN$8:$AN$42="Y")+('Aug 9'!$AO$8:$AO$42="Y")))+SUMPRODUCT(('Aug 10'!$F$8:$F$42=$T8)*'Aug 10'!$AI$8:$AI$42*(('Aug 10'!$AM$8:$AM$42="Y")+('Aug 10'!$AN$8:$AN$42="Y")+('Aug 10'!$AO$8:$AO$42="Y")))+SUMPRODUCT(('Aug 11'!$F$8:$F$42=$T8)*'Aug 11'!$AI$8:$AI$42*(('Aug 11'!$AM$8:$AM$42="Y")+('Aug 11'!$AN$8:$AN$42="Y")+('Aug 11'!$AO$8:$AO$42="Y")))+SUMPRODUCT(('Aug 12'!$F$8:$F$42=$T8)*'Aug 12'!$AI$8:$AI$42*(('Aug 12'!$AM$8:$AM$42="Y")+('Aug 12'!$AN$8:$AN$42="Y")+('Aug 12'!$AO$8:$AO$42="Y")))+SUMPRODUCT(('Aug 13'!$F$8:$F$42=$T8)*'Aug 13'!$AI$8:$AI$42*(('Aug 13'!$AM$8:$AM$42="Y")+('Aug 13'!$AN$8:$AN$42="Y")+('Aug 13'!$AO$8:$AO$42="Y")))+SUMPRODUCT(('Aug 14'!$F$8:$F$42=$T8)*'Aug 14'!$AI$8:$AI$42*(('Aug 14'!$AM$8:$AM$42="Y")+('Aug 14'!$AN$8:$AN$42="Y")+('Aug 14'!$AO$8:$AO$42="Y")))+SUMPRODUCT(('Aug 15'!$F$8:$F$42=$T8)*'Aug 15'!$AI$8:$AI$42*(('Aug 15'!$AM$8:$AM$42="Y")+('Aug 15'!$AN$8:$AN$42="Y")+('Aug 15'!$AO$8:$AO$42="Y")))+SUMPRODUCT(('Aug 16'!$F$8:$F$42=$T8)*'Aug 16'!$AI$8:$AI$42*(('Aug 16'!$AM$8:$AM$42="Y")+('Aug 16'!$AN$8:$AN$42="Y")+('Aug 16'!$AO$8:$AO$42="Y")))+SUMPRODUCT(('Aug 17'!$F$8:$F$42=$T8)*'Aug 17'!$AI$8:$AI$42*(('Aug 17'!$AM$8:$AM$42="Y")+('Aug 17'!$AN$8:$AN$42="Y")+('Aug 17'!$AO$8:$AO$42="Y")))+SUMPRODUCT(('Aug 18'!$F$8:$F$42=$T8)*'Aug 18'!$AI$8:$AI$42*(('Aug 18'!$AM$8:$AM$42="Y")+('Aug 18'!$AN$8:$AN$42="Y")+('Aug 18'!$AO$8:$AO$42="Y")))+SUMPRODUCT(('Aug 19'!$F$8:$F$42=$T8)*'Aug 19'!$AI$8:$AI$42*(('Aug 19'!$AM$8:$AM$42="Y")+('Aug 19'!$AN$8:$AN$42="Y")+('Aug 19'!$AO$8:$AO$42="Y")))+SUMPRODUCT(('Aug 20'!$F$8:$F$42=$T8)*'Aug 20'!$AI$8:$AI$42*(('Aug 20'!$AM$8:$AM$42="Y")+('Aug 20'!$AN$8:$AN$42="Y")+('Aug 20'!$AO$8:$AO$42="Y")))+SUMPRODUCT(('Aug 21'!$F$8:$F$42=$T8)*'Aug 21'!$AI$8:$AI$42*(('Aug 21'!$AM$8:$AM$42="Y")+('Aug 21'!$AN$8:$AN$42="Y")+('Aug 21'!$AO$8:$AO$42="Y")))+SUMPRODUCT(('Aug 22'!$F$8:$F$42=$T8)*'Aug 22'!$AI$8:$AI$42*(('Aug 22'!$AM$8:$AM$42="Y")+('Aug 22'!$AN$8:$AN$42="Y")+('Aug 22'!$AO$8:$AO$42="Y")))+SUMPRODUCT(('Aug 23'!$F$8:$F$42=$T8)*'Aug 23'!$AI$8:$AI$42*(('Aug 23'!$AM$8:$AM$42="Y")+('Aug 23'!$AN$8:$AN$42="Y")+('Aug 23'!$AO$8:$AO$42="Y")))+SUMPRODUCT(('Aug 24'!$F$8:$F$42=$T8)*'Aug 24'!$AI$8:$AI$42*(('Aug 24'!$AM$8:$AM$42="Y")+('Aug 24'!$AN$8:$AN$42="Y")+('Aug 24'!$AO$8:$AO$42="Y")))+SUMPRODUCT(('Aug 25'!$F$8:$F$42=$T8)*'Aug 25'!$AI$8:$AI$42*(('Aug 25'!$AM$8:$AM$42="Y")+('Aug 25'!$AN$8:$AN$42="Y")+('Aug 25'!$AO$8:$AO$42="Y")))+SUMPRODUCT(('Aug 26'!$F$8:$F$42=$T8)*'Aug 26'!$AI$8:$AI$42*(('Aug 26'!$AM$8:$AM$42="Y")+('Aug 26'!$AN$8:$AN$42="Y")+('Aug 26'!$AO$8:$AO$42="Y")))+SUMPRODUCT(('Aug 27'!$F$8:$F$42=$T8)*'Aug 27'!$AI$8:$AI$42*(('Aug 27'!$AM$8:$AM$42="Y")+('Aug 27'!$AN$8:$AN$42="Y")+('Aug 27'!$AO$8:$AO$42="Y")))+SUMPRODUCT(('Aug 28'!$F$8:$F$42=$T8)*'Aug 28'!$AI$8:$AI$42*(('Aug 28'!$AM$8:$AM$42="Y")+('Aug 28'!$AN$8:$AN$42="Y")+('Aug 28'!$AO$8:$AO$42="Y")))+SUMPRODUCT(('Aug 29'!$F$8:$F$42=$T8)*'Aug 29'!$AI$8:$AI$42*(('Aug 29'!$AM$8:$AM$42="Y")+('Aug 29'!$AN$8:$AN$42="Y")+('Aug 29'!$AO$8:$AO$42="Y")))+SUMPRODUCT(('Aug 30'!$F$8:$F$42=$T8)*'Aug 30'!$AI$8:$AI$42*(('Aug 30'!$AM$8:$AM$42="Y")+('Aug 30'!$AN$8:$AN$42="Y")+('Aug 30'!$AO$8:$AO$42="Y")))+SUMPRODUCT(('Aug 31'!$F$8:$F$42=$T8)*'Aug 31'!$AI$8:$AI$42*(('Aug 31'!$AM$8:$AM$42="Y")+('Aug 31'!$AN$8:$AN$42="Y")+('Aug 31'!$AO$8:$AO$42="Y"))) -> 0 | BD8: =SUM(U8:AY8) -> 0 | BE8: =SUM(U27:AY27) -> 0 | BF8: =SUM(U46:AY46) -> 0 | BH8: =SUMPRODUCT((BD4:BD19>0)*(BB4:BB19<1)) -> 0
A9: 3 | B9: =$T6 -> RICH AMMERMAN | C9: =BD6 -> 0 | D9: =BE6 -> 0 | E9: =IF(BD6=0,"—",BE6/BD6) -> — | F9: =IF(BD6=0,"—",INDEX('Pay Plan'!$B$6:$B$12,BB6)) -> — | G9: =BF6 -> 0 | H9: =LOOKUP(BD6,'Pay Plan'!$B$15:$B$20,'Pay Plan'!$C$15:$C$20) -> 0 | I9: =LOOKUP(BA6,'Pay Plan'!$E$15:$E$19,'Pay Plan'!$F$15:$F$19) -> 0 | J9: =BC6*'Pay Plan'!$I$15 -> 0 | K9: =G9+H9+I9+J9 -> 0 | O9: =K9-N9 -> 0 | T9: ='Staff & Lists'!A10 -> ZAY JOHNSON | U9: =SUMPRODUCT(('Aug 1'!$F$8:$F$42=$T9)*'Aug 1'!$AJ$8:$AJ$42+('Aug 1'!$G$8:$G$42=$T9)*'Aug 1'!$AK$8:$AK$42) -> 0 | V9: =SUMPRODUCT(('Aug 2'!$F$8:$F$42=$T9)*'Aug 2'!$AJ$8:$AJ$42+('Aug 2'!$G$8:$G$42=$T9)*'Aug 2'!$AK$8:$AK$42) -> 0 | W9: =SUMPRODUCT(('Aug 3'!$F$8:$F$42=$T9)*'Aug 3'!$AJ$8:$AJ$42+('Aug 3'!$G$8:$G$42=$T9)*'Aug 3'!$AK$8:$AK$42) -> 0 | X9: =SUMPRODUCT(('Aug 4'!$F$8:$F$42=$T9)*'Aug 4'!$AJ$8:$AJ$42+('Aug 4'!$G$8:$G$42=$T9)*'Aug 4'!$AK$8:$AK$42) -> 0 | Y9: =SUMPRODUCT(('Aug 5'!$F$8:$F$42=$T9)*'Aug 5'!$AJ$8:$AJ$42+('Aug 5'!$G$8:$G$42=$T9)*'Aug 5'!$AK$8:$AK$42) -> 0 | Z9: =SUMPRODUCT(('Aug 6'!$F$8:$F$42=$T9)*'Aug 6'!$AJ$8:$AJ$42+('Aug 6'!$G$8:$G$42=$T9)*'Aug 6'!$AK$8:$AK$42) -> 0 | AA9: =SUMPRODUCT(('Aug 7'!$F$8:$F$42=$T9)*'Aug 7'!$AJ$8:$AJ$42+('Aug 7'!$G$8:$G$42=$T9)*'Aug 7'!$AK$8:$AK$42) -> 0 | AB9: =SUMPRODUCT(('Aug 8'!$F$8:$F$42=$T9)*'Aug 8'!$AJ$8:$AJ$42+('Aug 8'!$G$8:$G$42=$T9)*'Aug 8'!$AK$8:$AK$42) -> 0 | AC9: =SUMPRODUCT(('Aug 9'!$F$8:$F$42=$T9)*'Aug 9'!$AJ$8:$AJ$42+('Aug 9'!$G$8:$G$42=$T9)*'Aug 9'!$AK$8:$AK$42) -> 0 | AD9: =SUMPRODUCT(('Aug 10'!$F$8:$F$42=$T9)*'Aug 10'!$AJ$8:$AJ$42+('Aug 10'!$G$8:$G$42=$T9)*'Aug 10'!$AK$8:$AK$42) -> 0 | AE9: =SUMPRODUCT(('Aug 11'!$F$8:$F$42=$T9)*'Aug 11'!$AJ$8:$AJ$42+('Aug 11'!$G$8:$G$42=$T9)*'Aug 11'!$AK$8:$AK$42) -> 0 | AF9: =SUMPRODUCT(('Aug 12'!$F$8:$F$42=$T9)*'Aug 12'!$AJ$8:$AJ$42+('Aug 12'!$G$8:$G$42=$T9)*'Aug 12'!$AK$8:$AK$42) -> 0 | AG9: =SUMPRODUCT(('Aug 13'!$F$8:$F$42=$T9)*'Aug 13'!$AJ$8:$AJ$42+('Aug 13'!$G$8:$G$42=$T9)*'Aug 13'!$AK$8:$AK$42) -> 0 | AH9: =SUMPRODUCT(('Aug 14'!$F$8:$F$42=$T9)*'Aug 14'!$AJ$8:$AJ$42+('Aug 14'!$G$8:$G$42=$T9)*'Aug 14'!$AK$8:$AK$42) -> 0 | AI9: =SUMPRODUCT(('Aug 15'!$F$8:$F$42=$T9)*'Aug 15'!$AJ$8:$AJ$42+('Aug 15'!$G$8:$G$42=$T9)*'Aug 15'!$AK$8:$AK$42) -> 0 | AJ9: =SUMPRODUCT(('Aug 16'!$F$8:$F$42=$T9)*'Aug 16'!$AJ$8:$AJ$42+('Aug 16'!$G$8:$G$42=$T9)*'Aug 16'!$AK$8:$AK$42) -> 0 | AK9: =SUMPRODUCT(('Aug 17'!$F$8:$F$42=$T9)*'Aug 17'!$AJ$8:$AJ$42+('Aug 17'!$G$8:$G$42=$T9)*'Aug 17'!$AK$8:$AK$42) -> 0 | AL9: =SUMPRODUCT(('Aug 18'!$F$8:$F$42=$T9)*'Aug 18'!$AJ$8:$AJ$42+('Aug 18'!$G$8:$G$42=$T9)*'Aug 18'!$AK$8:$AK$42) -> 0 | AM9: =SUMPRODUCT(('Aug 19'!$F$8:$F$42=$T9)*'Aug 19'!$AJ$8:$AJ$42+('Aug 19'!$G$8:$G$42=$T9)*'Aug 19'!$AK$8:$AK$42) -> 0 | AN9: =SUMPRODUCT(('Aug 20'!$F$8:$F$42=$T9)*'Aug 20'!$AJ$8:$AJ$42+('Aug 20'!$G$8:$G$42=$T9)*'Aug 20'!$AK$8:$AK$42) -> 0 | AO9: =SUMPRODUCT(('Aug 21'!$F$8:$F$42=$T9)*'Aug 21'!$AJ$8:$AJ$42+('Aug 21'!$G$8:$G$42=$T9)*'Aug 21'!$AK$8:$AK$42) -> 0 | AP9: =SUMPRODUCT(('Aug 22'!$F$8:$F$42=$T9)*'Aug 22'!$AJ$8:$AJ$42+('Aug 22'!$G$8:$G$42=$T9)*'Aug 22'!$AK$8:$AK$42) -> 0 | AQ9: =SUMPRODUCT(('Aug 23'!$F$8:$F$42=$T9)*'Aug 23'!$AJ$8:$AJ$42+('Aug 23'!$G$8:$G$42=$T9)*'Aug 23'!$AK$8:$AK$42) -> 0 | AR9: =SUMPRODUCT(('Aug 24'!$F$8:$F$42=$T9)*'Aug 24'!$AJ$8:$AJ$42+('Aug 24'!$G$8:$G$42=$T9)*'Aug 24'!$AK$8:$AK$42) -> 0 | AS9: =SUMPRODUCT(('Aug 25'!$F$8:$F$42=$T9)*'Aug 25'!$AJ$8:$AJ$42+('Aug 25'!$G$8:$G$42=$T9)*'Aug 25'!$AK$8:$AK$42) -> 0 | AT9: =SUMPRODUCT(('Aug 26'!$F$8:$F$42=$T9)*'Aug 26'!$AJ$8:$AJ$42+('Aug 26'!$G$8:$G$42=$T9)*'Aug 26'!$AK$8:$AK$42) -> 0 | AU9: =SUMPRODUCT(('Aug 27'!$F$8:$F$42=$T9)*'Aug 27'!$AJ$8:$AJ$42+('Aug 27'!$G$8:$G$42=$T9)*'Aug 27'!$AK$8:$AK$42) -> 0 | AV9: =SUMPRODUCT(('Aug 28'!$F$8:$F$42=$T9)*'Aug 28'!$AJ$8:$AJ$42+('Aug 28'!$G$8:$G$42=$T9)*'Aug 28'!$AK$8:$AK$42) -> 0 | AW9: =SUMPRODUCT(('Aug 29'!$F$8:$F$42=$T9)*'Aug 29'!$AJ$8:$AJ$42+('Aug 29'!$G$8:$G$42=$T9)*'Aug 29'!$AK$8:$AK$42) -> 0 | AX9: =SUMPRODUCT(('Aug 30'!$F$8:$F$42=$T9)*'Aug 30'!$AJ$8:$AJ$42+('Aug 30'!$G$8:$G$42=$T9)*'Aug 30'!$AK$8:$AK$42) -> 0 | AY9: =SUMPRODUCT(('Aug 31'!$F$8:$F$42=$T9)*'Aug 31'!$AJ$8:$AJ$42+('Aug 31'!$G$8:$G$42=$T9)*'Aug 31'!$AK$8:$AK$42) -> 0 | BA9: =SUM(U9:AD9) -> 0 | BB9: =MATCH(BD9,'Pay Plan'!$C$6:$C$12,1) -> 1 | BC9: =SUMPRODUCT(('Aug 1'!$F$8:$F$42=$T9)*'Aug 1'!$AI$8:$AI$42*(('Aug 1'!$AM$8:$AM$42="Y")+('Aug 1'!$AN$8:$AN$42="Y")+('Aug 1'!$AO$8:$AO$42="Y")))+SUMPRODUCT(('Aug 2'!$F$8:$F$42=$T9)*'Aug 2'!$AI$8:$AI$42*(('Aug 2'!$AM$8:$AM$42="Y")+('Aug 2'!$AN$8:$AN$42="Y")+('Aug 2'!$AO$8:$AO$42="Y")))+SUMPRODUCT(('Aug 3'!$F$8:$F$42=$T9)*'Aug 3'!$AI$8:$AI$42*(('Aug 3'!$AM$8:$AM$42="Y")+('Aug 3'!$AN$8:$AN$42="Y")+('Aug 3'!$AO$8:$AO$42="Y")))+SUMPRODUCT(('Aug 4'!$F$8:$F$42=$T9)*'Aug 4'!$AI$8:$AI$42*(('Aug 4'!$AM$8:$AM$42="Y")+('Aug 4'!$AN$8:$AN$42="Y")+('Aug 4'!$AO$8:$AO$42="Y")))+SUMPRODUCT(('Aug 5'!$F$8:$F$42=$T9)*'Aug 5'!$AI$8:$AI$42*(('Aug 5'!$AM$8:$AM$42="Y")+('Aug 5'!$AN$8:$AN$42="Y")+('Aug 5'!$AO$8:$AO$42="Y")))+SUMPRODUCT(('Aug 6'!$F$8:$F$42=$T9)*'Aug 6'!$AI$8:$AI$42*(('Aug 6'!$AM$8:$AM$42="Y")+('Aug 6'!$AN$8:$AN$42="Y")+('Aug 6'!$AO$8:$AO$42="Y")))+SUMPRODUCT(('Aug 7'!$F$8:$F$42=$T9)*'Aug 7'!$AI$8:$AI$42*(('Aug 7'!$AM$8:$AM$42="Y")+('Aug 7'!$AN$8:$AN$42="Y")+('Aug 7'!$AO$8:$AO$42="Y")))+SUMPRODUCT(('Aug 8'!$F$8:$F$42=$T9)*'Aug 8'!$AI$8:$AI$42*(('Aug 8'!$AM$8:$AM$42="Y")+('Aug 8'!$AN$8:$AN$42="Y")+('Aug 8'!$AO$8:$AO$42="Y")))+SUMPRODUCT(('Aug 9'!$F$8:$F$42=$T9)*'Aug 9'!$AI$8:$AI$42*(('Aug 9'!$AM$8:$AM$42="Y")+('Aug 9'!$AN$8:$AN$42="Y")+('Aug 9'!$AO$8:$AO$42="Y")))+SUMPRODUCT(('Aug 10'!$F$8:$F$42=$T9)*'Aug 10'!$AI$8:$AI$42*(('Aug 10'!$AM$8:$AM$42="Y")+('Aug 10'!$AN$8:$AN$42="Y")+('Aug 10'!$AO$8:$AO$42="Y")))+SUMPRODUCT(('Aug 11'!$F$8:$F$42=$T9)*'Aug 11'!$AI$8:$AI$42*(('Aug 11'!$AM$8:$AM$42="Y")+('Aug 11'!$AN$8:$AN$42="Y")+('Aug 11'!$AO$8:$AO$42="Y")))+SUMPRODUCT(('Aug 12'!$F$8:$F$42=$T9)*'Aug 12'!$AI$8:$AI$42*(('Aug 12'!$AM$8:$AM$42="Y")+('Aug 12'!$AN$8:$AN$42="Y")+('Aug 12'!$AO$8:$AO$42="Y")))+SUMPRODUCT(('Aug 13'!$F$8:$F$42=$T9)*'Aug 13'!$AI$8:$AI$42*(('Aug 13'!$AM$8:$AM$42="Y")+('Aug 13'!$AN$8:$AN$42="Y")+('Aug 13'!$AO$8:$AO$42="Y")))+SUMPRODUCT(('Aug 14'!$F$8:$F$42=$T9)*'Aug 14'!$AI$8:$AI$42*(('Aug 14'!$AM$8:$AM$42="Y")+('Aug 14'!$AN$8:$AN$42="Y")+('Aug 14'!$AO$8:$AO$42="Y")))+SUMPRODUCT(('Aug 15'!$F$8:$F$42=$T9)*'Aug 15'!$AI$8:$AI$42*(('Aug 15'!$AM$8:$AM$42="Y")+('Aug 15'!$AN$8:$AN$42="Y")+('Aug 15'!$AO$8:$AO$42="Y")))+SUMPRODUCT(('Aug 16'!$F$8:$F$42=$T9)*'Aug 16'!$AI$8:$AI$42*(('Aug 16'!$AM$8:$AM$42="Y")+('Aug 16'!$AN$8:$AN$42="Y")+('Aug 16'!$AO$8:$AO$42="Y")))+SUMPRODUCT(('Aug 17'!$F$8:$F$42=$T9)*'Aug 17'!$AI$8:$AI$42*(('Aug 17'!$AM$8:$AM$42="Y")+('Aug 17'!$AN$8:$AN$42="Y")+('Aug 17'!$AO$8:$AO$42="Y")))+SUMPRODUCT(('Aug 18'!$F$8:$F$42=$T9)*'Aug 18'!$AI$8:$AI$42*(('Aug 18'!$AM$8:$AM$42="Y")+('Aug 18'!$AN$8:$AN$42="Y")+('Aug 18'!$AO$8:$AO$42="Y")))+SUMPRODUCT(('Aug 19'!$F$8:$F$42=$T9)*'Aug 19'!$AI$8:$AI$42*(('Aug 19'!$AM$8:$AM$42="Y")+('Aug 19'!$AN$8:$AN$42="Y")+('Aug 19'!$AO$8:$AO$42="Y")))+SUMPRODUCT(('Aug 20'!$F$8:$F$42=$T9)*'Aug 20'!$AI$8:$AI$42*(('Aug 20'!$AM$8:$AM$42="Y")+('Aug 20'!$AN$8:$AN$42="Y")+('Aug 20'!$AO$8:$AO$42="Y")))+SUMPRODUCT(('Aug 21'!$F$8:$F$42=$T9)*'Aug 21'!$AI$8:$AI$42*(('Aug 21'!$AM$8:$AM$42="Y")+('Aug 21'!$AN$8:$AN$42="Y")+('Aug 21'!$AO$8:$AO$42="Y")))+SUMPRODUCT(('Aug 22'!$F$8:$F$42=$T9)*'Aug 22'!$AI$8:$AI$42*(('Aug 22'!$AM$8:$AM$42="Y")+('Aug 22'!$AN$8:$AN$42="Y")+('Aug 22'!$AO$8:$AO$42="Y")))+SUMPRODUCT(('Aug 23'!$F$8:$F$42=$T9)*'Aug 23'!$AI$8:$AI$42*(('Aug 23'!$AM$8:$AM$42="Y")+('Aug 23'!$AN$8:$AN$42="Y")+('Aug 23'!$AO$8:$AO$42="Y")))+SUMPRODUCT(('Aug 24'!$F$8:$F$42=$T9)*'Aug 24'!$AI$8:$AI$42*(('Aug 24'!$AM$8:$AM$42="Y")+('Aug 24'!$AN$8:$AN$42="Y")+('Aug 24'!$AO$8:$AO$42="Y")))+SUMPRODUCT(('Aug 25'!$F$8:$F$42=$T9)*'Aug 25'!$AI$8:$AI$42*(('Aug 25'!$AM$8:$AM$42="Y")+('Aug 25'!$AN$8:$AN$42="Y")+('Aug 25'!$AO$8:$AO$42="Y")))+SUMPRODUCT(('Aug 26'!$F$8:$F$42=$T9)*'Aug 26'!$AI$8:$AI$42*(('Aug 26'!$AM$8:$AM$42="Y")+('Aug 26'!$AN$8:$AN$42="Y")+('Aug 26'!$AO$8:$AO$42="Y")))+SUMPRODUCT(('Aug 27'!$F$8:$F$42=$T9)*'Aug 27'!$AI$8:$AI$42*(('Aug 27'!$AM$8:$AM$42="Y")+('Aug 27'!$AN$8:$AN$42="Y")+('Aug 27'!$AO$8:$AO$42="Y")))+SUMPRODUCT(('Aug 28'!$F$8:$F$42=$T9)*'Aug 28'!$AI$8:$AI$42*(('Aug 28'!$AM$8:$AM$42="Y")+('Aug 28'!$AN$8:$AN$42="Y")+('Aug 28'!$AO$8:$AO$42="Y")))+SUMPRODUCT(('Aug 29'!$F$8:$F$42=$T9)*'Aug 29'!$AI$8:$AI$42*(('Aug 29'!$AM$8:$AM$42="Y")+('Aug 29'!$AN$8:$AN$42="Y")+('Aug 29'!$AO$8:$AO$42="Y")))+SUMPRODUCT(('Aug 30'!$F$8:$F$42=$T9)*'Aug 30'!$AI$8:$AI$42*(('Aug 30'!$AM$8:$AM$42="Y")+('Aug 30'!$AN$8:$AN$42="Y")+('Aug 30'!$AO$8:$AO$42="Y")))+SUMPRODUCT(('Aug 31'!$F$8:$F$42=$T9)*'Aug 31'!$AI$8:$AI$42*(('Aug 31'!$AM$8:$AM$42="Y")+('Aug 31'!$AN$8:$AN$42="Y")+('Aug 31'!$AO$8:$AO$42="Y"))) -> 0 | BD9: =SUM(U9:AY9) -> 0 | BE9: =SUM(U28:AY28) -> 0 | BF9: =SUM(U47:AY47) -> 0
A10: 4 | B10: =$T7 -> GARRET SCHWETTMAN | C10: =BD7 -> 0 | D10: =BE7 -> 0 | E10: =IF(BD7=0,"—",BE7/BD7) -> — | F10: =IF(BD7=0,"—",INDEX('Pay Plan'!$B$6:$B$12,BB7)) -> — | G10: =BF7 -> 0 | H10: =LOOKUP(BD7,'Pay Plan'!$B$15:$B$20,'Pay Plan'!$C$15:$C$20) -> 0 | I10: =LOOKUP(BA7,'Pay Plan'!$E$15:$E$19,'Pay Plan'!$F$15:$F$19) -> 0 | J10: =BC7*'Pay Plan'!$I$15 -> 0 | K10: =G10+H10+I10+J10 -> 0 | O10: =K10-N10 -> 0 | T10: ='Staff & Lists'!A11 -> JUSTIN ROLLER | U10: =SUMPRODUCT(('Aug 1'!$F$8:$F$42=$T10)*'Aug 1'!$AJ$8:$AJ$42+('Aug 1'!$G$8:$G$42=$T10)*'Aug 1'!$AK$8:$AK$42) -> 0 | V10: =SUMPRODUCT(('Aug 2'!$F$8:$F$42=$T10)*'Aug 2'!$AJ$8:$AJ$42+('Aug 2'!$G$8:$G$42=$T10)*'Aug 2'!$AK$8:$AK$42) -> 0 | W10: =SUMPRODUCT(('Aug 3'!$F$8:$F$42=$T10)*'Aug 3'!$AJ$8:$AJ$42+('Aug 3'!$G$8:$G$42=$T10)*'Aug 3'!$AK$8:$AK$42) -> 0 | X10: =SUMPRODUCT(('Aug 4'!$F$8:$F$42=$T10)*'Aug 4'!$AJ$8:$AJ$42+('Aug 4'!$G$8:$G$42=$T10)*'Aug 4'!$AK$8:$AK$42) -> 0 | Y10: =SUMPRODUCT(('Aug 5'!$F$8:$F$42=$T10)*'Aug 5'!$AJ$8:$AJ$42+('Aug 5'!$G$8:$G$42=$T10)*'Aug 5'!$AK$8:$AK$42) -> 0 | Z10: =SUMPRODUCT(('Aug 6'!$F$8:$F$42=$T10)*'Aug 6'!$AJ$8:$AJ$42+('Aug 6'!$G$8:$G$42=$T10)*'Aug 6'!$AK$8:$AK$42) -> 0 | AA10: =SUMPRODUCT(('Aug 7'!$F$8:$F$42=$T10)*'Aug 7'!$AJ$8:$AJ$42+('Aug 7'!$G$8:$G$42=$T10)*'Aug 7'!$AK$8:$AK$42) -> 0 | AB10: =SUMPRODUCT(('Aug 8'!$F$8:$F$42=$T10)*'Aug 8'!$AJ$8:$AJ$42+('Aug 8'!$G$8:$G$42=$T10)*'Aug 8'!$AK$8:$AK$42) -> 0 | AC10: =SUMPRODUCT(('Aug 9'!$F$8:$F$42=$T10)*'Aug 9'!$AJ$8:$AJ$42+('Aug 9'!$G$8:$G$42=$T10)*'Aug 9'!$AK$8:$AK$42) -> 0 | AD10: =SUMPRODUCT(('Aug 10'!$F$8:$F$42=$T10)*'Aug 10'!$AJ$8:$AJ$42+('Aug 10'!$G$8:$G$42=$T10)*'Aug 10'!$AK$8:$AK$42) -> 0 | AE10: =SUMPRODUCT(('Aug 11'!$F$8:$F$42=$T10)*'Aug 11'!$AJ$8:$AJ$42+('Aug 11'!$G$8:$G$42=$T10)*'Aug 11'!$AK$8:$AK$42) -> 0 | AF10: =SUMPRODUCT(('Aug 12'!$F$8:$F$42=$T10)*'Aug 12'!$AJ$8:$AJ$42+('Aug 12'!$G$8:$G$42=$T10)*'Aug 12'!$AK$8:$AK$42) -> 0 | AG10: =SUMPRODUCT(('Aug 13'!$F$8:$F$42=$T10)*'Aug 13'!$AJ$8:$AJ$42+('Aug 13'!$G$8:$G$42=$T10)*'Aug 13'!$AK$8:$AK$42) -> 0 | AH10: =SUMPRODUCT(('Aug 14'!$F$8:$F$42=$T10)*'Aug 14'!$AJ$8:$AJ$42+('Aug 14'!$G$8:$G$42=$T10)*'Aug 14'!$AK$8:$AK$42) -> 0 | AI10: =SUMPRODUCT(('Aug 15'!$F$8:$F$42=$T10)*'Aug 15'!$AJ$8:$AJ$42+('Aug 15'!$G$8:$G$42=$T10)*'Aug 15'!$AK$8:$AK$42) -> 0 | AJ10: =SUMPRODUCT(('Aug 16'!$F$8:$F$42=$T10)*'Aug 16'!$AJ$8:$AJ$42+('Aug 16'!$G$8:$G$42=$T10)*'Aug 16'!$AK$8:$AK$42) -> 0 | AK10: =SUMPRODUCT(('Aug 17'!$F$8:$F$42=$T10)*'Aug 17'!$AJ$8:$AJ$42+('Aug 17'!$G$8:$G$42=$T10)*'Aug 17'!$AK$8:$AK$42) -> 0 | AL10: =SUMPRODUCT(('Aug 18'!$F$8:$F$42=$T10)*'Aug 18'!$AJ$8:$AJ$42+('Aug 18'!$G$8:$G$42=$T10)*'Aug 18'!$AK$8:$AK$42) -> 0 | AM10: =SUMPRODUCT(('Aug 19'!$F$8:$F$42=$T10)*'Aug 19'!$AJ$8:$AJ$42+('Aug 19'!$G$8:$G$42=$T10)*'Aug 19'!$AK$8:$AK$42) -> 0 | AN10: =SUMPRODUCT(('Aug 20'!$F$8:$F$42=$T10)*'Aug 20'!$AJ$8:$AJ$42+('Aug 20'!$G$8:$G$42=$T10)*'Aug 20'!$AK$8:$AK$42) -> 0 | AO10: =SUMPRODUCT(('Aug 21'!$F$8:$F$42=$T10)*'Aug 21'!$AJ$8:$AJ$42+('Aug 21'!$G$8:$G$42=$T10)*'Aug 21'!$AK$8:$AK$42) -> 0 | AP10: =SUMPRODUCT(('Aug 22'!$F$8:$F$42=$T10)*'Aug 22'!$AJ$8:$AJ$42+('Aug 22'!$G$8:$G$42=$T10)*'Aug 22'!$AK$8:$AK$42) -> 0 | AQ10: =SUMPRODUCT(('Aug 23'!$F$8:$F$42=$T10)*'Aug 23'!$AJ$8:$AJ$42+('Aug 23'!$G$8:$G$42=$T10)*'Aug 23'!$AK$8:$AK$42) -> 0 | AR10: =SUMPRODUCT(('Aug 24'!$F$8:$F$42=$T10)*'Aug 24'!$AJ$8:$AJ$42+('Aug 24'!$G$8:$G$42=$T10)*'Aug 24'!$AK$8:$AK$42) -> 0 | AS10: =SUMPRODUCT(('Aug 25'!$F$8:$F$42=$T10)*'Aug 25'!$AJ$8:$AJ$42+('Aug 25'!$G$8:$G$42=$T10)*'Aug 25'!$AK$8:$AK$42) -> 0 | AT10: =SUMPRODUCT(('Aug 26'!$F$8:$F$42=$T10)*'Aug 26'!$AJ$8:$AJ$42+('Aug 26'!$G$8:$G$42=$T10)*'Aug 26'!$AK$8:$AK$42) -> 0 | AU10: =SUMPRODUCT(('Aug 27'!$F$8:$F$42=$T10)*'Aug 27'!$AJ$8:$AJ$42+('Aug 27'!$G$8:$G$42=$T10)*'Aug 27'!$AK$8:$AK$42) -> 0 | AV10: =SUMPRODUCT(('Aug 28'!$F$8:$F$42=$T10)*'Aug 28'!$AJ$8:$AJ$42+('Aug 28'!$G$8:$G$42=$T10)*'Aug 28'!$AK$8:$AK$42) -> 0 | AW10: =SUMPRODUCT(('Aug 29'!$F$8:$F$42=$T10)*'Aug 29'!$AJ$8:$AJ$42+('Aug 29'!$G$8:$G$42=$T10)*'Aug 29'!$AK$8:$AK$42) -> 0 | AX10: =SUMPRODUCT(('Aug 30'!$F$8:$F$42=$T10)*'Aug 30'!$AJ$8:$AJ$42+('Aug 30'!$G$8:$G$42=$T10)*'Aug 30'!$AK$8:$AK$42) -> 0 | AY10: =SUMPRODUCT(('Aug 31'!$F$8:$F$42=$T10)*'Aug 31'!$AJ$8:$AJ$42+('Aug 31'!$G$8:$G$42=$T10)*'Aug 31'!$AK$8:$AK$42) -> 0 | BA10: =SUM(U10:AD10) -> 0 | BB10: =MATCH(BD10,'Pay Plan'!$C$6:$C$12,1) -> 1 | BC10: =SUMPRODUCT(('Aug 1'!$F$8:$F$42=$T10)*'Aug 1'!$AI$8:$AI$42*(('Aug 1'!$AM$8:$AM$42="Y")+('Aug 1'!$AN$8:$AN$42="Y")+('Aug 1'!$AO$8:$AO$42="Y")))+SUMPRODUCT(('Aug 2'!$F$8:$F$42=$T10)*'Aug 2'!$AI$8:$AI$42*(('Aug 2'!$AM$8:$AM$42="Y")+('Aug 2'!$AN$8:$AN$42="Y")+('Aug 2'!$AO$8:$AO$42="Y")))+SUMPRODUCT(('Aug 3'!$F$8:$F$42=$T10)*'Aug 3'!$AI$8:$AI$42*(('Aug 3'!$AM$8:$AM$42="Y")+('Aug 3'!$AN$8:$AN$42="Y")+('Aug 3'!$AO$8:$AO$42="Y")))+SUMPRODUCT(('Aug 4'!$F$8:$F$42=$T10)*'Aug 4'!$AI$8:$AI$42*(('Aug 4'!$AM$8:$AM$42="Y")+('Aug 4'!$AN$8:$AN$42="Y")+('Aug 4'!$AO$8:$AO$42="Y")))+SUMPRODUCT(('Aug 5'!$F$8:$F$42=$T10)*'Aug 5'!$AI$8:$AI$42*(('Aug 5'!$AM$8:$AM$42="Y")+('Aug 5'!$AN$8:$AN$42="Y")+('Aug 5'!$AO$8:$AO$42="Y")))+SUMPRODUCT(('Aug 6'!$F$8:$F$42=$T10)*'Aug 6'!$AI$8:$AI$42*(('Aug 6'!$AM$8:$AM$42="Y")+('Aug 6'!$AN$8:$AN$42="Y")+('Aug 6'!$AO$8:$AO$42="Y")))+SUMPRODUCT(('Aug 7'!$F$8:$F$42=$T10)*'Aug 7'!$AI$8:$AI$42*(('Aug 7'!$AM$8:$AM$42="Y")+('Aug 7'!$AN$8:$AN$42="Y")+('Aug 7'!$AO$8:$AO$42="Y")))+SUMPRODUCT(('Aug 8'!$F$8:$F$42=$T10)*'Aug 8'!$AI$8:$AI$42*(('Aug 8'!$AM$8:$AM$42="Y")+('Aug 8'!$AN$8:$AN$42="Y")+('Aug 8'!$AO$8:$AO$42="Y")))+SUMPRODUCT(('Aug 9'!$F$8:$F$42=$T10)*'Aug 9'!$AI$8:$AI$42*(('Aug 9'!$AM$8:$AM$42="Y")+('Aug 9'!$AN$8:$AN$42="Y")+('Aug 9'!$AO$8:$AO$42="Y")))+SUMPRODUCT(('Aug 10'!$F$8:$F$42=$T10)*'Aug 10'!$AI$8:$AI$42*(('Aug 10'!$AM$8:$AM$42="Y")+('Aug 10'!$AN$8:$AN$42="Y")+('Aug 10'!$AO$8:$AO$42="Y")))+SUMPRODUCT(('Aug 11'!$F$8:$F$42=$T10)*'Aug 11'!$AI$8:$AI$42*(('Aug 11'!$AM$8:$AM$42="Y")+('Aug 11'!$AN$8:$AN$42="Y")+('Aug 11'!$AO$8:$AO$42="Y")))+SUMPRODUCT(('Aug 12'!$F$8:$F$42=$T10)*'Aug 12'!$AI$8:$AI$42*(('Aug 12'!$AM$8:$AM$42="Y")+('Aug 12'!$AN$8:$AN$42="Y")+('Aug 12'!$AO$8:$AO$42="Y")))+SUMPRODUCT(('Aug 13'!$F$8:$F$42=$T10)*'Aug 13'!$AI$8:$AI$42*(('Aug 13'!$AM$8:$AM$42="Y")+('Aug 13'!$AN$8:$AN$42="Y")+('Aug 13'!$AO$8:$AO$42="Y")))+SUMPRODUCT(('Aug 14'!$F$8:$F$42=$T10)*'Aug 14'!$AI$8:$AI$42*(('Aug 14'!$AM$8:$AM$42="Y")+('Aug 14'!$AN$8:$AN$42="Y")+('Aug 14'!$AO$8:$AO$42="Y")))+SUMPRODUCT(('Aug 15'!$F$8:$F$42=$T10)*'Aug 15'!$AI$8:$AI$42*(('Aug 15'!$AM$8:$AM$42="Y")+('Aug 15'!$AN$8:$AN$42="Y")+('Aug 15'!$AO$8:$AO$42="Y")))+SUMPRODUCT(('Aug 16'!$F$8:$F$42=$T10)*'Aug 16'!$AI$8:$AI$42*(('Aug 16'!$AM$8:$AM$42="Y")+('Aug 16'!$AN$8:$AN$42="Y")+('Aug 16'!$AO$8:$AO$42="Y")))+SUMPRODUCT(('Aug 17'!$F$8:$F$42=$T10)*'Aug 17'!$AI$8:$AI$42*(('Aug 17'!$AM$8:$AM$42="Y")+('Aug 17'!$AN$8:$AN$42="Y")+('Aug 17'!$AO$8:$AO$42="Y")))+SUMPRODUCT(('Aug 18'!$F$8:$F$42=$T10)*'Aug 18'!$AI$8:$AI$42*(('Aug 18'!$AM$8:$AM$42="Y")+('Aug 18'!$AN$8:$AN$42="Y")+('Aug 18'!$AO$8:$AO$42="Y")))+SUMPRODUCT(('Aug 19'!$F$8:$F$42=$T10)*'Aug 19'!$AI$8:$AI$42*(('Aug 19'!$AM$8:$AM$42="Y")+('Aug 19'!$AN$8:$AN$42="Y")+('Aug 19'!$AO$8:$AO$42="Y")))+SUMPRODUCT(('Aug 20'!$F$8:$F$42=$T10)*'Aug 20'!$AI$8:$AI$42*(('Aug 20'!$AM$8:$AM$42="Y")+('Aug 20'!$AN$8:$AN$42="Y")+('Aug 20'!$AO$8:$AO$42="Y")))+SUMPRODUCT(('Aug 21'!$F$8:$F$42=$T10)*'Aug 21'!$AI$8:$AI$42*(('Aug 21'!$AM$8:$AM$42="Y")+('Aug 21'!$AN$8:$AN$42="Y")+('Aug 21'!$AO$8:$AO$42="Y")))+SUMPRODUCT(('Aug 22'!$F$8:$F$42=$T10)*'Aug 22'!$AI$8:$AI$42*(('Aug 22'!$AM$8:$AM$42="Y")+('Aug 22'!$AN$8:$AN$42="Y")+('Aug 22'!$AO$8:$AO$42="Y")))+SUMPRODUCT(('Aug 23'!$F$8:$F$42=$T10)*'Aug 23'!$AI$8:$AI$42*(('Aug 23'!$AM$8:$AM$42="Y")+('Aug 23'!$AN$8:$AN$42="Y")+('Aug 23'!$AO$8:$AO$42="Y")))+SUMPRODUCT(('Aug 24'!$F$8:$F$42=$T10)*'Aug 24'!$AI$8:$AI$42*(('Aug 24'!$AM$8:$AM$42="Y")+('Aug 24'!$AN$8:$AN$42="Y")+('Aug 24'!$AO$8:$AO$42="Y")))+SUMPRODUCT(('Aug 25'!$F$8:$F$42=$T10)*'Aug 25'!$AI$8:$AI$42*(('Aug 25'!$AM$8:$AM$42="Y")+('Aug 25'!$AN$8:$AN$42="Y")+('Aug 25'!$AO$8:$AO$42="Y")))+SUMPRODUCT(('Aug 26'!$F$8:$F$42=$T10)*'Aug 26'!$AI$8:$AI$42*(('Aug 26'!$AM$8:$AM$42="Y")+('Aug 26'!$AN$8:$AN$42="Y")+('Aug 26'!$AO$8:$AO$42="Y")))+SUMPRODUCT(('Aug 27'!$F$8:$F$42=$T10)*'Aug 27'!$AI$8:$AI$42*(('Aug 27'!$AM$8:$AM$42="Y")+('Aug 27'!$AN$8:$AN$42="Y")+('Aug 27'!$AO$8:$AO$42="Y")))+SUMPRODUCT(('Aug 28'!$F$8:$F$42=$T10)*'Aug 28'!$AI$8:$AI$42*(('Aug 28'!$AM$8:$AM$42="Y")+('Aug 28'!$AN$8:$AN$42="Y")+('Aug 28'!$AO$8:$AO$42="Y")))+SUMPRODUCT(('Aug 29'!$F$8:$F$42=$T10)*'Aug 29'!$AI$8:$AI$42*(('Aug 29'!$AM$8:$AM$42="Y")+('Aug 29'!$AN$8:$AN$42="Y")+('Aug 29'!$AO$8:$AO$42="Y")))+SUMPRODUCT(('Aug 30'!$F$8:$F$42=$T10)*'Aug 30'!$AI$8:$AI$42*(('Aug 30'!$AM$8:$AM$42="Y")+('Aug 30'!$AN$8:$AN$42="Y")+('Aug 30'!$AO$8:$AO$42="Y")))+SUMPRODUCT(('Aug 31'!$F$8:$F$42=$T10)*'Aug 31'!$AI$8:$AI$42*(('Aug 31'!$AM$8:$AM$42="Y")+('Aug 31'!$AN$8:$AN$42="Y")+('Aug 31'!$AO$8:$AO$42="Y"))) -> 0 | BD10: =SUM(U10:AY10) -> 0 | BE10: =SUM(U29:AY29) -> 0 | BF10: =SUM(U48:AY48) -> 0
A11: 5 | B11: =$T8 -> MERCEDES CLARK | C11: =BD8 -> 0 | D11: =BE8 -> 0 | E11: =IF(BD8=0,"—",BE8/BD8) -> — | F11: =IF(BD8=0,"—",INDEX('Pay Plan'!$B$6:$B$12,BB8)) -> — | G11: =BF8 -> 0 | H11: =LOOKUP(BD8,'Pay Plan'!$B$15:$B$20,'Pay Plan'!$C$15:$C$20) -> 0 | I11: =LOOKUP(BA8,'Pay Plan'!$E$15:$E$19,'Pay Plan'!$F$15:$F$19) -> 0 | J11: =BC8*'Pay Plan'!$I$15 -> 0 | K11: =G11+H11+I11+J11 -> 0 | O11: =K11-N11 -> 0 | T11: ='Staff & Lists'!A12 -> MATT ALFIERI | U11: =SUMPRODUCT(('Aug 1'!$F$8:$F$42=$T11)*'Aug 1'!$AJ$8:$AJ$42+('Aug 1'!$G$8:$G$42=$T11)*'Aug 1'!$AK$8:$AK$42) -> 0 | V11: =SUMPRODUCT(('Aug 2'!$F$8:$F$42=$T11)*'Aug 2'!$AJ$8:$AJ$42+('Aug 2'!$G$8:$G$42=$T11)*'Aug 2'!$AK$8:$AK$42) -> 0 | W11: =SUMPRODUCT(('Aug 3'!$F$8:$F$42=$T11)*'Aug 3'!$AJ$8:$AJ$42+('Aug 3'!$G$8:$G$42=$T11)*'Aug 3'!$AK$8:$AK$42) -> 0 | X11: =SUMPRODUCT(('Aug 4'!$F$8:$F$42=$T11)*'Aug 4'!$AJ$8:$AJ$42+('Aug 4'!$G$8:$G$42=$T11)*'Aug 4'!$AK$8:$AK$42) -> 0 | Y11: =SUMPRODUCT(('Aug 5'!$F$8:$F$42=$T11)*'Aug 5'!$AJ$8:$AJ$42+('Aug 5'!$G$8:$G$42=$T11)*'Aug 5'!$AK$8:$AK$42) -> 0 | Z11: =SUMPRODUCT(('Aug 6'!$F$8:$F$42=$T11)*'Aug 6'!$AJ$8:$AJ$42+('Aug 6'!$G$8:$G$42=$T11)*'Aug 6'!$AK$8:$AK$42) -> 0 | AA11: =SUMPRODUCT(('Aug 7'!$F$8:$F$42=$T11)*'Aug 7'!$AJ$8:$AJ$42+('Aug 7'!$G$8:$G$42=$T11)*'Aug 7'!$AK$8:$AK$42) -> 0 | AB11: =SUMPRODUCT(('Aug 8'!$F$8:$F$42=$T11)*'Aug 8'!$AJ$8:$AJ$42+('Aug 8'!$G$8:$G$42=$T11)*'Aug 8'!$AK$8:$AK$42) -> 0 | AC11: =SUMPRODUCT(('Aug 9'!$F$8:$F$42=$T11)*'Aug 9'!$AJ$8:$AJ$42+('Aug 9'!$G$8:$G$42=$T11)*'Aug 9'!$AK$8:$AK$42) -> 0 | AD11: =SUMPRODUCT(('Aug 10'!$F$8:$F$42=$T11)*'Aug 10'!$AJ$8:$AJ$42+('Aug 10'!$G$8:$G$42=$T11)*'Aug 10'!$AK$8:$AK$42) -> 0 | AE11: =SUMPRODUCT(('Aug 11'!$F$8:$F$42=$T11)*'Aug 11'!$AJ$8:$AJ$42+('Aug 11'!$G$8:$G$42=$T11)*'Aug 11'!$AK$8:$AK$42) -> 0 | AF11: =SUMPRODUCT(('Aug 12'!$F$8:$F$42=$T11)*'Aug 12'!$AJ$8:$AJ$42+('Aug 12'!$G$8:$G$42=$T11)*'Aug 12'!$AK$8:$AK$42) -> 0 | AG11: =SUMPRODUCT(('Aug 13'!$F$8:$F$42=$T11)*'Aug 13'!$AJ$8:$AJ$42+('Aug 13'!$G$8:$G$42=$T11)*'Aug 13'!$AK$8:$AK$42) -> 0 | AH11: =SUMPRODUCT(('Aug 14'!$F$8:$F$42=$T11)*'Aug 14'!$AJ$8:$AJ$42+('Aug 14'!$G$8:$G$42=$T11)*'Aug 14'!$AK$8:$AK$42) -> 0 | AI11: =SUMPRODUCT(('Aug 15'!$F$8:$F$42=$T11)*'Aug 15'!$AJ$8:$AJ$42+('Aug 15'!$G$8:$G$42=$T11)*'Aug 15'!$AK$8:$AK$42) -> 0 | AJ11: =SUMPRODUCT(('Aug 16'!$F$8:$F$42=$T11)*'Aug 16'!$AJ$8:$AJ$42+('Aug 16'!$G$8:$G$42=$T11)*'Aug 16'!$AK$8:$AK$42) -> 0 | AK11: =SUMPRODUCT(('Aug 17'!$F$8:$F$42=$T11)*'Aug 17'!$AJ$8:$AJ$42+('Aug 17'!$G$8:$G$42=$T11)*'Aug 17'!$AK$8:$AK$42) -> 0 | AL11: =SUMPRODUCT(('Aug 18'!$F$8:$F$42=$T11)*'Aug 18'!$AJ$8:$AJ$42+('Aug 18'!$G$8:$G$42=$T11)*'Aug 18'!$AK$8:$AK$42) -> 0 | AM11: =SUMPRODUCT(('Aug 19'!$F$8:$F$42=$T11)*'Aug 19'!$AJ$8:$AJ$42+('Aug 19'!$G$8:$G$42=$T11)*'Aug 19'!$AK$8:$AK$42) -> 0 | AN11: =SUMPRODUCT(('Aug 20'!$F$8:$F$42=$T11)*'Aug 20'!$AJ$8:$AJ$42+('Aug 20'!$G$8:$G$42=$T11)*'Aug 20'!$AK$8:$AK$42) -> 0 | AO11: =SUMPRODUCT(('Aug 21'!$F$8:$F$42=$T11)*'Aug 21'!$AJ$8:$AJ$42+('Aug 21'!$G$8:$G$42=$T11)*'Aug 21'!$AK$8:$AK$42) -> 0 | AP11: =SUMPRODUCT(('Aug 22'!$F$8:$F$42=$T11)*'Aug 22'!$AJ$8:$AJ$42+('Aug 22'!$G$8:$G$42=$T11)*'Aug 22'!$AK$8:$AK$42) -> 0 | AQ11: =SUMPRODUCT(('Aug 23'!$F$8:$F$42=$T11)*'Aug 23'!$AJ$8:$AJ$42+('Aug 23'!$G$8:$G$42=$T11)*'Aug 23'!$AK$8:$AK$42) -> 0 | AR11: =SUMPRODUCT(('Aug 24'!$F$8:$F$42=$T11)*'Aug 24'!$AJ$8:$AJ$42+('Aug 24'!$G$8:$G$42=$T11)*'Aug 24'!$AK$8:$AK$42) -> 0 | AS11: =SUMPRODUCT(('Aug 25'!$F$8:$F$42=$T11)*'Aug 25'!$AJ$8:$AJ$42+('Aug 25'!$G$8:$G$42=$T11)*'Aug 25'!$AK$8:$AK$42) -> 0 | AT11: =SUMPRODUCT(('Aug 26'!$F$8:$F$42=$T11)*'Aug 26'!$AJ$8:$AJ$42+('Aug 26'!$G$8:$G$42=$T11)*'Aug 26'!$AK$8:$AK$42) -> 0 | AU11: =SUMPRODUCT(('Aug 27'!$F$8:$F$42=$T11)*'Aug 27'!$AJ$8:$AJ$42+('Aug 27'!$G$8:$G$42=$T11)*'Aug 27'!$AK$8:$AK$42) -> 0 | AV11: =SUMPRODUCT(('Aug 28'!$F$8:$F$42=$T11)*'Aug 28'!$AJ$8:$AJ$42+('Aug 28'!$G$8:$G$42=$T11)*'Aug 28'!$AK$8:$AK$42) -> 0 | AW11: =SUMPRODUCT(('Aug 29'!$F$8:$F$42=$T11)*'Aug 29'!$AJ$8:$AJ$42+('Aug 29'!$G$8:$G$42=$T11)*'Aug 29'!$AK$8:$AK$42) -> 0 | AX11: =SUMPRODUCT(('Aug 30'!$F$8:$F$42=$T11)*'Aug 30'!$AJ$8:$AJ$42+('Aug 30'!$G$8:$G$42=$T11)*'Aug 30'!$AK$8:$AK$42) -> 0 | AY11: =SUMPRODUCT(('Aug 31'!$F$8:$F$42=$T11)*'Aug 31'!$AJ$8:$AJ$42+('Aug 31'!$G$8:$G$42=$T11)*'Aug 31'!$AK$8:$AK$42) -> 0 | BA11: =SUM(U11:AD11) -> 0 | BB11: =MATCH(BD11,'Pay Plan'!$C$6:$C$12,1) -> 1 | BC11: =SUMPRODUCT(('Aug 1'!$F$8:$F$42=$T11)*'Aug 1'!$AI$8:$AI$42*(('Aug 1'!$AM$8:$AM$42="Y")+('Aug 1'!$AN$8:$AN$42="Y")+('Aug 1'!$AO$8:$AO$42="Y")))+SUMPRODUCT(('Aug 2'!$F$8:$F$42=$T11)*'Aug 2'!$AI$8:$AI$42*(('Aug 2'!$AM$8:$AM$42="Y")+('Aug 2'!$AN$8:$AN$42="Y")+('Aug 2'!$AO$8:$AO$42="Y")))+SUMPRODUCT(('Aug 3'!$F$8:$F$42=$T11)*'Aug 3'!$AI$8:$AI$42*(('Aug 3'!$AM$8:$AM$42="Y")+('Aug 3'!$AN$8:$AN$42="Y")+('Aug 3'!$AO$8:$AO$42="Y")))+SUMPRODUCT(('Aug 4'!$F$8:$F$42=$T11)*'Aug 4'!$AI$8:$AI$42*(('Aug 4'!$AM$8:$AM$42="Y")+('Aug 4'!$AN$8:$AN$42="Y")+('Aug 4'!$AO$8:$AO$42="Y")))+SUMPRODUCT(('Aug 5'!$F$8:$F$42=$T11)*'Aug 5'!$AI$8:$AI$42*(('Aug 5'!$AM$8:$AM$42="Y")+('Aug 5'!$AN$8:$AN$42="Y")+('Aug 5'!$AO$8:$AO$42="Y")))+SUMPRODUCT(('Aug 6'!$F$8:$F$42=$T11)*'Aug 6'!$AI$8:$AI$42*(('Aug 6'!$AM$8:$AM$42="Y")+('Aug 6'!$AN$8:$AN$42="Y")+('Aug 6'!$AO$8:$AO$42="Y")))+SUMPRODUCT(('Aug 7'!$F$8:$F$42=$T11)*'Aug 7'!$AI$8:$AI$42*(('Aug 7'!$AM$8:$AM$42="Y")+('Aug 7'!$AN$8:$AN$42="Y")+('Aug 7'!$AO$8:$AO$42="Y")))+SUMPRODUCT(('Aug 8'!$F$8:$F$42=$T11)*'Aug 8'!$AI$8:$AI$42*(('Aug 8'!$AM$8:$AM$42="Y")+('Aug 8'!$AN$8:$AN$42="Y")+('Aug 8'!$AO$8:$AO$42="Y")))+SUMPRODUCT(('Aug 9'!$F$8:$F$42=$T11)*'Aug 9'!$AI$8:$AI$42*(('Aug 9'!$AM$8:$AM$42="Y")+('Aug 9'!$AN$8:$AN$42="Y")+('Aug 9'!$AO$8:$AO$42="Y")))+SUMPRODUCT(('Aug 10'!$F$8:$F$42=$T11)*'Aug 10'!$AI$8:$AI$42*(('Aug 10'!$AM$8:$AM$42="Y")+('Aug 10'!$AN$8:$AN$42="Y")+('Aug 10'!$AO$8:$AO$42="Y")))+SUMPRODUCT(('Aug 11'!$F$8:$F$42=$T11)*'Aug 11'!$AI$8:$AI$42*(('Aug 11'!$AM$8:$AM$42="Y")+('Aug 11'!$AN$8:$AN$42="Y")+('Aug 11'!$AO$8:$AO$42="Y")))+SUMPRODUCT(('Aug 12'!$F$8:$F$42=$T11)*'Aug 12'!$AI$8:$AI$42*(('Aug 12'!$AM$8:$AM$42="Y")+('Aug 12'!$AN$8:$AN$42="Y")+('Aug 12'!$AO$8:$AO$42="Y")))+SUMPRODUCT(('Aug 13'!$F$8:$F$42=$T11)*'Aug 13'!$AI$8:$AI$42*(('Aug 13'!$AM$8:$AM$42="Y")+('Aug 13'!$AN$8:$AN$42="Y")+('Aug 13'!$AO$8:$AO$42="Y")))+SUMPRODUCT(('Aug 14'!$F$8:$F$42=$T11)*'Aug 14'!$AI$8:$AI$42*(('Aug 14'!$AM$8:$AM$42="Y")+('Aug 14'!$AN$8:$AN$42="Y")+('Aug 14'!$AO$8:$AO$42="Y")))+SUMPRODUCT(('Aug 15'!$F$8:$F$42=$T11)*'Aug 15'!$AI$8:$AI$42*(('Aug 15'!$AM$8:$AM$42="Y")+('Aug 15'!$AN$8:$AN$42="Y")+('Aug 15'!$AO$8:$AO$42="Y")))+SUMPRODUCT(('Aug 16'!$F$8:$F$42=$T11)*'Aug 16'!$AI$8:$AI$42*(('Aug 16'!$AM$8:$AM$42="Y")+('Aug 16'!$AN$8:$AN$42="Y")+('Aug 16'!$AO$8:$AO$42="Y")))+SUMPRODUCT(('Aug 17'!$F$8:$F$42=$T11)*'Aug 17'!$AI$8:$AI$42*(('Aug 17'!$AM$8:$AM$42="Y")+('Aug 17'!$AN$8:$AN$42="Y")+('Aug 17'!$AO$8:$AO$42="Y")))+SUMPRODUCT(('Aug 18'!$F$8:$F$42=$T11)*'Aug 18'!$AI$8:$AI$42*(('Aug 18'!$AM$8:$AM$42="Y")+('Aug 18'!$AN$8:$AN$42="Y")+('Aug 18'!$AO$8:$AO$42="Y")))+SUMPRODUCT(('Aug 19'!$F$8:$F$42=$T11)*'Aug 19'!$AI$8:$AI$42*(('Aug 19'!$AM$8:$AM$42="Y")+('Aug 19'!$AN$8:$AN$42="Y")+('Aug 19'!$AO$8:$AO$42="Y")))+SUMPRODUCT(('Aug 20'!$F$8:$F$42=$T11)*'Aug 20'!$AI$8:$AI$42*(('Aug 20'!$AM$8:$AM$42="Y")+('Aug 20'!$AN$8:$AN$42="Y")+('Aug 20'!$AO$8:$AO$42="Y")))+SUMPRODUCT(('Aug 21'!$F$8:$F$42=$T11)*'Aug 21'!$AI$8:$AI$42*(('Aug 21'!$AM$8:$AM$42="Y")+('Aug 21'!$AN$8:$AN$42="Y")+('Aug 21'!$AO$8:$AO$42="Y")))+SUMPRODUCT(('Aug 22'!$F$8:$F$42=$T11)*'Aug 22'!$AI$8:$AI$42*(('Aug 22'!$AM$8:$AM$42="Y")+('Aug 22'!$AN$8:$AN$42="Y")+('Aug 22'!$AO$8:$AO$42="Y")))+SUMPRODUCT(('Aug 23'!$F$8:$F$42=$T11)*'Aug 23'!$AI$8:$AI$42*(('Aug 23'!$AM$8:$AM$42="Y")+('Aug 23'!$AN$8:$AN$42="Y")+('Aug 23'!$AO$8:$AO$42="Y")))+SUMPRODUCT(('Aug 24'!$F$8:$F$42=$T11)*'Aug 24'!$AI$8:$AI$42*(('Aug 24'!$AM$8:$AM$42="Y")+('Aug 24'!$AN$8:$AN$42="Y")+('Aug 24'!$AO$8:$AO$42="Y")))+SUMPRODUCT(('Aug 25'!$F$8:$F$42=$T11)*'Aug 25'!$AI$8:$AI$42*(('Aug 25'!$AM$8:$AM$42="Y")+('Aug 25'!$AN$8:$AN$42="Y")+('Aug 25'!$AO$8:$AO$42="Y")))+SUMPRODUCT(('Aug 26'!$F$8:$F$42=$T11)*'Aug 26'!$AI$8:$AI$42*(('Aug 26'!$AM$8:$AM$42="Y")+('Aug 26'!$AN$8:$AN$42="Y")+('Aug 26'!$AO$8:$AO$42="Y")))+SUMPRODUCT(('Aug 27'!$F$8:$F$42=$T11)*'Aug 27'!$AI$8:$AI$42*(('Aug 27'!$AM$8:$AM$42="Y")+('Aug 27'!$AN$8:$AN$42="Y")+('Aug 27'!$AO$8:$AO$42="Y")))+SUMPRODUCT(('Aug 28'!$F$8:$F$42=$T11)*'Aug 28'!$AI$8:$AI$42*(('Aug 28'!$AM$8:$AM$42="Y")+('Aug 28'!$AN$8:$AN$42="Y")+('Aug 28'!$AO$8:$AO$42="Y")))+SUMPRODUCT(('Aug 29'!$F$8:$F$42=$T11)*'Aug 29'!$AI$8:$AI$42*(('Aug 29'!$AM$8:$AM$42="Y")+('Aug 29'!$AN$8:$AN$42="Y")+('Aug 29'!$AO$8:$AO$42="Y")))+SUMPRODUCT(('Aug 30'!$F$8:$F$42=$T11)*'Aug 30'!$AI$8:$AI$42*(('Aug 30'!$AM$8:$AM$42="Y")+('Aug 30'!$AN$8:$AN$42="Y")+('Aug 30'!$AO$8:$AO$42="Y")))+SUMPRODUCT(('Aug 31'!$F$8:$F$42=$T11)*'Aug 31'!$AI$8:$AI$42*(('Aug 31'!$AM$8:$AM$42="Y")+('Aug 31'!$AN$8:$AN$42="Y")+('Aug 31'!$AO$8:$AO$42="Y"))) -> 0 | BD11: =SUM(U11:AY11) -> 0 | BE11: =SUM(U30:AY30) -> 0 | BF11: =SUM(U49:AY49) -> 0
A12: 6 | B12: =$T9 -> ZAY JOHNSON | C12: =BD9 -> 0 | D12: =BE9 -> 0 | E12: =IF(BD9=0,"—",BE9/BD9) -> — | F12: =IF(BD9=0,"—",INDEX('Pay Plan'!$B$6:$B$12,BB9)) -> — | G12: =BF9 -> 0 | H12: =LOOKUP(BD9,'Pay Plan'!$B$15:$B$20,'Pay Plan'!$C$15:$C$20) -> 0 | I12: =LOOKUP(BA9,'Pay Plan'!$E$15:$E$19,'Pay Plan'!$F$15:$F$19) -> 0 | J12: =BC9*'Pay Plan'!$I$15 -> 0 | K12: =G12+H12+I12+J12 -> 0 | O12: =K12-N12 -> 0 | T12: ='Staff & Lists'!A13 -> ZACH CUPP | U12: =SUMPRODUCT(('Aug 1'!$F$8:$F$42=$T12)*'Aug 1'!$AJ$8:$AJ$42+('Aug 1'!$G$8:$G$42=$T12)*'Aug 1'!$AK$8:$AK$42) -> 0 | V12: =SUMPRODUCT(('Aug 2'!$F$8:$F$42=$T12)*'Aug 2'!$AJ$8:$AJ$42+('Aug 2'!$G$8:$G$42=$T12)*'Aug 2'!$AK$8:$AK$42) -> 0 | W12: =SUMPRODUCT(('Aug 3'!$F$8:$F$42=$T12)*'Aug 3'!$AJ$8:$AJ$42+('Aug 3'!$G$8:$G$42=$T12)*'Aug 3'!$AK$8:$AK$42) -> 0 | X12: =SUMPRODUCT(('Aug 4'!$F$8:$F$42=$T12)*'Aug 4'!$AJ$8:$AJ$42+('Aug 4'!$G$8:$G$42=$T12)*'Aug 4'!$AK$8:$AK$42) -> 0 | Y12: =SUMPRODUCT(('Aug 5'!$F$8:$F$42=$T12)*'Aug 5'!$AJ$8:$AJ$42+('Aug 5'!$G$8:$G$42=$T12)*'Aug 5'!$AK$8:$AK$42) -> 0 | Z12: =SUMPRODUCT(('Aug 6'!$F$8:$F$42=$T12)*'Aug 6'!$AJ$8:$AJ$42+('Aug 6'!$G$8:$G$42=$T12)*'Aug 6'!$AK$8:$AK$42) -> 0 | AA12: =SUMPRODUCT(('Aug 7'!$F$8:$F$42=$T12)*'Aug 7'!$AJ$8:$AJ$42+('Aug 7'!$G$8:$G$42=$T12)*'Aug 7'!$AK$8:$AK$42) -> 0 | AB12: =SUMPRODUCT(('Aug 8'!$F$8:$F$42=$T12)*'Aug 8'!$AJ$8:$AJ$42+('Aug 8'!$G$8:$G$42=$T12)*'Aug 8'!$AK$8:$AK$42) -> 0 | AC12: =SUMPRODUCT(('Aug 9'!$F$8:$F$42=$T12)*'Aug 9'!$AJ$8:$AJ$42+('Aug 9'!$G$8:$G$42=$T12)*'Aug 9'!$AK$8:$AK$42) -> 0 | AD12: =SUMPRODUCT(('Aug 10'!$F$8:$F$42=$T12)*'Aug 10'!$AJ$8:$AJ$42+('Aug 10'!$G$8:$G$42=$T12)*'Aug 10'!$AK$8:$AK$42) -> 0 | AE12: =SUMPRODUCT(('Aug 11'!$F$8:$F$42=$T12)*'Aug 11'!$AJ$8:$AJ$42+('Aug 11'!$G$8:$G$42=$T12)*'Aug 11'!$AK$8:$AK$42) -> 0 | AF12: =SUMPRODUCT(('Aug 12'!$F$8:$F$42=$T12)*'Aug 12'!$AJ$8:$AJ$42+('Aug 12'!$G$8:$G$42=$T12)*'Aug 12'!$AK$8:$AK$42) -> 0 | AG12: =SUMPRODUCT(('Aug 13'!$F$8:$F$42=$T12)*'Aug 13'!$AJ$8:$AJ$42+('Aug 13'!$G$8:$G$42=$T12)*'Aug 13'!$AK$8:$AK$42) -> 0 | AH12: =SUMPRODUCT(('Aug 14'!$F$8:$F$42=$T12)*'Aug 14'!$AJ$8:$AJ$42+('Aug 14'!$G$8:$G$42=$T12)*'Aug 14'!$AK$8:$AK$42) -> 0 | AI12: =SUMPRODUCT(('Aug 15'!$F$8:$F$42=$T12)*'Aug 15'!$AJ$8:$AJ$42+('Aug 15'!$G$8:$G$42=$T12)*'Aug 15'!$AK$8:$AK$42) -> 0 | AJ12: =SUMPRODUCT(('Aug 16'!$F$8:$F$42=$T12)*'Aug 16'!$AJ$8:$AJ$42+('Aug 16'!$G$8:$G$42=$T12)*'Aug 16'!$AK$8:$AK$42) -> 0 | AK12: =SUMPRODUCT(('Aug 17'!$F$8:$F$42=$T12)*'Aug 17'!$AJ$8:$AJ$42+('Aug 17'!$G$8:$G$42=$T12)*'Aug 17'!$AK$8:$AK$42) -> 0 | AL12: =SUMPRODUCT(('Aug 18'!$F$8:$F$42=$T12)*'Aug 18'!$AJ$8:$AJ$42+('Aug 18'!$G$8:$G$42=$T12)*'Aug 18'!$AK$8:$AK$42) -> 0 | AM12: =SUMPRODUCT(('Aug 19'!$F$8:$F$42=$T12)*'Aug 19'!$AJ$8:$AJ$42+('Aug 19'!$G$8:$G$42=$T12)*'Aug 19'!$AK$8:$AK$42) -> 0 | AN12: =SUMPRODUCT(('Aug 20'!$F$8:$F$42=$T12)*'Aug 20'!$AJ$8:$AJ$42+('Aug 20'!$G$8:$G$42=$T12)*'Aug 20'!$AK$8:$AK$42) -> 0 | AO12: =SUMPRODUCT(('Aug 21'!$F$8:$F$42=$T12)*'Aug 21'!$AJ$8:$AJ$42+('Aug 21'!$G$8:$G$42=$T12)*'Aug 21'!$AK$8:$AK$42) -> 0 | AP12: =SUMPRODUCT(('Aug 22'!$F$8:$F$42=$T12)*'Aug 22'!$AJ$8:$AJ$42+('Aug 22'!$G$8:$G$42=$T12)*'Aug 22'!$AK$8:$AK$42) -> 0 | AQ12: =SUMPRODUCT(('Aug 23'!$F$8:$F$42=$T12)*'Aug 23'!$AJ$8:$AJ$42+('Aug 23'!$G$8:$G$42=$T12)*'Aug 23'!$AK$8:$AK$42) -> 0 | AR12: =SUMPRODUCT(('Aug 24'!$F$8:$F$42=$T12)*'Aug 24'!$AJ$8:$AJ$42+('Aug 24'!$G$8:$G$42=$T12)*'Aug 24'!$AK$8:$AK$42) -> 0 | AS12: =SUMPRODUCT(('Aug 25'!$F$8:$F$42=$T12)*'Aug 25'!$AJ$8:$AJ$42+('Aug 25'!$G$8:$G$42=$T12)*'Aug 25'!$AK$8:$AK$42) -> 0 | AT12: =SUMPRODUCT(('Aug 26'!$F$8:$F$42=$T12)*'Aug 26'!$AJ$8:$AJ$42+('Aug 26'!$G$8:$G$42=$T12)*'Aug 26'!$AK$8:$AK$42) -> 0 | AU12: =SUMPRODUCT(('Aug 27'!$F$8:$F$42=$T12)*'Aug 27'!$AJ$8:$AJ$42+('Aug 27'!$G$8:$G$42=$T12)*'Aug 27'!$AK$8:$AK$42) -> 0 | AV12: =SUMPRODUCT(('Aug 28'!$F$8:$F$42=$T12)*'Aug 28'!$AJ$8:$AJ$42+('Aug 28'!$G$8:$G$42=$T12)*'Aug 28'!$AK$8:$AK$42) -> 0 | AW12: =SUMPRODUCT(('Aug 29'!$F$8:$F$42=$T12)*'Aug 29'!$AJ$8:$AJ$42+('Aug 29'!$G$8:$G$42=$T12)*'Aug 29'!$AK$8:$AK$42) -> 0 | AX12: =SUMPRODUCT(('Aug 30'!$F$8:$F$42=$T12)*'Aug 30'!$AJ$8:$AJ$42+('Aug 30'!$G$8:$G$42=$T12)*'Aug 30'!$AK$8:$AK$42) -> 0 | AY12: =SUMPRODUCT(('Aug 31'!$F$8:$F$42=$T12)*'Aug 31'!$AJ$8:$AJ$42+('Aug 31'!$G$8:$G$42=$T12)*'Aug 31'!$AK$8:$AK$42) -> 0 | BA12: =SUM(U12:AD12) -> 0 | BB12: =MATCH(BD12,'Pay Plan'!$C$6:$C$12,1) -> 1 | BC12: =SUMPRODUCT(('Aug 1'!$F$8:$F$42=$T12)*'Aug 1'!$AI$8:$AI$42*(('Aug 1'!$AM$8:$AM$42="Y")+('Aug 1'!$AN$8:$AN$42="Y")+('Aug 1'!$AO$8:$AO$42="Y")))+SUMPRODUCT(('Aug 2'!$F$8:$F$42=$T12)*'Aug 2'!$AI$8:$AI$42*(('Aug 2'!$AM$8:$AM$42="Y")+('Aug 2'!$AN$8:$AN$42="Y")+('Aug 2'!$AO$8:$AO$42="Y")))+SUMPRODUCT(('Aug 3'!$F$8:$F$42=$T12)*'Aug 3'!$AI$8:$AI$42*(('Aug 3'!$AM$8:$AM$42="Y")+('Aug 3'!$AN$8:$AN$42="Y")+('Aug 3'!$AO$8:$AO$42="Y")))+SUMPRODUCT(('Aug 4'!$F$8:$F$42=$T12)*'Aug 4'!$AI$8:$AI$42*(('Aug 4'!$AM$8:$AM$42="Y")+('Aug 4'!$AN$8:$AN$42="Y")+('Aug 4'!$AO$8:$AO$42="Y")))+SUMPRODUCT(('Aug 5'!$F$8:$F$42=$T12)*'Aug 5'!$AI$8:$AI$42*(('Aug 5'!$AM$8:$AM$42="Y")+('Aug 5'!$AN$8:$AN$42="Y")+('Aug 5'!$AO$8:$AO$42="Y")))+SUMPRODUCT(('Aug 6'!$F$8:$F$42=$T12)*'Aug 6'!$AI$8:$AI$42*(('Aug 6'!$AM$8:$AM$42="Y")+('Aug 6'!$AN$8:$AN$42="Y")+('Aug 6'!$AO$8:$AO$42="Y")))+SUMPRODUCT(('Aug 7'!$F$8:$F$42=$T12)*'Aug 7'!$AI$8:$AI$42*(('Aug 7'!$AM$8:$AM$42="Y")+('Aug 7'!$AN$8:$AN$42="Y")+('Aug 7'!$AO$8:$AO$42="Y")))+SUMPRODUCT(('Aug 8'!$F$8:$F$42=$T12)*'Aug 8'!$AI$8:$AI$42*(('Aug 8'!$AM$8:$AM$42="Y")+('Aug 8'!$AN$8:$AN$42="Y")+('Aug 8'!$AO$8:$AO$42="Y")))+SUMPRODUCT(('Aug 9'!$F$8:$F$42=$T12)*'Aug 9'!$AI$8:$AI$42*(('Aug 9'!$AM$8:$AM$42="Y")+('Aug 9'!$AN$8:$AN$42="Y")+('Aug 9'!$AO$8:$AO$42="Y")))+SUMPRODUCT(('Aug 10'!$F$8:$F$42=$T12)*'Aug 10'!$AI$8:$AI$42*(('Aug 10'!$AM$8:$AM$42="Y")+('Aug 10'!$AN$8:$AN$42="Y")+('Aug 10'!$AO$8:$AO$42="Y")))+SUMPRODUCT(('Aug 11'!$F$8:$F$42=$T12)*'Aug 11'!$AI$8:$AI$42*(('Aug 11'!$AM$8:$AM$42="Y")+('Aug 11'!$AN$8:$AN$42="Y")+('Aug 11'!$AO$8:$AO$42="Y")))+SUMPRODUCT(('Aug 12'!$F$8:$F$42=$T12)*'Aug 12'!$AI$8:$AI$42*(('Aug 12'!$AM$8:$AM$42="Y")+('Aug 12'!$AN$8:$AN$42="Y")+('Aug 12'!$AO$8:$AO$42="Y")))+SUMPRODUCT(('Aug 13'!$F$8:$F$42=$T12)*'Aug 13'!$AI$8:$AI$42*(('Aug 13'!$AM$8:$AM$42="Y")+('Aug 13'!$AN$8:$AN$42="Y")+('Aug 13'!$AO$8:$AO$42="Y")))+SUMPRODUCT(('Aug 14'!$F$8:$F$42=$T12)*'Aug 14'!$AI$8:$AI$42*(('Aug 14'!$AM$8:$AM$42="Y")+('Aug 14'!$AN$8:$AN$42="Y")+('Aug 14'!$AO$8:$AO$42="Y")))+SUMPRODUCT(('Aug 15'!$F$8:$F$42=$T12)*'Aug 15'!$AI$8:$AI$42*(('Aug 15'!$AM$8:$AM$42="Y")+('Aug 15'!$AN$8:$AN$42="Y")+('Aug 15'!$AO$8:$AO$42="Y")))+SUMPRODUCT(('Aug 16'!$F$8:$F$42=$T12)*'Aug 16'!$AI$8:$AI$42*(('Aug 16'!$AM$8:$AM$42="Y")+('Aug 16'!$AN$8:$AN$42="Y")+('Aug 16'!$AO$8:$AO$42="Y")))+SUMPRODUCT(('Aug 17'!$F$8:$F$42=$T12)*'Aug 17'!$AI$8:$AI$42*(('Aug 17'!$AM$8:$AM$42="Y")+('Aug 17'!$AN$8:$AN$42="Y")+('Aug 17'!$AO$8:$AO$42="Y")))+SUMPRODUCT(('Aug 18'!$F$8:$F$42=$T12)*'Aug 18'!$AI$8:$AI$42*(('Aug 18'!$AM$8:$AM$42="Y")+('Aug 18'!$AN$8:$AN$42="Y")+('Aug 18'!$AO$8:$AO$42="Y")))+SUMPRODUCT(('Aug 19'!$F$8:$F$42=$T12)*'Aug 19'!$AI$8:$AI$42*(('Aug 19'!$AM$8:$AM$42="Y")+('Aug 19'!$AN$8:$AN$42="Y")+('Aug 19'!$AO$8:$AO$42="Y")))+SUMPRODUCT(('Aug 20'!$F$8:$F$42=$T12)*'Aug 20'!$AI$8:$AI$42*(('Aug 20'!$AM$8:$AM$42="Y")+('Aug 20'!$AN$8:$AN$42="Y")+('Aug 20'!$AO$8:$AO$42="Y")))+SUMPRODUCT(('Aug 21'!$F$8:$F$42=$T12)*'Aug 21'!$AI$8:$AI$42*(('Aug 21'!$AM$8:$AM$42="Y")+('Aug 21'!$AN$8:$AN$42="Y")+('Aug 21'!$AO$8:$AO$42="Y")))+SUMPRODUCT(('Aug 22'!$F$8:$F$42=$T12)*'Aug 22'!$AI$8:$AI$42*(('Aug 22'!$AM$8:$AM$42="Y")+('Aug 22'!$AN$8:$AN$42="Y")+('Aug 22'!$AO$8:$AO$42="Y")))+SUMPRODUCT(('Aug 23'!$F$8:$F$42=$T12)*'Aug 23'!$AI$8:$AI$42*(('Aug 23'!$AM$8:$AM$42="Y")+('Aug 23'!$AN$8:$AN$42="Y")+('Aug 23'!$AO$8:$AO$42="Y")))+SUMPRODUCT(('Aug 24'!$F$8:$F$42=$T12)*'Aug 24'!$AI$8:$AI$42*(('Aug 24'!$AM$8:$AM$42="Y")+('Aug 24'!$AN$8:$AN$42="Y")+('Aug 24'!$AO$8:$AO$42="Y")))+SUMPRODUCT(('Aug 25'!$F$8:$F$42=$T12)*'Aug 25'!$AI$8:$AI$42*(('Aug 25'!$AM$8:$AM$42="Y")+('Aug 25'!$AN$8:$AN$42="Y")+('Aug 25'!$AO$8:$AO$42="Y")))+SUMPRODUCT(('Aug 26'!$F$8:$F$42=$T12)*'Aug 26'!$AI$8:$AI$42*(('Aug 26'!$AM$8:$AM$42="Y")+('Aug 26'!$AN$8:$AN$42="Y")+('Aug 26'!$AO$8:$AO$42="Y")))+SUMPRODUCT(('Aug 27'!$F$8:$F$42=$T12)*'Aug 27'!$AI$8:$AI$42*(('Aug 27'!$AM$8:$AM$42="Y")+('Aug 27'!$AN$8:$AN$42="Y")+('Aug 27'!$AO$8:$AO$42="Y")))+SUMPRODUCT(('Aug 28'!$F$8:$F$42=$T12)*'Aug 28'!$AI$8:$AI$42*(('Aug 28'!$AM$8:$AM$42="Y")+('Aug 28'!$AN$8:$AN$42="Y")+('Aug 28'!$AO$8:$AO$42="Y")))+SUMPRODUCT(('Aug 29'!$F$8:$F$42=$T12)*'Aug 29'!$AI$8:$AI$42*(('Aug 29'!$AM$8:$AM$42="Y")+('Aug 29'!$AN$8:$AN$42="Y")+('Aug 29'!$AO$8:$AO$42="Y")))+SUMPRODUCT(('Aug 30'!$F$8:$F$42=$T12)*'Aug 30'!$AI$8:$AI$42*(('Aug 30'!$AM$8:$AM$42="Y")+('Aug 30'!$AN$8:$AN$42="Y")+('Aug 30'!$AO$8:$AO$42="Y")))+SUMPRODUCT(('Aug 31'!$F$8:$F$42=$T12)*'Aug 31'!$AI$8:$AI$42*(('Aug 31'!$AM$8:$AM$42="Y")+('Aug 31'!$AN$8:$AN$42="Y")+('Aug 31'!$AO$8:$AO$42="Y"))) -> 0 | BD12: =SUM(U12:AY12) -> 0 | BE12: =SUM(U31:AY31) -> 0 | BF12: =SUM(U50:AY50) -> 0
A13: 7 | B13: =$T10 -> JUSTIN ROLLER | C13: =BD10 -> 0 | D13: =BE10 -> 0 | E13: =IF(BD10=0,"—",BE10/BD10) -> — | F13: =IF(BD10=0,"—",INDEX('Pay Plan'!$B$6:$B$12,BB10)) -> — | G13: =BF10 -> 0 | H13: =LOOKUP(BD10,'Pay Plan'!$B$15:$B$20,'Pay Plan'!$C$15:$C$20) -> 0 | I13: =LOOKUP(BA10,'Pay Plan'!$E$15:$E$19,'Pay Plan'!$F$15:$F$19) -> 0 | J13: =BC10*'Pay Plan'!$I$15 -> 0 | K13: =G13+H13+I13+J13 -> 0 | O13: =K13-N13 -> 0 | T13: ='Staff & Lists'!A14 -> ANDREW MIEIR | U13: =SUMPRODUCT(('Aug 1'!$F$8:$F$42=$T13)*'Aug 1'!$AJ$8:$AJ$42+('Aug 1'!$G$8:$G$42=$T13)*'Aug 1'!$AK$8:$AK$42) -> 0 | V13: =SUMPRODUCT(('Aug 2'!$F$8:$F$42=$T13)*'Aug 2'!$AJ$8:$AJ$42+('Aug 2'!$G$8:$G$42=$T13)*'Aug 2'!$AK$8:$AK$42) -> 0 | W13: =SUMPRODUCT(('Aug 3'!$F$8:$F$42=$T13)*'Aug 3'!$AJ$8:$AJ$42+('Aug 3'!$G$8:$G$42=$T13)*'Aug 3'!$AK$8:$AK$42) -> 0 | X13: =SUMPRODUCT(('Aug 4'!$F$8:$F$42=$T13)*'Aug 4'!$AJ$8:$AJ$42+('Aug 4'!$G$8:$G$42=$T13)*'Aug 4'!$AK$8:$AK$42) -> 0 | Y13: =SUMPRODUCT(('Aug 5'!$F$8:$F$42=$T13)*'Aug 5'!$AJ$8:$AJ$42+('Aug 5'!$G$8:$G$42=$T13)*'Aug 5'!$AK$8:$AK$42) -> 0 | Z13: =SUMPRODUCT(('Aug 6'!$F$8:$F$42=$T13)*'Aug 6'!$AJ$8:$AJ$42+('Aug 6'!$G$8:$G$42=$T13)*'Aug 6'!$AK$8:$AK$42) -> 0 | AA13: =SUMPRODUCT(('Aug 7'!$F$8:$F$42=$T13)*'Aug 7'!$AJ$8:$AJ$42+('Aug 7'!$G$8:$G$42=$T13)*'Aug 7'!$AK$8:$AK$42) -> 0 | AB13: =SUMPRODUCT(('Aug 8'!$F$8:$F$42=$T13)*'Aug 8'!$AJ$8:$AJ$42+('Aug 8'!$G$8:$G$42=$T13)*'Aug 8'!$AK$8:$AK$42) -> 0 | AC13: =SUMPRODUCT(('Aug 9'!$F$8:$F$42=$T13)*'Aug 9'!$AJ$8:$AJ$42+('Aug 9'!$G$8:$G$42=$T13)*'Aug 9'!$AK$8:$AK$42) -> 0 | AD13: =SUMPRODUCT(('Aug 10'!$F$8:$F$42=$T13)*'Aug 10'!$AJ$8:$AJ$42+('Aug 10'!$G$8:$G$42=$T13)*'Aug 10'!$AK$8:$AK$42) -> 0 | AE13: =SUMPRODUCT(('Aug 11'!$F$8:$F$42=$T13)*'Aug 11'!$AJ$8:$AJ$42+('Aug 11'!$G$8:$G$42=$T13)*'Aug 11'!$AK$8:$AK$42) -> 0 | AF13: =SUMPRODUCT(('Aug 12'!$F$8:$F$42=$T13)*'Aug 12'!$AJ$8:$AJ$42+('Aug 12'!$G$8:$G$42=$T13)*'Aug 12'!$AK$8:$AK$42) -> 0 | AG13: =SUMPRODUCT(('Aug 13'!$F$8:$F$42=$T13)*'Aug 13'!$AJ$8:$AJ$42+('Aug 13'!$G$8:$G$42=$T13)*'Aug 13'!$AK$8:$AK$42) -> 0 | AH13: =SUMPRODUCT(('Aug 14'!$F$8:$F$42=$T13)*'Aug 14'!$AJ$8:$AJ$42+('Aug 14'!$G$8:$G$42=$T13)*'Aug 14'!$AK$8:$AK$42) -> 0 | AI13: =SUMPRODUCT(('Aug 15'!$F$8:$F$42=$T13)*'Aug 15'!$AJ$8:$AJ$42+('Aug 15'!$G$8:$G$42=$T13)*'Aug 15'!$AK$8:$AK$42) -> 0 | AJ13: =SUMPRODUCT(('Aug 16'!$F$8:$F$42=$T13)*'Aug 16'!$AJ$8:$AJ$42+('Aug 16'!$G$8:$G$42=$T13)*'Aug 16'!$AK$8:$AK$42) -> 0 | AK13: =SUMPRODUCT(('Aug 17'!$F$8:$F$42=$T13)*'Aug 17'!$AJ$8:$AJ$42+('Aug 17'!$G$8:$G$42=$T13)*'Aug 17'!$AK$8:$AK$42) -> 0 | AL13: =SUMPRODUCT(('Aug 18'!$F$8:$F$42=$T13)*'Aug 18'!$AJ$8:$AJ$42+('Aug 18'!$G$8:$G$42=$T13)*'Aug 18'!$AK$8:$AK$42) -> 0 | AM13: =SUMPRODUCT(('Aug 19'!$F$8:$F$42=$T13)*'Aug 19'!$AJ$8:$AJ$42+('Aug 19'!$G$8:$G$42=$T13)*'Aug 19'!$AK$8:$AK$42) -> 0 | AN13: =SUMPRODUCT(('Aug 20'!$F$8:$F$42=$T13)*'Aug 20'!$AJ$8:$AJ$42+('Aug 20'!$G$8:$G$42=$T13)*'Aug 20'!$AK$8:$AK$42) -> 0 | AO13: =SUMPRODUCT(('Aug 21'!$F$8:$F$42=$T13)*'Aug 21'!$AJ$8:$AJ$42+('Aug 21'!$G$8:$G$42=$T13)*'Aug 21'!$AK$8:$AK$42) -> 0 | AP13: =SUMPRODUCT(('Aug 22'!$F$8:$F$42=$T13)*'Aug 22'!$AJ$8:$AJ$42+('Aug 22'!$G$8:$G$42=$T13)*'Aug 22'!$AK$8:$AK$42) -> 0 | AQ13: =SUMPRODUCT(('Aug 23'!$F$8:$F$42=$T13)*'Aug 23'!$AJ$8:$AJ$42+('Aug 23'!$G$8:$G$42=$T13)*'Aug 23'!$AK$8:$AK$42) -> 0 | AR13: =SUMPRODUCT(('Aug 24'!$F$8:$F$42=$T13)*'Aug 24'!$AJ$8:$AJ$42+('Aug 24'!$G$8:$G$42=$T13)*'Aug 24'!$AK$8:$AK$42) -> 0 | AS13: =SUMPRODUCT(('Aug 25'!$F$8:$F$42=$T13)*'Aug 25'!$AJ$8:$AJ$42+('Aug 25'!$G$8:$G$42=$T13)*'Aug 25'!$AK$8:$AK$42) -> 0 | AT13: =SUMPRODUCT(('Aug 26'!$F$8:$F$42=$T13)*'Aug 26'!$AJ$8:$AJ$42+('Aug 26'!$G$8:$G$42=$T13)*'Aug 26'!$AK$8:$AK$42) -> 0 | AU13: =SUMPRODUCT(('Aug 27'!$F$8:$F$42=$T13)*'Aug 27'!$AJ$8:$AJ$42+('Aug 27'!$G$8:$G$42=$T13)*'Aug 27'!$AK$8:$AK$42) -> 0 | AV13: =SUMPRODUCT(('Aug 28'!$F$8:$F$42=$T13)*'Aug 28'!$AJ$8:$AJ$42+('Aug 28'!$G$8:$G$42=$T13)*'Aug 28'!$AK$8:$AK$42) -> 0 | AW13: =SUMPRODUCT(('Aug 29'!$F$8:$F$42=$T13)*'Aug 29'!$AJ$8:$AJ$42+('Aug 29'!$G$8:$G$42=$T13)*'Aug 29'!$AK$8:$AK$42) -> 0 | AX13: =SUMPRODUCT(('Aug 30'!$F$8:$F$42=$T13)*'Aug 30'!$AJ$8:$AJ$42+('Aug 30'!$G$8:$G$42=$T13)*'Aug 30'!$AK$8:$AK$42) -> 0 | AY13: =SUMPRODUCT(('Aug 31'!$F$8:$F$42=$T13)*'Aug 31'!$AJ$8:$AJ$42+('Aug 31'!$G$8:$G$42=$T13)*'Aug 31'!$AK$8:$AK$42) -> 0 | BA13: =SUM(U13:AD13) -> 0 | BB13: =MATCH(BD13,'Pay Plan'!$C$6:$C$12,1) -> 1 | BC13: =SUMPRODUCT(('Aug 1'!$F$8:$F$42=$T13)*'Aug 1'!$AI$8:$AI$42*(('Aug 1'!$AM$8:$AM$42="Y")+('Aug 1'!$AN$8:$AN$42="Y")+('Aug 1'!$AO$8:$AO$42="Y")))+SUMPRODUCT(('Aug 2'!$F$8:$F$42=$T13)*'Aug 2'!$AI$8:$AI$42*(('Aug 2'!$AM$8:$AM$42="Y")+('Aug 2'!$AN$8:$AN$42="Y")+('Aug 2'!$AO$8:$AO$42="Y")))+SUMPRODUCT(('Aug 3'!$F$8:$F$42=$T13)*'Aug 3'!$AI$8:$AI$42*(('Aug 3'!$AM$8:$AM$42="Y")+('Aug 3'!$AN$8:$AN$42="Y")+('Aug 3'!$AO$8:$AO$42="Y")))+SUMPRODUCT(('Aug 4'!$F$8:$F$42=$T13)*'Aug 4'!$AI$8:$AI$42*(('Aug 4'!$AM$8:$AM$42="Y")+('Aug 4'!$AN$8:$AN$42="Y")+('Aug 4'!$AO$8:$AO$42="Y")))+SUMPRODUCT(('Aug 5'!$F$8:$F$42=$T13)*'Aug 5'!$AI$8:$AI$42*(('Aug 5'!$AM$8:$AM$42="Y")+('Aug 5'!$AN$8:$AN$42="Y")+('Aug 5'!$AO$8:$AO$42="Y")))+SUMPRODUCT(('Aug 6'!$F$8:$F$42=$T13)*'Aug 6'!$AI$8:$AI$42*(('Aug 6'!$AM$8:$AM$42="Y")+('Aug 6'!$AN$8:$AN$42="Y")+('Aug 6'!$AO$8:$AO$42="Y")))+SUMPRODUCT(('Aug 7'!$F$8:$F$42=$T13)*'Aug 7'!$AI$8:$AI$42*(('Aug 7'!$AM$8:$AM$42="Y")+('Aug 7'!$AN$8:$AN$42="Y")+('Aug 7'!$AO$8:$AO$42="Y")))+SUMPRODUCT(('Aug 8'!$F$8:$F$42=$T13)*'Aug 8'!$AI$8:$AI$42*(('Aug 8'!$AM$8:$AM$42="Y")+('Aug 8'!$AN$8:$AN$42="Y")+('Aug 8'!$AO$8:$AO$42="Y")))+SUMPRODUCT(('Aug 9'!$F$8:$F$42=$T13)*'Aug 9'!$AI$8:$AI$42*(('Aug 9'!$AM$8:$AM$42="Y")+('Aug 9'!$AN$8:$AN$42="Y")+('Aug 9'!$AO$8:$AO$42="Y")))+SUMPRODUCT(('Aug 10'!$F$8:$F$42=$T13)*'Aug 10'!$AI$8:$AI$42*(('Aug 10'!$AM$8:$AM$42="Y")+('Aug 10'!$AN$8:$AN$42="Y")+('Aug 10'!$AO$8:$AO$42="Y")))+SUMPRODUCT(('Aug 11'!$F$8:$F$42=$T13)*'Aug 11'!$AI$8:$AI$42*(('Aug 11'!$AM$8:$AM$42="Y")+('Aug 11'!$AN$8:$AN$42="Y")+('Aug 11'!$AO$8:$AO$42="Y")))+SUMPRODUCT(('Aug 12'!$F$8:$F$42=$T13)*'Aug 12'!$AI$8:$AI$42*(('Aug 12'!$AM$8:$AM$42="Y")+('Aug 12'!$AN$8:$AN$42="Y")+('Aug 12'!$AO$8:$AO$42="Y")))+SUMPRODUCT(('Aug 13'!$F$8:$F$42=$T13)*'Aug 13'!$AI$8:$AI$42*(('Aug 13'!$AM$8:$AM$42="Y")+('Aug 13'!$AN$8:$AN$42="Y")+('Aug 13'!$AO$8:$AO$42="Y")))+SUMPRODUCT(('Aug 14'!$F$8:$F$42=$T13)*'Aug 14'!$AI$8:$AI$42*(('Aug 14'!$AM$8:$AM$42="Y")+('Aug 14'!$AN$8:$AN$42="Y")+('Aug 14'!$AO$8:$AO$42="Y")))+SUMPRODUCT(('Aug 15'!$F$8:$F$42=$T13)*'Aug 15'!$AI$8:$AI$42*(('Aug 15'!$AM$8:$AM$42="Y")+('Aug 15'!$AN$8:$AN$42="Y")+('Aug 15'!$AO$8:$AO$42="Y")))+SUMPRODUCT(('Aug 16'!$F$8:$F$42=$T13)*'Aug 16'!$AI$8:$AI$42*(('Aug 16'!$AM$8:$AM$42="Y")+('Aug 16'!$AN$8:$AN$42="Y")+('Aug 16'!$AO$8:$AO$42="Y")))+SUMPRODUCT(('Aug 17'!$F$8:$F$42=$T13)*'Aug 17'!$AI$8:$AI$42*(('Aug 17'!$AM$8:$AM$42="Y")+('Aug 17'!$AN$8:$AN$42="Y")+('Aug 17'!$AO$8:$AO$42="Y")))+SUMPRODUCT(('Aug 18'!$F$8:$F$42=$T13)*'Aug 18'!$AI$8:$AI$42*(('Aug 18'!$AM$8:$AM$42="Y")+('Aug 18'!$AN$8:$AN$42="Y")+('Aug 18'!$AO$8:$AO$42="Y")))+SUMPRODUCT(('Aug 19'!$F$8:$F$42=$T13)*'Aug 19'!$AI$8:$AI$42*(('Aug 19'!$AM$8:$AM$42="Y")+('Aug 19'!$AN$8:$AN$42="Y")+('Aug 19'!$AO$8:$AO$42="Y")))+SUMPRODUCT(('Aug 20'!$F$8:$F$42=$T13)*'Aug 20'!$AI$8:$AI$42*(('Aug 20'!$AM$8:$AM$42="Y")+('Aug 20'!$AN$8:$AN$42="Y")+('Aug 20'!$AO$8:$AO$42="Y")))+SUMPRODUCT(('Aug 21'!$F$8:$F$42=$T13)*'Aug 21'!$AI$8:$AI$42*(('Aug 21'!$AM$8:$AM$42="Y")+('Aug 21'!$AN$8:$AN$42="Y")+('Aug 21'!$AO$8:$AO$42="Y")))+SUMPRODUCT(('Aug 22'!$F$8:$F$42=$T13)*'Aug 22'!$AI$8:$AI$42*(('Aug 22'!$AM$8:$AM$42="Y")+('Aug 22'!$AN$8:$AN$42="Y")+('Aug 22'!$AO$8:$AO$42="Y")))+SUMPRODUCT(('Aug 23'!$F$8:$F$42=$T13)*'Aug 23'!$AI$8:$AI$42*(('Aug 23'!$AM$8:$AM$42="Y")+('Aug 23'!$AN$8:$AN$42="Y")+('Aug 23'!$AO$8:$AO$42="Y")))+SUMPRODUCT(('Aug 24'!$F$8:$F$42=$T13)*'Aug 24'!$AI$8:$AI$42*(('Aug 24'!$AM$8:$AM$42="Y")+('Aug 24'!$AN$8:$AN$42="Y")+('Aug 24'!$AO$8:$AO$42="Y")))+SUMPRODUCT(('Aug 25'!$F$8:$F$42=$T13)*'Aug 25'!$AI$8:$AI$42*(('Aug 25'!$AM$8:$AM$42="Y")+('Aug 25'!$AN$8:$AN$42="Y")+('Aug 25'!$AO$8:$AO$42="Y")))+SUMPRODUCT(('Aug 26'!$F$8:$F$42=$T13)*'Aug 26'!$AI$8:$AI$42*(('Aug 26'!$AM$8:$AM$42="Y")+('Aug 26'!$AN$8:$AN$42="Y")+('Aug 26'!$AO$8:$AO$42="Y")))+SUMPRODUCT(('Aug 27'!$F$8:$F$42=$T13)*'Aug 27'!$AI$8:$AI$42*(('Aug 27'!$AM$8:$AM$42="Y")+('Aug 27'!$AN$8:$AN$42="Y")+('Aug 27'!$AO$8:$AO$42="Y")))+SUMPRODUCT(('Aug 28'!$F$8:$F$42=$T13)*'Aug 28'!$AI$8:$AI$42*(('Aug 28'!$AM$8:$AM$42="Y")+('Aug 28'!$AN$8:$AN$42="Y")+('Aug 28'!$AO$8:$AO$42="Y")))+SUMPRODUCT(('Aug 29'!$F$8:$F$42=$T13)*'Aug 29'!$AI$8:$AI$42*(('Aug 29'!$AM$8:$AM$42="Y")+('Aug 29'!$AN$8:$AN$42="Y")+('Aug 29'!$AO$8:$AO$42="Y")))+SUMPRODUCT(('Aug 30'!$F$8:$F$42=$T13)*'Aug 30'!$AI$8:$AI$42*(('Aug 30'!$AM$8:$AM$42="Y")+('Aug 30'!$AN$8:$AN$42="Y")+('Aug 30'!$AO$8:$AO$42="Y")))+SUMPRODUCT(('Aug 31'!$F$8:$F$42=$T13)*'Aug 31'!$AI$8:$AI$42*(('Aug 31'!$AM$8:$AM$42="Y")+('Aug 31'!$AN$8:$AN$42="Y")+('Aug 31'!$AO$8:$AO$42="Y"))) -> 0 | BD13: =SUM(U13:AY13) -> 0 | BE13: =SUM(U32:AY32) -> 0 | BF13: =SUM(U51:AY51) -> 0
A14: 8 | B14: =$T11 -> MATT ALFIERI | C14: =BD11 -> 0 | D14: =BE11 -> 0 | E14: =IF(BD11=0,"—",BE11/BD11) -> — | F14: =IF(BD11=0,"—",INDEX('Pay Plan'!$B$6:$B$12,BB11)) -> — | G14: =BF11 -> 0 | H14: =LOOKUP(BD11,'Pay Plan'!$B$15:$B$20,'Pay Plan'!$C$15:$C$20) -> 0 | I14: =LOOKUP(BA11,'Pay Plan'!$E$15:$E$19,'Pay Plan'!$F$15:$F$19) -> 0 | J14: =BC11*'Pay Plan'!$I$15 -> 0 | K14: =G14+H14+I14+J14 -> 0 | O14: =K14-N14 -> 0 | T14: ='Staff & Lists'!A15 -> RAFAEL CAMPOS | U14: =SUMPRODUCT(('Aug 1'!$F$8:$F$42=$T14)*'Aug 1'!$AJ$8:$AJ$42+('Aug 1'!$G$8:$G$42=$T14)*'Aug 1'!$AK$8:$AK$42) -> 0 | V14: =SUMPRODUCT(('Aug 2'!$F$8:$F$42=$T14)*'Aug 2'!$AJ$8:$AJ$42+('Aug 2'!$G$8:$G$42=$T14)*'Aug 2'!$AK$8:$AK$42) -> 0 | W14: =SUMPRODUCT(('Aug 3'!$F$8:$F$42=$T14)*'Aug 3'!$AJ$8:$AJ$42+('Aug 3'!$G$8:$G$42=$T14)*'Aug 3'!$AK$8:$AK$42) -> 0 | X14: =SUMPRODUCT(('Aug 4'!$F$8:$F$42=$T14)*'Aug 4'!$AJ$8:$AJ$42+('Aug 4'!$G$8:$G$42=$T14)*'Aug 4'!$AK$8:$AK$42) -> 0 | Y14: =SUMPRODUCT(('Aug 5'!$F$8:$F$42=$T14)*'Aug 5'!$AJ$8:$AJ$42+('Aug 5'!$G$8:$G$42=$T14)*'Aug 5'!$AK$8:$AK$42) -> 0 | Z14: =SUMPRODUCT(('Aug 6'!$F$8:$F$42=$T14)*'Aug 6'!$AJ$8:$AJ$42+('Aug 6'!$G$8:$G$42=$T14)*'Aug 6'!$AK$8:$AK$42) -> 0 | AA14: =SUMPRODUCT(('Aug 7'!$F$8:$F$42=$T14)*'Aug 7'!$AJ$8:$AJ$42+('Aug 7'!$G$8:$G$42=$T14)*'Aug 7'!$AK$8:$AK$42) -> 0 | AB14: =SUMPRODUCT(('Aug 8'!$F$8:$F$42=$T14)*'Aug 8'!$AJ$8:$AJ$42+('Aug 8'!$G$8:$G$42=$T14)*'Aug 8'!$AK$8:$AK$42) -> 0 | AC14: =SUMPRODUCT(('Aug 9'!$F$8:$F$42=$T14)*'Aug 9'!$AJ$8:$AJ$42+('Aug 9'!$G$8:$G$42=$T14)*'Aug 9'!$AK$8:$AK$42) -> 0 | AD14: =SUMPRODUCT(('Aug 10'!$F$8:$F$42=$T14)*'Aug 10'!$AJ$8:$AJ$42+('Aug 10'!$G$8:$G$42=$T14)*'Aug 10'!$AK$8:$AK$42) -> 0 | AE14: =SUMPRODUCT(('Aug 11'!$F$8:$F$42=$T14)*'Aug 11'!$AJ$8:$AJ$42+('Aug 11'!$G$8:$G$42=$T14)*'Aug 11'!$AK$8:$AK$42) -> 0 | AF14: =SUMPRODUCT(('Aug 12'!$F$8:$F$42=$T14)*'Aug 12'!$AJ$8:$AJ$42+('Aug 12'!$G$8:$G$42=$T14)*'Aug 12'!$AK$8:$AK$42) -> 0 | AG14: =SUMPRODUCT(('Aug 13'!$F$8:$F$42=$T14)*'Aug 13'!$AJ$8:$AJ$42+('Aug 13'!$G$8:$G$42=$T14)*'Aug 13'!$AK$8:$AK$42) -> 0 | AH14: =SUMPRODUCT(('Aug 14'!$F$8:$F$42=$T14)*'Aug 14'!$AJ$8:$AJ$42+('Aug 14'!$G$8:$G$42=$T14)*'Aug 14'!$AK$8:$AK$42) -> 0 | AI14: =SUMPRODUCT(('Aug 15'!$F$8:$F$42=$T14)*'Aug 15'!$AJ$8:$AJ$42+('Aug 15'!$G$8:$G$42=$T14)*'Aug 15'!$AK$8:$AK$42) -> 0 | AJ14: =SUMPRODUCT(('Aug 16'!$F$8:$F$42=$T14)*'Aug 16'!$AJ$8:$AJ$42+('Aug 16'!$G$8:$G$42=$T14)*'Aug 16'!$AK$8:$AK$42) -> 0 | AK14: =SUMPRODUCT(('Aug 17'!$F$8:$F$42=$T14)*'Aug 17'!$AJ$8:$AJ$42+('Aug 17'!$G$8:$G$42=$T14)*'Aug 17'!$AK$8:$AK$42) -> 0 | AL14: =SUMPRODUCT(('Aug 18'!$F$8:$F$42=$T14)*'Aug 18'!$AJ$8:$AJ$42+('Aug 18'!$G$8:$G$42=$T14)*'Aug 18'!$AK$8:$AK$42) -> 0 | AM14: =SUMPRODUCT(('Aug 19'!$F$8:$F$42=$T14)*'Aug 19'!$AJ$8:$AJ$42+('Aug 19'!$G$8:$G$42=$T14)*'Aug 19'!$AK$8:$AK$42) -> 0 | AN14: =SUMPRODUCT(('Aug 20'!$F$8:$F$42=$T14)*'Aug 20'!$AJ$8:$AJ$42+('Aug 20'!$G$8:$G$42=$T14)*'Aug 20'!$AK$8:$AK$42) -> 0 | AO14: =SUMPRODUCT(('Aug 21'!$F$8:$F$42=$T14)*'Aug 21'!$AJ$8:$AJ$42+('Aug 21'!$G$8:$G$42=$T14)*'Aug 21'!$AK$8:$AK$42) -> 0 | AP14: =SUMPRODUCT(('Aug 22'!$F$8:$F$42=$T14)*'Aug 22'!$AJ$8:$AJ$42+('Aug 22'!$G$8:$G$42=$T14)*'Aug 22'!$AK$8:$AK$42) -> 0 | AQ14: =SUMPRODUCT(('Aug 23'!$F$8:$F$42=$T14)*'Aug 23'!$AJ$8:$AJ$42+('Aug 23'!$G$8:$G$42=$T14)*'Aug 23'!$AK$8:$AK$42) -> 0 | AR14: =SUMPRODUCT(('Aug 24'!$F$8:$F$42=$T14)*'Aug 24'!$AJ$8:$AJ$42+('Aug 24'!$G$8:$G$42=$T14)*'Aug 24'!$AK$8:$AK$42) -> 0 | AS14: =SUMPRODUCT(('Aug 25'!$F$8:$F$42=$T14)*'Aug 25'!$AJ$8:$AJ$42+('Aug 25'!$G$8:$G$42=$T14)*'Aug 25'!$AK$8:$AK$42) -> 0 | AT14: =SUMPRODUCT(('Aug 26'!$F$8:$F$42=$T14)*'Aug 26'!$AJ$8:$AJ$42+('Aug 26'!$G$8:$G$42=$T14)*'Aug 26'!$AK$8:$AK$42) -> 0 | AU14: =SUMPRODUCT(('Aug 27'!$F$8:$F$42=$T14)*'Aug 27'!$AJ$8:$AJ$42+('Aug 27'!$G$8:$G$42=$T14)*'Aug 27'!$AK$8:$AK$42) -> 0 | AV14: =SUMPRODUCT(('Aug 28'!$F$8:$F$42=$T14)*'Aug 28'!$AJ$8:$AJ$42+('Aug 28'!$G$8:$G$42=$T14)*'Aug 28'!$AK$8:$AK$42) -> 0 | AW14: =SUMPRODUCT(('Aug 29'!$F$8:$F$42=$T14)*'Aug 29'!$AJ$8:$AJ$42+('Aug 29'!$G$8:$G$42=$T14)*'Aug 29'!$AK$8:$AK$42) -> 0 | AX14: =SUMPRODUCT(('Aug 30'!$F$8:$F$42=$T14)*'Aug 30'!$AJ$8:$AJ$42+('Aug 30'!$G$8:$G$42=$T14)*'Aug 30'!$AK$8:$AK$42) -> 0 | AY14: =SUMPRODUCT(('Aug 31'!$F$8:$F$42=$T14)*'Aug 31'!$AJ$8:$AJ$42+('Aug 31'!$G$8:$G$42=$T14)*'Aug 31'!$AK$8:$AK$42) -> 0 | BA14: =SUM(U14:AD14) -> 0 | BB14: =MATCH(BD14,'Pay Plan'!$C$6:$C$12,1) -> 1 | BC14: =SUMPRODUCT(('Aug 1'!$F$8:$F$42=$T14)*'Aug 1'!$AI$8:$AI$42*(('Aug 1'!$AM$8:$AM$42="Y")+('Aug 1'!$AN$8:$AN$42="Y")+('Aug 1'!$AO$8:$AO$42="Y")))+SUMPRODUCT(('Aug 2'!$F$8:$F$42=$T14)*'Aug 2'!$AI$8:$AI$42*(('Aug 2'!$AM$8:$AM$42="Y")+('Aug 2'!$AN$8:$AN$42="Y")+('Aug 2'!$AO$8:$AO$42="Y")))+SUMPRODUCT(('Aug 3'!$F$8:$F$42=$T14)*'Aug 3'!$AI$8:$AI$42*(('Aug 3'!$AM$8:$AM$42="Y")+('Aug 3'!$AN$8:$AN$42="Y")+('Aug 3'!$AO$8:$AO$42="Y")))+SUMPRODUCT(('Aug 4'!$F$8:$F$42=$T14)*'Aug 4'!$AI$8:$AI$42*(('Aug 4'!$AM$8:$AM$42="Y")+('Aug 4'!$AN$8:$AN$42="Y")+('Aug 4'!$AO$8:$AO$42="Y")))+SUMPRODUCT(('Aug 5'!$F$8:$F$42=$T14)*'Aug 5'!$AI$8:$AI$42*(('Aug 5'!$AM$8:$AM$42="Y")+('Aug 5'!$AN$8:$AN$42="Y")+('Aug 5'!$AO$8:$AO$42="Y")))+SUMPRODUCT(('Aug 6'!$F$8:$F$42=$T14)*'Aug 6'!$AI$8:$AI$42*(('Aug 6'!$AM$8:$AM$42="Y")+('Aug 6'!$AN$8:$AN$42="Y")+('Aug 6'!$AO$8:$AO$42="Y")))+SUMPRODUCT(('Aug 7'!$F$8:$F$42=$T14)*'Aug 7'!$AI$8:$AI$42*(('Aug 7'!$AM$8:$AM$42="Y")+('Aug 7'!$AN$8:$AN$42="Y")+('Aug 7'!$AO$8:$AO$42="Y")))+SUMPRODUCT(('Aug 8'!$F$8:$F$42=$T14)*'Aug 8'!$AI$8:$AI$42*(('Aug 8'!$AM$8:$AM$42="Y")+('Aug 8'!$AN$8:$AN$42="Y")+('Aug 8'!$AO$8:$AO$42="Y")))+SUMPRODUCT(('Aug 9'!$F$8:$F$42=$T14)*'Aug 9'!$AI$8:$AI$42*(('Aug 9'!$AM$8:$AM$42="Y")+('Aug 9'!$AN$8:$AN$42="Y")+('Aug 9'!$AO$8:$AO$42="Y")))+SUMPRODUCT(('Aug 10'!$F$8:$F$42=$T14)*'Aug 10'!$AI$8:$AI$42*(('Aug 10'!$AM$8:$AM$42="Y")+('Aug 10'!$AN$8:$AN$42="Y")+('Aug 10'!$AO$8:$AO$42="Y")))+SUMPRODUCT(('Aug 11'!$F$8:$F$42=$T14)*'Aug 11'!$AI$8:$AI$42*(('Aug 11'!$AM$8:$AM$42="Y")+('Aug 11'!$AN$8:$AN$42="Y")+('Aug 11'!$AO$8:$AO$42="Y")))+SUMPRODUCT(('Aug 12'!$F$8:$F$42=$T14)*'Aug 12'!$AI$8:$AI$42*(('Aug 12'!$AM$8:$AM$42="Y")+('Aug 12'!$AN$8:$AN$42="Y")+('Aug 12'!$AO$8:$AO$42="Y")))+SUMPRODUCT(('Aug 13'!$F$8:$F$42=$T14)*'Aug 13'!$AI$8:$AI$42*(('Aug 13'!$AM$8:$AM$42="Y")+('Aug 13'!$AN$8:$AN$42="Y")+('Aug 13'!$AO$8:$AO$42="Y")))+SUMPRODUCT(('Aug 14'!$F$8:$F$42=$T14)*'Aug 14'!$AI$8:$AI$42*(('Aug 14'!$AM$8:$AM$42="Y")+('Aug 14'!$AN$8:$AN$42="Y")+('Aug 14'!$AO$8:$AO$42="Y")))+SUMPRODUCT(('Aug 15'!$F$8:$F$42=$T14)*'Aug 15'!$AI$8:$AI$42*(('Aug 15'!$AM$8:$AM$42="Y")+('Aug 15'!$AN$8:$AN$42="Y")+('Aug 15'!$AO$8:$AO$42="Y")))+SUMPRODUCT(('Aug 16'!$F$8:$F$42=$T14)*'Aug 16'!$AI$8:$AI$42*(('Aug 16'!$AM$8:$AM$42="Y")+('Aug 16'!$AN$8:$AN$42="Y")+('Aug 16'!$AO$8:$AO$42="Y")))+SUMPRODUCT(('Aug 17'!$F$8:$F$42=$T14)*'Aug 17'!$AI$8:$AI$42*(('Aug 17'!$AM$8:$AM$42="Y")+('Aug 17'!$AN$8:$AN$42="Y")+('Aug 17'!$AO$8:$AO$42="Y")))+SUMPRODUCT(('Aug 18'!$F$8:$F$42=$T14)*'Aug 18'!$AI$8:$AI$42*(('Aug 18'!$AM$8:$AM$42="Y")+('Aug 18'!$AN$8:$AN$42="Y")+('Aug 18'!$AO$8:$AO$42="Y")))+SUMPRODUCT(('Aug 19'!$F$8:$F$42=$T14)*'Aug 19'!$AI$8:$AI$42*(('Aug 19'!$AM$8:$AM$42="Y")+('Aug 19'!$AN$8:$AN$42="Y")+('Aug 19'!$AO$8:$AO$42="Y")))+SUMPRODUCT(('Aug 20'!$F$8:$F$42=$T14)*'Aug 20'!$AI$8:$AI$42*(('Aug 20'!$AM$8:$AM$42="Y")+('Aug 20'!$AN$8:$AN$42="Y")+('Aug 20'!$AO$8:$AO$42="Y")))+SUMPRODUCT(('Aug 21'!$F$8:$F$42=$T14)*'Aug 21'!$AI$8:$AI$42*(('Aug 21'!$AM$8:$AM$42="Y")+('Aug 21'!$AN$8:$AN$42="Y")+('Aug 21'!$AO$8:$AO$42="Y")))+SUMPRODUCT(('Aug 22'!$F$8:$F$42=$T14)*'Aug 22'!$AI$8:$AI$42*(('Aug 22'!$AM$8:$AM$42="Y")+('Aug 22'!$AN$8:$AN$42="Y")+('Aug 22'!$AO$8:$AO$42="Y")))+SUMPRODUCT(('Aug 23'!$F$8:$F$42=$T14)*'Aug 23'!$AI$8:$AI$42*(('Aug 23'!$AM$8:$AM$42="Y")+('Aug 23'!$AN$8:$AN$42="Y")+('Aug 23'!$AO$8:$AO$42="Y")))+SUMPRODUCT(('Aug 24'!$F$8:$F$42=$T14)*'Aug 24'!$AI$8:$AI$42*(('Aug 24'!$AM$8:$AM$42="Y")+('Aug 24'!$AN$8:$AN$42="Y")+('Aug 24'!$AO$8:$AO$42="Y")))+SUMPRODUCT(('Aug 25'!$F$8:$F$42=$T14)*'Aug 25'!$AI$8:$AI$42*(('Aug 25'!$AM$8:$AM$42="Y")+('Aug 25'!$AN$8:$AN$42="Y")+('Aug 25'!$AO$8:$AO$42="Y")))+SUMPRODUCT(('Aug 26'!$F$8:$F$42=$T14)*'Aug 26'!$AI$8:$AI$42*(('Aug 26'!$AM$8:$AM$42="Y")+('Aug 26'!$AN$8:$AN$42="Y")+('Aug 26'!$AO$8:$AO$42="Y")))+SUMPRODUCT(('Aug 27'!$F$8:$F$42=$T14)*'Aug 27'!$AI$8:$AI$42*(('Aug 27'!$AM$8:$AM$42="Y")+('Aug 27'!$AN$8:$AN$42="Y")+('Aug 27'!$AO$8:$AO$42="Y")))+SUMPRODUCT(('Aug 28'!$F$8:$F$42=$T14)*'Aug 28'!$AI$8:$AI$42*(('Aug 28'!$AM$8:$AM$42="Y")+('Aug 28'!$AN$8:$AN$42="Y")+('Aug 28'!$AO$8:$AO$42="Y")))+SUMPRODUCT(('Aug 29'!$F$8:$F$42=$T14)*'Aug 29'!$AI$8:$AI$42*(('Aug 29'!$AM$8:$AM$42="Y")+('Aug 29'!$AN$8:$AN$42="Y")+('Aug 29'!$AO$8:$AO$42="Y")))+SUMPRODUCT(('Aug 30'!$F$8:$F$42=$T14)*'Aug 30'!$AI$8:$AI$42*(('Aug 30'!$AM$8:$AM$42="Y")+('Aug 30'!$AN$8:$AN$42="Y")+('Aug 30'!$AO$8:$AO$42="Y")))+SUMPRODUCT(('Aug 31'!$F$8:$F$42=$T14)*'Aug 31'!$AI$8:$AI$42*(('Aug 31'!$AM$8:$AM$42="Y")+('Aug 31'!$AN$8:$AN$42="Y")+('Aug 31'!$AO$8:$AO$42="Y"))) -> 0 | BD14: =SUM(U14:AY14) -> 0 | BE14: =SUM(U33:AY33) -> 0 | BF14: =SUM(U52:AY52) -> 0
A15: 9 | B15: =$T12 -> ZACH CUPP | C15: =BD12 -> 0 | D15: =BE12 -> 0 | E15: =IF(BD12=0,"—",BE12/BD12) -> — | F15: =IF(BD12=0,"—",INDEX('Pay Plan'!$B$6:$B$12,BB12)) -> — | G15: =BF12 -> 0 | H15: =LOOKUP(BD12,'Pay Plan'!$B$15:$B$20,'Pay Plan'!$C$15:$C$20) -> 0 | I15: =LOOKUP(BA12,'Pay Plan'!$E$15:$E$19,'Pay Plan'!$F$15:$F$19) -> 0 | J15: =BC12*'Pay Plan'!$I$15 -> 0 | K15: =G15+H15+I15+J15 -> 0 | O15: =K15-N15 -> 0 | T15: ='Staff & Lists'!A16 -> JACOB LICHTENSTRAHL | U15: =SUMPRODUCT(('Aug 1'!$F$8:$F$42=$T15)*'Aug 1'!$AJ$8:$AJ$42+('Aug 1'!$G$8:$G$42=$T15)*'Aug 1'!$AK$8:$AK$42) -> 0 | V15: =SUMPRODUCT(('Aug 2'!$F$8:$F$42=$T15)*'Aug 2'!$AJ$8:$AJ$42+('Aug 2'!$G$8:$G$42=$T15)*'Aug 2'!$AK$8:$AK$42) -> 0 | W15: =SUMPRODUCT(('Aug 3'!$F$8:$F$42=$T15)*'Aug 3'!$AJ$8:$AJ$42+('Aug 3'!$G$8:$G$42=$T15)*'Aug 3'!$AK$8:$AK$42) -> 0 | X15: =SUMPRODUCT(('Aug 4'!$F$8:$F$42=$T15)*'Aug 4'!$AJ$8:$AJ$42+('Aug 4'!$G$8:$G$42=$T15)*'Aug 4'!$AK$8:$AK$42) -> 0 | Y15: =SUMPRODUCT(('Aug 5'!$F$8:$F$42=$T15)*'Aug 5'!$AJ$8:$AJ$42+('Aug 5'!$G$8:$G$42=$T15)*'Aug 5'!$AK$8:$AK$42) -> 0 | Z15: =SUMPRODUCT(('Aug 6'!$F$8:$F$42=$T15)*'Aug 6'!$AJ$8:$AJ$42+('Aug 6'!$G$8:$G$42=$T15)*'Aug 6'!$AK$8:$AK$42) -> 0 | AA15: =SUMPRODUCT(('Aug 7'!$F$8:$F$42=$T15)*'Aug 7'!$AJ$8:$AJ$42+('Aug 7'!$G$8:$G$42=$T15)*'Aug 7'!$AK$8:$AK$42) -> 0 | AB15: =SUMPRODUCT(('Aug 8'!$F$8:$F$42=$T15)*'Aug 8'!$AJ$8:$AJ$42+('Aug 8'!$G$8:$G$42=$T15)*'Aug 8'!$AK$8:$AK$42) -> 0 | AC15: =SUMPRODUCT(('Aug 9'!$F$8:$F$42=$T15)*'Aug 9'!$AJ$8:$AJ$42+('Aug 9'!$G$8:$G$42=$T15)*'Aug 9'!$AK$8:$AK$42) -> 0 | AD15: =SUMPRODUCT(('Aug 10'!$F$8:$F$42=$T15)*'Aug 10'!$AJ$8:$AJ$42+('Aug 10'!$G$8:$G$42=$T15)*'Aug 10'!$AK$8:$AK$42) -> 0 | AE15: =SUMPRODUCT(('Aug 11'!$F$8:$F$42=$T15)*'Aug 11'!$AJ$8:$AJ$42+('Aug 11'!$G$8:$G$42=$T15)*'Aug 11'!$AK$8:$AK$42) -> 0 | AF15: =SUMPRODUCT(('Aug 12'!$F$8:$F$42=$T15)*'Aug 12'!$AJ$8:$AJ$42+('Aug 12'!$G$8:$G$42=$T15)*'Aug 12'!$AK$8:$AK$42) -> 0 | AG15: =SUMPRODUCT(('Aug 13'!$F$8:$F$42=$T15)*'Aug 13'!$AJ$8:$AJ$42+('Aug 13'!$G$8:$G$42=$T15)*'Aug 13'!$AK$8:$AK$42) -> 0 | AH15: =SUMPRODUCT(('Aug 14'!$F$8:$F$42=$T15)*'Aug 14'!$AJ$8:$AJ$42+('Aug 14'!$G$8:$G$42=$T15)*'Aug 14'!$AK$8:$AK$42) -> 0 | AI15: =SUMPRODUCT(('Aug 15'!$F$8:$F$42=$T15)*'Aug 15'!$AJ$8:$AJ$42+('Aug 15'!$G$8:$G$42=$T15)*'Aug 15'!$AK$8:$AK$42) -> 0 | AJ15: =SUMPRODUCT(('Aug 16'!$F$8:$F$42=$T15)*'Aug 16'!$AJ$8:$AJ$42+('Aug 16'!$G$8:$G$42=$T15)*'Aug 16'!$AK$8:$AK$42) -> 0 | AK15: =SUMPRODUCT(('Aug 17'!$F$8:$F$42=$T15)*'Aug 17'!$AJ$8:$AJ$42+('Aug 17'!$G$8:$G$42=$T15)*'Aug 17'!$AK$8:$AK$42) -> 0 | AL15: =SUMPRODUCT(('Aug 18'!$F$8:$F$42=$T15)*'Aug 18'!$AJ$8:$AJ$42+('Aug 18'!$G$8:$G$42=$T15)*'Aug 18'!$AK$8:$AK$42) -> 0 | AM15: =SUMPRODUCT(('Aug 19'!$F$8:$F$42=$T15)*'Aug 19'!$AJ$8:$AJ$42+('Aug 19'!$G$8:$G$42=$T15)*'Aug 19'!$AK$8:$AK$42) -> 0 | AN15: =SUMPRODUCT(('Aug 20'!$F$8:$F$42=$T15)*'Aug 20'!$AJ$8:$AJ$42+('Aug 20'!$G$8:$G$42=$T15)*'Aug 20'!$AK$8:$AK$42) -> 0 | AO15: =SUMPRODUCT(('Aug 21'!$F$8:$F$42=$T15)*'Aug 21'!$AJ$8:$AJ$42+('Aug 21'!$G$8:$G$42=$T15)*'Aug 21'!$AK$8:$AK$42) -> 0 | AP15: =SUMPRODUCT(('Aug 22'!$F$8:$F$42=$T15)*'Aug 22'!$AJ$8:$AJ$42+('Aug 22'!$G$8:$G$42=$T15)*'Aug 22'!$AK$8:$AK$42) -> 0 | AQ15: =SUMPRODUCT(('Aug 23'!$F$8:$F$42=$T15)*'Aug 23'!$AJ$8:$AJ$42+('Aug 23'!$G$8:$G$42=$T15)*'Aug 23'!$AK$8:$AK$42) -> 0 | AR15: =SUMPRODUCT(('Aug 24'!$F$8:$F$42=$T15)*'Aug 24'!$AJ$8:$AJ$42+('Aug 24'!$G$8:$G$42=$T15)*'Aug 24'!$AK$8:$AK$42) -> 0 | AS15: =SUMPRODUCT(('Aug 25'!$F$8:$F$42=$T15)*'Aug 25'!$AJ$8:$AJ$42+('Aug 25'!$G$8:$G$42=$T15)*'Aug 25'!$AK$8:$AK$42) -> 0 | AT15: =SUMPRODUCT(('Aug 26'!$F$8:$F$42=$T15)*'Aug 26'!$AJ$8:$AJ$42+('Aug 26'!$G$8:$G$42=$T15)*'Aug 26'!$AK$8:$AK$42) -> 0 | AU15: =SUMPRODUCT(('Aug 27'!$F$8:$F$42=$T15)*'Aug 27'!$AJ$8:$AJ$42+('Aug 27'!$G$8:$G$42=$T15)*'Aug 27'!$AK$8:$AK$42) -> 0 | AV15: =SUMPRODUCT(('Aug 28'!$F$8:$F$42=$T15)*'Aug 28'!$AJ$8:$AJ$42+('Aug 28'!$G$8:$G$42=$T15)*'Aug 28'!$AK$8:$AK$42) -> 0 | AW15: =SUMPRODUCT(('Aug 29'!$F$8:$F$42=$T15)*'Aug 29'!$AJ$8:$AJ$42+('Aug 29'!$G$8:$G$42=$T15)*'Aug 29'!$AK$8:$AK$42) -> 0 | AX15: =SUMPRODUCT(('Aug 30'!$F$8:$F$42=$T15)*'Aug 30'!$AJ$8:$AJ$42+('Aug 30'!$G$8:$G$42=$T15)*'Aug 30'!$AK$8:$AK$42) -> 0 | AY15: =SUMPRODUCT(('Aug 31'!$F$8:$F$42=$T15)*'Aug 31'!$AJ$8:$AJ$42+('Aug 31'!$G$8:$G$42=$T15)*'Aug 31'!$AK$8:$AK$42) -> 0 | BA15: =SUM(U15:AD15) -> 0 | BB15: =MATCH(BD15,'Pay Plan'!$C$6:$C$12,1) -> 1 | BC15: =SUMPRODUCT(('Aug 1'!$F$8:$F$42=$T15)*'Aug 1'!$AI$8:$AI$42*(('Aug 1'!$AM$8:$AM$42="Y")+('Aug 1'!$AN$8:$AN$42="Y")+('Aug 1'!$AO$8:$AO$42="Y")))+SUMPRODUCT(('Aug 2'!$F$8:$F$42=$T15)*'Aug 2'!$AI$8:$AI$42*(('Aug 2'!$AM$8:$AM$42="Y")+('Aug 2'!$AN$8:$AN$42="Y")+('Aug 2'!$AO$8:$AO$42="Y")))+SUMPRODUCT(('Aug 3'!$F$8:$F$42=$T15)*'Aug 3'!$AI$8:$AI$42*(('Aug 3'!$AM$8:$AM$42="Y")+('Aug 3'!$AN$8:$AN$42="Y")+('Aug 3'!$AO$8:$AO$42="Y")))+SUMPRODUCT(('Aug 4'!$F$8:$F$42=$T15)*'Aug 4'!$AI$8:$AI$42*(('Aug 4'!$AM$8:$AM$42="Y")+('Aug 4'!$AN$8:$AN$42="Y")+('Aug 4'!$AO$8:$AO$42="Y")))+SUMPRODUCT(('Aug 5'!$F$8:$F$42=$T15)*'Aug 5'!$AI$8:$AI$42*(('Aug 5'!$AM$8:$AM$42="Y")+('Aug 5'!$AN$8:$AN$42="Y")+('Aug 5'!$AO$8:$AO$42="Y")))+SUMPRODUCT(('Aug 6'!$F$8:$F$42=$T15)*'Aug 6'!$AI$8:$AI$42*(('Aug 6'!$AM$8:$AM$42="Y")+('Aug 6'!$AN$8:$AN$42="Y")+('Aug 6'!$AO$8:$AO$42="Y")))+SUMPRODUCT(('Aug 7'!$F$8:$F$42=$T15)*'Aug 7'!$AI$8:$AI$42*(('Aug 7'!$AM$8:$AM$42="Y")+('Aug 7'!$AN$8:$AN$42="Y")+('Aug 7'!$AO$8:$AO$42="Y")))+SUMPRODUCT(('Aug 8'!$F$8:$F$42=$T15)*'Aug 8'!$AI$8:$AI$42*(('Aug 8'!$AM$8:$AM$42="Y")+('Aug 8'!$AN$8:$AN$42="Y")+('Aug 8'!$AO$8:$AO$42="Y")))+SUMPRODUCT(('Aug 9'!$F$8:$F$42=$T15)*'Aug 9'!$AI$8:$AI$42*(('Aug 9'!$AM$8:$AM$42="Y")+('Aug 9'!$AN$8:$AN$42="Y")+('Aug 9'!$AO$8:$AO$42="Y")))+SUMPRODUCT(('Aug 10'!$F$8:$F$42=$T15)*'Aug 10'!$AI$8:$AI$42*(('Aug 10'!$AM$8:$AM$42="Y")+('Aug 10'!$AN$8:$AN$42="Y")+('Aug 10'!$AO$8:$AO$42="Y")))+SUMPRODUCT(('Aug 11'!$F$8:$F$42=$T15)*'Aug 11'!$AI$8:$AI$42*(('Aug 11'!$AM$8:$AM$42="Y")+('Aug 11'!$AN$8:$AN$42="Y")+('Aug 11'!$AO$8:$AO$42="Y")))+SUMPRODUCT(('Aug 12'!$F$8:$F$42=$T15)*'Aug 12'!$AI$8:$AI$42*(('Aug 12'!$AM$8:$AM$42="Y")+('Aug 12'!$AN$8:$AN$42="Y")+('Aug 12'!$AO$8:$AO$42="Y")))+SUMPRODUCT(('Aug 13'!$F$8:$F$42=$T15)*'Aug 13'!$AI$8:$AI$42*(('Aug 13'!$AM$8:$AM$42="Y")+('Aug 13'!$AN$8:$AN$42="Y")+('Aug 13'!$AO$8:$AO$42="Y")))+SUMPRODUCT(('Aug 14'!$F$8:$F$42=$T15)*'Aug 14'!$AI$8:$AI$42*(('Aug 14'!$AM$8:$AM$42="Y")+('Aug 14'!$AN$8:$AN$42="Y")+('Aug 14'!$AO$8:$AO$42="Y")))+SUMPRODUCT(('Aug 15'!$F$8:$F$42=$T15)*'Aug 15'!$AI$8:$AI$42*(('Aug 15'!$AM$8:$AM$42="Y")+('Aug 15'!$AN$8:$AN$42="Y")+('Aug 15'!$AO$8:$AO$42="Y")))+SUMPRODUCT(('Aug 16'!$F$8:$F$42=$T15)*'Aug 16'!$AI$8:$AI$42*(('Aug 16'!$AM$8:$AM$42="Y")+('Aug 16'!$AN$8:$AN$42="Y")+('Aug 16'!$AO$8:$AO$42="Y")))+SUMPRODUCT(('Aug 17'!$F$8:$F$42=$T15)*'Aug 17'!$AI$8:$AI$42*(('Aug 17'!$AM$8:$AM$42="Y")+('Aug 17'!$AN$8:$AN$42="Y")+('Aug 17'!$AO$8:$AO$42="Y")))+SUMPRODUCT(('Aug 18'!$F$8:$F$42=$T15)*'Aug 18'!$AI$8:$AI$42*(('Aug 18'!$AM$8:$AM$42="Y")+('Aug 18'!$AN$8:$AN$42="Y")+('Aug 18'!$AO$8:$AO$42="Y")))+SUMPRODUCT(('Aug 19'!$F$8:$F$42=$T15)*'Aug 19'!$AI$8:$AI$42*(('Aug 19'!$AM$8:$AM$42="Y")+('Aug 19'!$AN$8:$AN$42="Y")+('Aug 19'!$AO$8:$AO$42="Y")))+SUMPRODUCT(('Aug 20'!$F$8:$F$42=$T15)*'Aug 20'!$AI$8:$AI$42*(('Aug 20'!$AM$8:$AM$42="Y")+('Aug 20'!$AN$8:$AN$42="Y")+('Aug 20'!$AO$8:$AO$42="Y")))+SUMPRODUCT(('Aug 21'!$F$8:$F$42=$T15)*'Aug 21'!$AI$8:$AI$42*(('Aug 21'!$AM$8:$AM$42="Y")+('Aug 21'!$AN$8:$AN$42="Y")+('Aug 21'!$AO$8:$AO$42="Y")))+SUMPRODUCT(('Aug 22'!$F$8:$F$42=$T15)*'Aug 22'!$AI$8:$AI$42*(('Aug 22'!$AM$8:$AM$42="Y")+('Aug 22'!$AN$8:$AN$42="Y")+('Aug 22'!$AO$8:$AO$42="Y")))+SUMPRODUCT(('Aug 23'!$F$8:$F$42=$T15)*'Aug 23'!$AI$8:$AI$42*(('Aug 23'!$AM$8:$AM$42="Y")+('Aug 23'!$AN$8:$AN$42="Y")+('Aug 23'!$AO$8:$AO$42="Y")))+SUMPRODUCT(('Aug 24'!$F$8:$F$42=$T15)*'Aug 24'!$AI$8:$AI$42*(('Aug 24'!$AM$8:$AM$42="Y")+('Aug 24'!$AN$8:$AN$42="Y")+('Aug 24'!$AO$8:$AO$42="Y")))+SUMPRODUCT(('Aug 25'!$F$8:$F$42=$T15)*'Aug 25'!$AI$8:$AI$42*(('Aug 25'!$AM$8:$AM$42="Y")+('Aug 25'!$AN$8:$AN$42="Y")+('Aug 25'!$AO$8:$AO$42="Y")))+SUMPRODUCT(('Aug 26'!$F$8:$F$42=$T15)*'Aug 26'!$AI$8:$AI$42*(('Aug 26'!$AM$8:$AM$42="Y")+('Aug 26'!$AN$8:$AN$42="Y")+('Aug 26'!$AO$8:$AO$42="Y")))+SUMPRODUCT(('Aug 27'!$F$8:$F$42=$T15)*'Aug 27'!$AI$8:$AI$42*(('Aug 27'!$AM$8:$AM$42="Y")+('Aug 27'!$AN$8:$AN$42="Y")+('Aug 27'!$AO$8:$AO$42="Y")))+SUMPRODUCT(('Aug 28'!$F$8:$F$42=$T15)*'Aug 28'!$AI$8:$AI$42*(('Aug 28'!$AM$8:$AM$42="Y")+('Aug 28'!$AN$8:$AN$42="Y")+('Aug 28'!$AO$8:$AO$42="Y")))+SUMPRODUCT(('Aug 29'!$F$8:$F$42=$T15)*'Aug 29'!$AI$8:$AI$42*(('Aug 29'!$AM$8:$AM$42="Y")+('Aug 29'!$AN$8:$AN$42="Y")+('Aug 29'!$AO$8:$AO$42="Y")))+SUMPRODUCT(('Aug 30'!$F$8:$F$42=$T15)*'Aug 30'!$AI$8:$AI$42*(('Aug 30'!$AM$8:$AM$42="Y")+('Aug 30'!$AN$8:$AN$42="Y")+('Aug 30'!$AO$8:$AO$42="Y")))+SUMPRODUCT(('Aug 31'!$F$8:$F$42=$T15)*'Aug 31'!$AI$8:$AI$42*(('Aug 31'!$AM$8:$AM$42="Y")+('Aug 31'!$AN$8:$AN$42="Y")+('Aug 31'!$AO$8:$AO$42="Y"))) -> 0 | BD15: =SUM(U15:AY15) -> 0 | BE15: =SUM(U34:AY34) -> 0 | BF15: =SUM(U53:AY53) -> 0
A16: 10 | B16: =$T13 -> ANDREW MIEIR | C16: =BD13 -> 0 | D16: =BE13 -> 0 | E16: =IF(BD13=0,"—",BE13/BD13) -> — | F16: =IF(BD13=0,"—",INDEX('Pay Plan'!$B$6:$B$12,BB13)) -> — | G16: =BF13 -> 0 | H16: =LOOKUP(BD13,'Pay Plan'!$B$15:$B$20,'Pay Plan'!$C$15:$C$20) -> 0 | I16: =LOOKUP(BA13,'Pay Plan'!$E$15:$E$19,'Pay Plan'!$F$15:$F$19) -> 0 | J16: =BC13*'Pay Plan'!$I$15 -> 0 | K16: =G16+H16+I16+J16 -> 0 | O16: =K16-N16 -> 0 | T16: ='Staff & Lists'!A17 -> BRAYDON JOHNSON | U16: =SUMPRODUCT(('Aug 1'!$F$8:$F$42=$T16)*'Aug 1'!$AJ$8:$AJ$42+('Aug 1'!$G$8:$G$42=$T16)*'Aug 1'!$AK$8:$AK$42) -> 0 | V16: =SUMPRODUCT(('Aug 2'!$F$8:$F$42=$T16)*'Aug 2'!$AJ$8:$AJ$42+('Aug 2'!$G$8:$G$42=$T16)*'Aug 2'!$AK$8:$AK$42) -> 0 | W16: =SUMPRODUCT(('Aug 3'!$F$8:$F$42=$T16)*'Aug 3'!$AJ$8:$AJ$42+('Aug 3'!$G$8:$G$42=$T16)*'Aug 3'!$AK$8:$AK$42) -> 0 | X16: =SUMPRODUCT(('Aug 4'!$F$8:$F$42=$T16)*'Aug 4'!$AJ$8:$AJ$42+('Aug 4'!$G$8:$G$42=$T16)*'Aug 4'!$AK$8:$AK$42) -> 0 | Y16: =SUMPRODUCT(('Aug 5'!$F$8:$F$42=$T16)*'Aug 5'!$AJ$8:$AJ$42+('Aug 5'!$G$8:$G$42=$T16)*'Aug 5'!$AK$8:$AK$42) -> 0 | Z16: =SUMPRODUCT(('Aug 6'!$F$8:$F$42=$T16)*'Aug 6'!$AJ$8:$AJ$42+('Aug 6'!$G$8:$G$42=$T16)*'Aug 6'!$AK$8:$AK$42) -> 0 | AA16: =SUMPRODUCT(('Aug 7'!$F$8:$F$42=$T16)*'Aug 7'!$AJ$8:$AJ$42+('Aug 7'!$G$8:$G$42=$T16)*'Aug 7'!$AK$8:$AK$42) -> 0 | AB16: =SUMPRODUCT(('Aug 8'!$F$8:$F$42=$T16)*'Aug 8'!$AJ$8:$AJ$42+('Aug 8'!$G$8:$G$42=$T16)*'Aug 8'!$AK$8:$AK$42) -> 0 | AC16: =SUMPRODUCT(('Aug 9'!$F$8:$F$42=$T16)*'Aug 9'!$AJ$8:$AJ$42+('Aug 9'!$G$8:$G$42=$T16)*'Aug 9'!$AK$8:$AK$42) -> 0 | AD16: =SUMPRODUCT(('Aug 10'!$F$8:$F$42=$T16)*'Aug 10'!$AJ$8:$AJ$42+('Aug 10'!$G$8:$G$42=$T16)*'Aug 10'!$AK$8:$AK$42) -> 0 | AE16: =SUMPRODUCT(('Aug 11'!$F$8:$F$42=$T16)*'Aug 11'!$AJ$8:$AJ$42+('Aug 11'!$G$8:$G$42=$T16)*'Aug 11'!$AK$8:$AK$42) -> 0 | AF16: =SUMPRODUCT(('Aug 12'!$F$8:$F$42=$T16)*'Aug 12'!$AJ$8:$AJ$42+('Aug 12'!$G$8:$G$42=$T16)*'Aug 12'!$AK$8:$AK$42) -> 0 | AG16: =SUMPRODUCT(('Aug 13'!$F$8:$F$42=$T16)*'Aug 13'!$AJ$8:$AJ$42+('Aug 13'!$G$8:$G$42=$T16)*'Aug 13'!$AK$8:$AK$42) -> 0 | AH16: =SUMPRODUCT(('Aug 14'!$F$8:$F$42=$T16)*'Aug 14'!$AJ$8:$AJ$42+('Aug 14'!$G$8:$G$42=$T16)*'Aug 14'!$AK$8:$AK$42) -> 0 | AI16: =SUMPRODUCT(('Aug 15'!$F$8:$F$42=$T16)*'Aug 15'!$AJ$8:$AJ$42+('Aug 15'!$G$8:$G$42=$T16)*'Aug 15'!$AK$8:$AK$42) -> 0 | AJ16: =SUMPRODUCT(('Aug 16'!$F$8:$F$42=$T16)*'Aug 16'!$AJ$8:$AJ$42+('Aug 16'!$G$8:$G$42=$T16)*'Aug 16'!$AK$8:$AK$42) -> 0 | AK16: =SUMPRODUCT(('Aug 17'!$F$8:$F$42=$T16)*'Aug 17'!$AJ$8:$AJ$42+('Aug 17'!$G$8:$G$42=$T16)*'Aug 17'!$AK$8:$AK$42) -> 0 | AL16: =SUMPRODUCT(('Aug 18'!$F$8:$F$42=$T16)*'Aug 18'!$AJ$8:$AJ$42+('Aug 18'!$G$8:$G$42=$T16)*'Aug 18'!$AK$8:$AK$42) -> 0 | AM16: =SUMPRODUCT(('Aug 19'!$F$8:$F$42=$T16)*'Aug 19'!$AJ$8:$AJ$42+('Aug 19'!$G$8:$G$42=$T16)*'Aug 19'!$AK$8:$AK$42) -> 0 | AN16: =SUMPRODUCT(('Aug 20'!$F$8:$F$42=$T16)*'Aug 20'!$AJ$8:$AJ$42+('Aug 20'!$G$8:$G$42=$T16)*'Aug 20'!$AK$8:$AK$42) -> 0 | AO16: =SUMPRODUCT(('Aug 21'!$F$8:$F$42=$T16)*'Aug 21'!$AJ$8:$AJ$42+('Aug 21'!$G$8:$G$42=$T16)*'Aug 21'!$AK$8:$AK$42) -> 0 | AP16: =SUMPRODUCT(('Aug 22'!$F$8:$F$42=$T16)*'Aug 22'!$AJ$8:$AJ$42+('Aug 22'!$G$8:$G$42=$T16)*'Aug 22'!$AK$8:$AK$42) -> 0 | AQ16: =SUMPRODUCT(('Aug 23'!$F$8:$F$42=$T16)*'Aug 23'!$AJ$8:$AJ$42+('Aug 23'!$G$8:$G$42=$T16)*'Aug 23'!$AK$8:$AK$42) -> 0 | AR16: =SUMPRODUCT(('Aug 24'!$F$8:$F$42=$T16)*'Aug 24'!$AJ$8:$AJ$42+('Aug 24'!$G$8:$G$42=$T16)*'Aug 24'!$AK$8:$AK$42) -> 0 | AS16: =SUMPRODUCT(('Aug 25'!$F$8:$F$42=$T16)*'Aug 25'!$AJ$8:$AJ$42+('Aug 25'!$G$8:$G$42=$T16)*'Aug 25'!$AK$8:$AK$42) -> 0 | AT16: =SUMPRODUCT(('Aug 26'!$F$8:$F$42=$T16)*'Aug 26'!$AJ$8:$AJ$42+('Aug 26'!$G$8:$G$42=$T16)*'Aug 26'!$AK$8:$AK$42) -> 0 | AU16: =SUMPRODUCT(('Aug 27'!$F$8:$F$42=$T16)*'Aug 27'!$AJ$8:$AJ$42+('Aug 27'!$G$8:$G$42=$T16)*'Aug 27'!$AK$8:$AK$42) -> 0 | AV16: =SUMPRODUCT(('Aug 28'!$F$8:$F$42=$T16)*'Aug 28'!$AJ$8:$AJ$42+('Aug 28'!$G$8:$G$42=$T16)*'Aug 28'!$AK$8:$AK$42) -> 0 | AW16: =SUMPRODUCT(('Aug 29'!$F$8:$F$42=$T16)*'Aug 29'!$AJ$8:$AJ$42+('Aug 29'!$G$8:$G$42=$T16)*'Aug 29'!$AK$8:$AK$42) -> 0 | AX16: =SUMPRODUCT(('Aug 30'!$F$8:$F$42=$T16)*'Aug 30'!$AJ$8:$AJ$42+('Aug 30'!$G$8:$G$42=$T16)*'Aug 30'!$AK$8:$AK$42) -> 0 | AY16: =SUMPRODUCT(('Aug 31'!$F$8:$F$42=$T16)*'Aug 31'!$AJ$8:$AJ$42+('Aug 31'!$G$8:$G$42=$T16)*'Aug 31'!$AK$8:$AK$42) -> 0 | BA16: =SUM(U16:AD16) -> 0 | BB16: =MATCH(BD16,'Pay Plan'!$C$6:$C$12,1) -> 1 | BC16: =SUMPRODUCT(('Aug 1'!$F$8:$F$42=$T16)*'Aug 1'!$AI$8:$AI$42*(('Aug 1'!$AM$8:$AM$42="Y")+('Aug 1'!$AN$8:$AN$42="Y")+('Aug 1'!$AO$8:$AO$42="Y")))+SUMPRODUCT(('Aug 2'!$F$8:$F$42=$T16)*'Aug 2'!$AI$8:$AI$42*(('Aug 2'!$AM$8:$AM$42="Y")+('Aug 2'!$AN$8:$AN$42="Y")+('Aug 2'!$AO$8:$AO$42="Y")))+SUMPRODUCT(('Aug 3'!$F$8:$F$42=$T16)*'Aug 3'!$AI$8:$AI$42*(('Aug 3'!$AM$8:$AM$42="Y")+('Aug 3'!$AN$8:$AN$42="Y")+('Aug 3'!$AO$8:$AO$42="Y")))+SUMPRODUCT(('Aug 4'!$F$8:$F$42=$T16)*'Aug 4'!$AI$8:$AI$42*(('Aug 4'!$AM$8:$AM$42="Y")+('Aug 4'!$AN$8:$AN$42="Y")+('Aug 4'!$AO$8:$AO$42="Y")))+SUMPRODUCT(('Aug 5'!$F$8:$F$42=$T16)*'Aug 5'!$AI$8:$AI$42*(('Aug 5'!$AM$8:$AM$42="Y")+('Aug 5'!$AN$8:$AN$42="Y")+('Aug 5'!$AO$8:$AO$42="Y")))+SUMPRODUCT(('Aug 6'!$F$8:$F$42=$T16)*'Aug 6'!$AI$8:$AI$42*(('Aug 6'!$AM$8:$AM$42="Y")+('Aug 6'!$AN$8:$AN$42="Y")+('Aug 6'!$AO$8:$AO$42="Y")))+SUMPRODUCT(('Aug 7'!$F$8:$F$42=$T16)*'Aug 7'!$AI$8:$AI$42*(('Aug 7'!$AM$8:$AM$42="Y")+('Aug 7'!$AN$8:$AN$42="Y")+('Aug 7'!$AO$8:$AO$42="Y")))+SUMPRODUCT(('Aug 8'!$F$8:$F$42=$T16)*'Aug 8'!$AI$8:$AI$42*(('Aug 8'!$AM$8:$AM$42="Y")+('Aug 8'!$AN$8:$AN$42="Y")+('Aug 8'!$AO$8:$AO$42="Y")))+SUMPRODUCT(('Aug 9'!$F$8:$F$42=$T16)*'Aug 9'!$AI$8:$AI$42*(('Aug 9'!$AM$8:$AM$42="Y")+('Aug 9'!$AN$8:$AN$42="Y")+('Aug 9'!$AO$8:$AO$42="Y")))+SUMPRODUCT(('Aug 10'!$F$8:$F$42=$T16)*'Aug 10'!$AI$8:$AI$42*(('Aug 10'!$AM$8:$AM$42="Y")+('Aug 10'!$AN$8:$AN$42="Y")+('Aug 10'!$AO$8:$AO$42="Y")))+SUMPRODUCT(('Aug 11'!$F$8:$F$42=$T16)*'Aug 11'!$AI$8:$AI$42*(('Aug 11'!$AM$8:$AM$42="Y")+('Aug 11'!$AN$8:$AN$42="Y")+('Aug 11'!$AO$8:$AO$42="Y")))+SUMPRODUCT(('Aug 12'!$F$8:$F$42=$T16)*'Aug 12'!$AI$8:$AI$42*(('Aug 12'!$AM$8:$AM$42="Y")+('Aug 12'!$AN$8:$AN$42="Y")+('Aug 12'!$AO$8:$AO$42="Y")))+SUMPRODUCT(('Aug 13'!$F$8:$F$42=$T16)*'Aug 13'!$AI$8:$AI$42*(('Aug 13'!$AM$8:$AM$42="Y")+('Aug 13'!$AN$8:$AN$42="Y")+('Aug 13'!$AO$8:$AO$42="Y")))+SUMPRODUCT(('Aug 14'!$F$8:$F$42=$T16)*'Aug 14'!$AI$8:$AI$42*(('Aug 14'!$AM$8:$AM$42="Y")+('Aug 14'!$AN$8:$AN$42="Y")+('Aug 14'!$AO$8:$AO$42="Y")))+SUMPRODUCT(('Aug 15'!$F$8:$F$42=$T16)*'Aug 15'!$AI$8:$AI$42*(('Aug 15'!$AM$8:$AM$42="Y")+('Aug 15'!$AN$8:$AN$42="Y")+('Aug 15'!$AO$8:$AO$42="Y")))+SUMPRODUCT(('Aug 16'!$F$8:$F$42=$T16)*'Aug 16'!$AI$8:$AI$42*(('Aug 16'!$AM$8:$AM$42="Y")+('Aug 16'!$AN$8:$AN$42="Y")+('Aug 16'!$AO$8:$AO$42="Y")))+SUMPRODUCT(('Aug 17'!$F$8:$F$42=$T16)*'Aug 17'!$AI$8:$AI$42*(('Aug 17'!$AM$8:$AM$42="Y")+('Aug 17'!$AN$8:$AN$42="Y")+('Aug 17'!$AO$8:$AO$42="Y")))+SUMPRODUCT(('Aug 18'!$F$8:$F$42=$T16)*'Aug 18'!$AI$8:$AI$42*(('Aug 18'!$AM$8:$AM$42="Y")+('Aug 18'!$AN$8:$AN$42="Y")+('Aug 18'!$AO$8:$AO$42="Y")))+SUMPRODUCT(('Aug 19'!$F$8:$F$42=$T16)*'Aug 19'!$AI$8:$AI$42*(('Aug 19'!$AM$8:$AM$42="Y")+('Aug 19'!$AN$8:$AN$42="Y")+('Aug 19'!$AO$8:$AO$42="Y")))+SUMPRODUCT(('Aug 20'!$F$8:$F$42=$T16)*'Aug 20'!$AI$8:$AI$42*(('Aug 20'!$AM$8:$AM$42="Y")+('Aug 20'!$AN$8:$AN$42="Y")+('Aug 20'!$AO$8:$AO$42="Y")))+SUMPRODUCT(('Aug 21'!$F$8:$F$42=$T16)*'Aug 21'!$AI$8:$AI$42*(('Aug 21'!$AM$8:$AM$42="Y")+('Aug 21'!$AN$8:$AN$42="Y")+('Aug 21'!$AO$8:$AO$42="Y")))+SUMPRODUCT(('Aug 22'!$F$8:$F$42=$T16)*'Aug 22'!$AI$8:$AI$42*(('Aug 22'!$AM$8:$AM$42="Y")+('Aug 22'!$AN$8:$AN$42="Y")+('Aug 22'!$AO$8:$AO$42="Y")))+SUMPRODUCT(('Aug 23'!$F$8:$F$42=$T16)*'Aug 23'!$AI$8:$AI$42*(('Aug 23'!$AM$8:$AM$42="Y")+('Aug 23'!$AN$8:$AN$42="Y")+('Aug 23'!$AO$8:$AO$42="Y")))+SUMPRODUCT(('Aug 24'!$F$8:$F$42=$T16)*'Aug 24'!$AI$8:$AI$42*(('Aug 24'!$AM$8:$AM$42="Y")+('Aug 24'!$AN$8:$AN$42="Y")+('Aug 24'!$AO$8:$AO$42="Y")))+SUMPRODUCT(('Aug 25'!$F$8:$F$42=$T16)*'Aug 25'!$AI$8:$AI$42*(('Aug 25'!$AM$8:$AM$42="Y")+('Aug 25'!$AN$8:$AN$42="Y")+('Aug 25'!$AO$8:$AO$42="Y")))+SUMPRODUCT(('Aug 26'!$F$8:$F$42=$T16)*'Aug 26'!$AI$8:$AI$42*(('Aug 26'!$AM$8:$AM$42="Y")+('Aug 26'!$AN$8:$AN$42="Y")+('Aug 26'!$AO$8:$AO$42="Y")))+SUMPRODUCT(('Aug 27'!$F$8:$F$42=$T16)*'Aug 27'!$AI$8:$AI$42*(('Aug 27'!$AM$8:$AM$42="Y")+('Aug 27'!$AN$8:$AN$42="Y")+('Aug 27'!$AO$8:$AO$42="Y")))+SUMPRODUCT(('Aug 28'!$F$8:$F$42=$T16)*'Aug 28'!$AI$8:$AI$42*(('Aug 28'!$AM$8:$AM$42="Y")+('Aug 28'!$AN$8:$AN$42="Y")+('Aug 28'!$AO$8:$AO$42="Y")))+SUMPRODUCT(('Aug 29'!$F$8:$F$42=$T16)*'Aug 29'!$AI$8:$AI$42*(('Aug 29'!$AM$8:$AM$42="Y")+('Aug 29'!$AN$8:$AN$42="Y")+('Aug 29'!$AO$8:$AO$42="Y")))+SUMPRODUCT(('Aug 30'!$F$8:$F$42=$T16)*'Aug 30'!$AI$8:$AI$42*(('Aug 30'!$AM$8:$AM$42="Y")+('Aug 30'!$AN$8:$AN$42="Y")+('Aug 30'!$AO$8:$AO$42="Y")))+SUMPRODUCT(('Aug 31'!$F$8:$F$42=$T16)*'Aug 31'!$AI$8:$AI$42*(('Aug 31'!$AM$8:$AM$42="Y")+('Aug 31'!$AN$8:$AN$42="Y")+('Aug 31'!$AO$8:$AO$42="Y"))) -> 0 | BD16: =SUM(U16:AY16) -> 0 | BE16: =SUM(U35:AY35) -> 0 | BF16: =SUM(U54:AY54) -> 0
A17: 11 | B17: =$T14 -> RAFAEL CAMPOS | C17: =BD14 -> 0 | D17: =BE14 -> 0 | E17: =IF(BD14=0,"—",BE14/BD14) -> — | F17: =IF(BD14=0,"—",INDEX('Pay Plan'!$B$6:$B$12,BB14)) -> — | G17: =BF14 -> 0 | H17: =LOOKUP(BD14,'Pay Plan'!$B$15:$B$20,'Pay Plan'!$C$15:$C$20) -> 0 | I17: =LOOKUP(BA14,'Pay Plan'!$E$15:$E$19,'Pay Plan'!$F$15:$F$19) -> 0 | J17: =BC14*'Pay Plan'!$I$15 -> 0 | K17: =G17+H17+I17+J17 -> 0 | O17: =K17-N17 -> 0 | T17: ='Staff & Lists'!A18 -> CHRIS HORNE | U17: =SUMPRODUCT(('Aug 1'!$F$8:$F$42=$T17)*'Aug 1'!$AJ$8:$AJ$42+('Aug 1'!$G$8:$G$42=$T17)*'Aug 1'!$AK$8:$AK$42) -> 0 | V17: =SUMPRODUCT(('Aug 2'!$F$8:$F$42=$T17)*'Aug 2'!$AJ$8:$AJ$42+('Aug 2'!$G$8:$G$42=$T17)*'Aug 2'!$AK$8:$AK$42) -> 0 | W17: =SUMPRODUCT(('Aug 3'!$F$8:$F$42=$T17)*'Aug 3'!$AJ$8:$AJ$42+('Aug 3'!$G$8:$G$42=$T17)*'Aug 3'!$AK$8:$AK$42) -> 0 | X17: =SUMPRODUCT(('Aug 4'!$F$8:$F$42=$T17)*'Aug 4'!$AJ$8:$AJ$42+('Aug 4'!$G$8:$G$42=$T17)*'Aug 4'!$AK$8:$AK$42) -> 0 | Y17: =SUMPRODUCT(('Aug 5'!$F$8:$F$42=$T17)*'Aug 5'!$AJ$8:$AJ$42+('Aug 5'!$G$8:$G$42=$T17)*'Aug 5'!$AK$8:$AK$42) -> 0 | Z17: =SUMPRODUCT(('Aug 6'!$F$8:$F$42=$T17)*'Aug 6'!$AJ$8:$AJ$42+('Aug 6'!$G$8:$G$42=$T17)*'Aug 6'!$AK$8:$AK$42) -> 0 | AA17: =SUMPRODUCT(('Aug 7'!$F$8:$F$42=$T17)*'Aug 7'!$AJ$8:$AJ$42+('Aug 7'!$G$8:$G$42=$T17)*'Aug 7'!$AK$8:$AK$42) -> 0 | AB17: =SUMPRODUCT(('Aug 8'!$F$8:$F$42=$T17)*'Aug 8'!$AJ$8:$AJ$42+('Aug 8'!$G$8:$G$42=$T17)*'Aug 8'!$AK$8:$AK$42) -> 0 | AC17: =SUMPRODUCT(('Aug 9'!$F$8:$F$42=$T17)*'Aug 9'!$AJ$8:$AJ$42+('Aug 9'!$G$8:$G$42=$T17)*'Aug 9'!$AK$8:$AK$42) -> 0 | AD17: =SUMPRODUCT(('Aug 10'!$F$8:$F$42=$T17)*'Aug 10'!$AJ$8:$AJ$42+('Aug 10'!$G$8:$G$42=$T17)*'Aug 10'!$AK$8:$AK$42) -> 0 | AE17: =SUMPRODUCT(('Aug 11'!$F$8:$F$42=$T17)*'Aug 11'!$AJ$8:$AJ$42+('Aug 11'!$G$8:$G$42=$T17)*'Aug 11'!$AK$8:$AK$42) -> 0 | AF17: =SUMPRODUCT(('Aug 12'!$F$8:$F$42=$T17)*'Aug 12'!$AJ$8:$AJ$42+('Aug 12'!$G$8:$G$42=$T17)*'Aug 12'!$AK$8:$AK$42) -> 0 | AG17: =SUMPRODUCT(('Aug 13'!$F$8:$F$42=$T17)*'Aug 13'!$AJ$8:$AJ$42+('Aug 13'!$G$8:$G$42=$T17)*'Aug 13'!$AK$8:$AK$42) -> 0 | AH17: =SUMPRODUCT(('Aug 14'!$F$8:$F$42=$T17)*'Aug 14'!$AJ$8:$AJ$42+('Aug 14'!$G$8:$G$42=$T17)*'Aug 14'!$AK$8:$AK$42) -> 0 | AI17: =SUMPRODUCT(('Aug 15'!$F$8:$F$42=$T17)*'Aug 15'!$AJ$8:$AJ$42+('Aug 15'!$G$8:$G$42=$T17)*'Aug 15'!$AK$8:$AK$42) -> 0 | AJ17: =SUMPRODUCT(('Aug 16'!$F$8:$F$42=$T17)*'Aug 16'!$AJ$8:$AJ$42+('Aug 16'!$G$8:$G$42=$T17)*'Aug 16'!$AK$8:$AK$42) -> 0 | AK17: =SUMPRODUCT(('Aug 17'!$F$8:$F$42=$T17)*'Aug 17'!$AJ$8:$AJ$42+('Aug 17'!$G$8:$G$42=$T17)*'Aug 17'!$AK$8:$AK$42) -> 0 | AL17: =SUMPRODUCT(('Aug 18'!$F$8:$F$42=$T17)*'Aug 18'!$AJ$8:$AJ$42+('Aug 18'!$G$8:$G$42=$T17)*'Aug 18'!$AK$8:$AK$42) -> 0 | AM17: =SUMPRODUCT(('Aug 19'!$F$8:$F$42=$T17)*'Aug 19'!$AJ$8:$AJ$42+('Aug 19'!$G$8:$G$42=$T17)*'Aug 19'!$AK$8:$AK$42) -> 0 | AN17: =SUMPRODUCT(('Aug 20'!$F$8:$F$42=$T17)*'Aug 20'!$AJ$8:$AJ$42+('Aug 20'!$G$8:$G$42=$T17)*'Aug 20'!$AK$8:$AK$42) -> 0 | AO17: =SUMPRODUCT(('Aug 21'!$F$8:$F$42=$T17)*'Aug 21'!$AJ$8:$AJ$42+('Aug 21'!$G$8:$G$42=$T17)*'Aug 21'!$AK$8:$AK$42) -> 0 | AP17: =SUMPRODUCT(('Aug 22'!$F$8:$F$42=$T17)*'Aug 22'!$AJ$8:$AJ$42+('Aug 22'!$G$8:$G$42=$T17)*'Aug 22'!$AK$8:$AK$42) -> 0 | AQ17: =SUMPRODUCT(('Aug 23'!$F$8:$F$42=$T17)*'Aug 23'!$AJ$8:$AJ$42+('Aug 23'!$G$8:$G$42=$T17)*'Aug 23'!$AK$8:$AK$42) -> 0 | AR17: =SUMPRODUCT(('Aug 24'!$F$8:$F$42=$T17)*'Aug 24'!$AJ$8:$AJ$42+('Aug 24'!$G$8:$G$42=$T17)*'Aug 24'!$AK$8:$AK$42) -> 0 | AS17: =SUMPRODUCT(('Aug 25'!$F$8:$F$42=$T17)*'Aug 25'!$AJ$8:$AJ$42+('Aug 25'!$G$8:$G$42=$T17)*'Aug 25'!$AK$8:$AK$42) -> 0 | AT17: =SUMPRODUCT(('Aug 26'!$F$8:$F$42=$T17)*'Aug 26'!$AJ$8:$AJ$42+('Aug 26'!$G$8:$G$42=$T17)*'Aug 26'!$AK$8:$AK$42) -> 0 | AU17: =SUMPRODUCT(('Aug 27'!$F$8:$F$42=$T17)*'Aug 27'!$AJ$8:$AJ$42+('Aug 27'!$G$8:$G$42=$T17)*'Aug 27'!$AK$8:$AK$42) -> 0 | AV17: =SUMPRODUCT(('Aug 28'!$F$8:$F$42=$T17)*'Aug 28'!$AJ$8:$AJ$42+('Aug 28'!$G$8:$G$42=$T17)*'Aug 28'!$AK$8:$AK$42) -> 0 | AW17: =SUMPRODUCT(('Aug 29'!$F$8:$F$42=$T17)*'Aug 29'!$AJ$8:$AJ$42+('Aug 29'!$G$8:$G$42=$T17)*'Aug 29'!$AK$8:$AK$42) -> 0 | AX17: =SUMPRODUCT(('Aug 30'!$F$8:$F$42=$T17)*'Aug 30'!$AJ$8:$AJ$42+('Aug 30'!$G$8:$G$42=$T17)*'Aug 30'!$AK$8:$AK$42) -> 0 | AY17: =SUMPRODUCT(('Aug 31'!$F$8:$F$42=$T17)*'Aug 31'!$AJ$8:$AJ$42+('Aug 31'!$G$8:$G$42=$T17)*'Aug 31'!$AK$8:$AK$42) -> 0 | BA17: =SUM(U17:AD17) -> 0 | BB17: =MATCH(BD17,'Pay Plan'!$C$6:$C$12,1) -> 1 | BC17: =SUMPRODUCT(('Aug 1'!$F$8:$F$42=$T17)*'Aug 1'!$AI$8:$AI$42*(('Aug 1'!$AM$8:$AM$42="Y")+('Aug 1'!$AN$8:$AN$42="Y")+('Aug 1'!$AO$8:$AO$42="Y")))+SUMPRODUCT(('Aug 2'!$F$8:$F$42=$T17)*'Aug 2'!$AI$8:$AI$42*(('Aug 2'!$AM$8:$AM$42="Y")+('Aug 2'!$AN$8:$AN$42="Y")+('Aug 2'!$AO$8:$AO$42="Y")))+SUMPRODUCT(('Aug 3'!$F$8:$F$42=$T17)*'Aug 3'!$AI$8:$AI$42*(('Aug 3'!$AM$8:$AM$42="Y")+('Aug 3'!$AN$8:$AN$42="Y")+('Aug 3'!$AO$8:$AO$42="Y")))+SUMPRODUCT(('Aug 4'!$F$8:$F$42=$T17)*'Aug 4'!$AI$8:$AI$42*(('Aug 4'!$AM$8:$AM$42="Y")+('Aug 4'!$AN$8:$AN$42="Y")+('Aug 4'!$AO$8:$AO$42="Y")))+SUMPRODUCT(('Aug 5'!$F$8:$F$42=$T17)*'Aug 5'!$AI$8:$AI$42*(('Aug 5'!$AM$8:$AM$42="Y")+('Aug 5'!$AN$8:$AN$42="Y")+('Aug 5'!$AO$8:$AO$42="Y")))+SUMPRODUCT(('Aug 6'!$F$8:$F$42=$T17)*'Aug 6'!$AI$8:$AI$42*(('Aug 6'!$AM$8:$AM$42="Y")+('Aug 6'!$AN$8:$AN$42="Y")+('Aug 6'!$AO$8:$AO$42="Y")))+SUMPRODUCT(('Aug 7'!$F$8:$F$42=$T17)*'Aug 7'!$AI$8:$AI$42*(('Aug 7'!$AM$8:$AM$42="Y")+('Aug 7'!$AN$8:$AN$42="Y")+('Aug 7'!$AO$8:$AO$42="Y")))+SUMPRODUCT(('Aug 8'!$F$8:$F$42=$T17)*'Aug 8'!$AI$8:$AI$42*(('Aug 8'!$AM$8:$AM$42="Y")+('Aug 8'!$AN$8:$AN$42="Y")+('Aug 8'!$AO$8:$AO$42="Y")))+SUMPRODUCT(('Aug 9'!$F$8:$F$42=$T17)*'Aug 9'!$AI$8:$AI$42*(('Aug 9'!$AM$8:$AM$42="Y")+('Aug 9'!$AN$8:$AN$42="Y")+('Aug 9'!$AO$8:$AO$42="Y")))+SUMPRODUCT(('Aug 10'!$F$8:$F$42=$T17)*'Aug 10'!$AI$8:$AI$42*(('Aug 10'!$AM$8:$AM$42="Y")+('Aug 10'!$AN$8:$AN$42="Y")+('Aug 10'!$AO$8:$AO$42="Y")))+SUMPRODUCT(('Aug 11'!$F$8:$F$42=$T17)*'Aug 11'!$AI$8:$AI$42*(('Aug 11'!$AM$8:$AM$42="Y")+('Aug 11'!$AN$8:$AN$42="Y")+('Aug 11'!$AO$8:$AO$42="Y")))+SUMPRODUCT(('Aug 12'!$F$8:$F$42=$T17)*'Aug 12'!$AI$8:$AI$42*(('Aug 12'!$AM$8:$AM$42="Y")+('Aug 12'!$AN$8:$AN$42="Y")+('Aug 12'!$AO$8:$AO$42="Y")))+SUMPRODUCT(('Aug 13'!$F$8:$F$42=$T17)*'Aug 13'!$AI$8:$AI$42*(('Aug 13'!$AM$8:$AM$42="Y")+('Aug 13'!$AN$8:$AN$42="Y")+('Aug 13'!$AO$8:$AO$42="Y")))+SUMPRODUCT(('Aug 14'!$F$8:$F$42=$T17)*'Aug 14'!$AI$8:$AI$42*(('Aug 14'!$AM$8:$AM$42="Y")+('Aug 14'!$AN$8:$AN$42="Y")+('Aug 14'!$AO$8:$AO$42="Y")))+SUMPRODUCT(('Aug 15'!$F$8:$F$42=$T17)*'Aug 15'!$AI$8:$AI$42*(('Aug 15'!$AM$8:$AM$42="Y")+('Aug 15'!$AN$8:$AN$42="Y")+('Aug 15'!$AO$8:$AO$42="Y")))+SUMPRODUCT(('Aug 16'!$F$8:$F$42=$T17)*'Aug 16'!$AI$8:$AI$42*(('Aug 16'!$AM$8:$AM$42="Y")+('Aug 16'!$AN$8:$AN$42="Y")+('Aug 16'!$AO$8:$AO$42="Y")))+SUMPRODUCT(('Aug 17'!$F$8:$F$42=$T17)*'Aug 17'!$AI$8:$AI$42*(('Aug 17'!$AM$8:$AM$42="Y")+('Aug 17'!$AN$8:$AN$42="Y")+('Aug 17'!$AO$8:$AO$42="Y")))+SUMPRODUCT(('Aug 18'!$F$8:$F$42=$T17)*'Aug 18'!$AI$8:$AI$42*(('Aug 18'!$AM$8:$AM$42="Y")+('Aug 18'!$AN$8:$AN$42="Y")+('Aug 18'!$AO$8:$AO$42="Y")))+SUMPRODUCT(('Aug 19'!$F$8:$F$42=$T17)*'Aug 19'!$AI$8:$AI$42*(('Aug 19'!$AM$8:$AM$42="Y")+('Aug 19'!$AN$8:$AN$42="Y")+('Aug 19'!$AO$8:$AO$42="Y")))+SUMPRODUCT(('Aug 20'!$F$8:$F$42=$T17)*'Aug 20'!$AI$8:$AI$42*(('Aug 20'!$AM$8:$AM$42="Y")+('Aug 20'!$AN$8:$AN$42="Y")+('Aug 20'!$AO$8:$AO$42="Y")))+SUMPRODUCT(('Aug 21'!$F$8:$F$42=$T17)*'Aug 21'!$AI$8:$AI$42*(('Aug 21'!$AM$8:$AM$42="Y")+('Aug 21'!$AN$8:$AN$42="Y")+('Aug 21'!$AO$8:$AO$42="Y")))+SUMPRODUCT(('Aug 22'!$F$8:$F$42=$T17)*'Aug 22'!$AI$8:$AI$42*(('Aug 22'!$AM$8:$AM$42="Y")+('Aug 22'!$AN$8:$AN$42="Y")+('Aug 22'!$AO$8:$AO$42="Y")))+SUMPRODUCT(('Aug 23'!$F$8:$F$42=$T17)*'Aug 23'!$AI$8:$AI$42*(('Aug 23'!$AM$8:$AM$42="Y")+('Aug 23'!$AN$8:$AN$42="Y")+('Aug 23'!$AO$8:$AO$42="Y")))+SUMPRODUCT(('Aug 24'!$F$8:$F$42=$T17)*'Aug 24'!$AI$8:$AI$42*(('Aug 24'!$AM$8:$AM$42="Y")+('Aug 24'!$AN$8:$AN$42="Y")+('Aug 24'!$AO$8:$AO$42="Y")))+SUMPRODUCT(('Aug 25'!$F$8:$F$42=$T17)*'Aug 25'!$AI$8:$AI$42*(('Aug 25'!$AM$8:$AM$42="Y")+('Aug 25'!$AN$8:$AN$42="Y")+('Aug 25'!$AO$8:$AO$42="Y")))+SUMPRODUCT(('Aug 26'!$F$8:$F$42=$T17)*'Aug 26'!$AI$8:$AI$42*(('Aug 26'!$AM$8:$AM$42="Y")+('Aug 26'!$AN$8:$AN$42="Y")+('Aug 26'!$AO$8:$AO$42="Y")))+SUMPRODUCT(('Aug 27'!$F$8:$F$42=$T17)*'Aug 27'!$AI$8:$AI$42*(('Aug 27'!$AM$8:$AM$42="Y")+('Aug 27'!$AN$8:$AN$42="Y")+('Aug 27'!$AO$8:$AO$42="Y")))+SUMPRODUCT(('Aug 28'!$F$8:$F$42=$T17)*'Aug 28'!$AI$8:$AI$42*(('Aug 28'!$AM$8:$AM$42="Y")+('Aug 28'!$AN$8:$AN$42="Y")+('Aug 28'!$AO$8:$AO$42="Y")))+SUMPRODUCT(('Aug 29'!$F$8:$F$42=$T17)*'Aug 29'!$AI$8:$AI$42*(('Aug 29'!$AM$8:$AM$42="Y")+('Aug 29'!$AN$8:$AN$42="Y")+('Aug 29'!$AO$8:$AO$42="Y")))+SUMPRODUCT(('Aug 30'!$F$8:$F$42=$T17)*'Aug 30'!$AI$8:$AI$42*(('Aug 30'!$AM$8:$AM$42="Y")+('Aug 30'!$AN$8:$AN$42="Y")+('Aug 30'!$AO$8:$AO$42="Y")))+SUMPRODUCT(('Aug 31'!$F$8:$F$42=$T17)*'Aug 31'!$AI$8:$AI$42*(('Aug 31'!$AM$8:$AM$42="Y")+('Aug 31'!$AN$8:$AN$42="Y")+('Aug 31'!$AO$8:$AO$42="Y"))) -> 0 | BD17: =SUM(U17:AY17) -> 0 | BE17: =SUM(U36:AY36) -> 0 | BF17: =SUM(U55:AY55) -> 0
A18: 12 | B18: =$T15 -> JACOB LICHTENSTRAHL | C18: =BD15 -> 0 | D18: =BE15 -> 0 | E18: =IF(BD15=0,"—",BE15/BD15) -> — | F18: =IF(BD15=0,"—",INDEX('Pay Plan'!$B$6:$B$12,BB15)) -> — | G18: =BF15 -> 0 | H18: =LOOKUP(BD15,'Pay Plan'!$B$15:$B$20,'Pay Plan'!$C$15:$C$20) -> 0 | I18: =LOOKUP(BA15,'Pay Plan'!$E$15:$E$19,'Pay Plan'!$F$15:$F$19) -> 0 | J18: =BC15*'Pay Plan'!$I$15 -> 0 | K18: =G18+H18+I18+J18 -> 0 | O18: =K18-N18 -> 0 | T18: ='Staff & Lists'!A19 -> TIM CAMPBELL | U18: =SUMPRODUCT(('Aug 1'!$F$8:$F$42=$T18)*'Aug 1'!$AJ$8:$AJ$42+('Aug 1'!$G$8:$G$42=$T18)*'Aug 1'!$AK$8:$AK$42) -> 0 | V18: =SUMPRODUCT(('Aug 2'!$F$8:$F$42=$T18)*'Aug 2'!$AJ$8:$AJ$42+('Aug 2'!$G$8:$G$42=$T18)*'Aug 2'!$AK$8:$AK$42) -> 0 | W18: =SUMPRODUCT(('Aug 3'!$F$8:$F$42=$T18)*'Aug 3'!$AJ$8:$AJ$42+('Aug 3'!$G$8:$G$42=$T18)*'Aug 3'!$AK$8:$AK$42) -> 0 | X18: =SUMPRODUCT(('Aug 4'!$F$8:$F$42=$T18)*'Aug 4'!$AJ$8:$AJ$42+('Aug 4'!$G$8:$G$42=$T18)*'Aug 4'!$AK$8:$AK$42) -> 0 | Y18: =SUMPRODUCT(('Aug 5'!$F$8:$F$42=$T18)*'Aug 5'!$AJ$8:$AJ$42+('Aug 5'!$G$8:$G$42=$T18)*'Aug 5'!$AK$8:$AK$42) -> 0 | Z18: =SUMPRODUCT(('Aug 6'!$F$8:$F$42=$T18)*'Aug 6'!$AJ$8:$AJ$42+('Aug 6'!$G$8:$G$42=$T18)*'Aug 6'!$AK$8:$AK$42) -> 0 | AA18: =SUMPRODUCT(('Aug 7'!$F$8:$F$42=$T18)*'Aug 7'!$AJ$8:$AJ$42+('Aug 7'!$G$8:$G$42=$T18)*'Aug 7'!$AK$8:$AK$42) -> 0 | AB18: =SUMPRODUCT(('Aug 8'!$F$8:$F$42=$T18)*'Aug 8'!$AJ$8:$AJ$42+('Aug 8'!$G$8:$G$42=$T18)*'Aug 8'!$AK$8:$AK$42) -> 0 | AC18: =SUMPRODUCT(('Aug 9'!$F$8:$F$42=$T18)*'Aug 9'!$AJ$8:$AJ$42+('Aug 9'!$G$8:$G$42=$T18)*'Aug 9'!$AK$8:$AK$42) -> 0 | AD18: =SUMPRODUCT(('Aug 10'!$F$8:$F$42=$T18)*'Aug 10'!$AJ$8:$AJ$42+('Aug 10'!$G$8:$G$42=$T18)*'Aug 10'!$AK$8:$AK$42) -> 0 | AE18: =SUMPRODUCT(('Aug 11'!$F$8:$F$42=$T18)*'Aug 11'!$AJ$8:$AJ$42+('Aug 11'!$G$8:$G$42=$T18)*'Aug 11'!$AK$8:$AK$42) -> 0 | AF18: =SUMPRODUCT(('Aug 12'!$F$8:$F$42=$T18)*'Aug 12'!$AJ$8:$AJ$42+('Aug 12'!$G$8:$G$42=$T18)*'Aug 12'!$AK$8:$AK$42) -> 0 | AG18: =SUMPRODUCT(('Aug 13'!$F$8:$F$42=$T18)*'Aug 13'!$AJ$8:$AJ$42+('Aug 13'!$G$8:$G$42=$T18)*'Aug 13'!$AK$8:$AK$42) -> 0 | AH18: =SUMPRODUCT(('Aug 14'!$F$8:$F$42=$T18)*'Aug 14'!$AJ$8:$AJ$42+('Aug 14'!$G$8:$G$42=$T18)*'Aug 14'!$AK$8:$AK$42) -> 0 | AI18: =SUMPRODUCT(('Aug 15'!$F$8:$F$42=$T18)*'Aug 15'!$AJ$8:$AJ$42+('Aug 15'!$G$8:$G$42=$T18)*'Aug 15'!$AK$8:$AK$42) -> 0 | AJ18: =SUMPRODUCT(('Aug 16'!$F$8:$F$42=$T18)*'Aug 16'!$AJ$8:$AJ$42+('Aug 16'!$G$8:$G$42=$T18)*'Aug 16'!$AK$8:$AK$42) -> 0 | AK18: =SUMPRODUCT(('Aug 17'!$F$8:$F$42=$T18)*'Aug 17'!$AJ$8:$AJ$42+('Aug 17'!$G$8:$G$42=$T18)*'Aug 17'!$AK$8:$AK$42) -> 0 | AL18: =SUMPRODUCT(('Aug 18'!$F$8:$F$42=$T18)*'Aug 18'!$AJ$8:$AJ$42+('Aug 18'!$G$8:$G$42=$T18)*'Aug 18'!$AK$8:$AK$42) -> 0 | AM18: =SUMPRODUCT(('Aug 19'!$F$8:$F$42=$T18)*'Aug 19'!$AJ$8:$AJ$42+('Aug 19'!$G$8:$G$42=$T18)*'Aug 19'!$AK$8:$AK$42) -> 0 | AN18: =SUMPRODUCT(('Aug 20'!$F$8:$F$42=$T18)*'Aug 20'!$AJ$8:$AJ$42+('Aug 20'!$G$8:$G$42=$T18)*'Aug 20'!$AK$8:$AK$42) -> 0 | AO18: =SUMPRODUCT(('Aug 21'!$F$8:$F$42=$T18)*'Aug 21'!$AJ$8:$AJ$42+('Aug 21'!$G$8:$G$42=$T18)*'Aug 21'!$AK$8:$AK$42) -> 0 | AP18: =SUMPRODUCT(('Aug 22'!$F$8:$F$42=$T18)*'Aug 22'!$AJ$8:$AJ$42+('Aug 22'!$G$8:$G$42=$T18)*'Aug 22'!$AK$8:$AK$42) -> 0 | AQ18: =SUMPRODUCT(('Aug 23'!$F$8:$F$42=$T18)*'Aug 23'!$AJ$8:$AJ$42+('Aug 23'!$G$8:$G$42=$T18)*'Aug 23'!$AK$8:$AK$42) -> 0 | AR18: =SUMPRODUCT(('Aug 24'!$F$8:$F$42=$T18)*'Aug 24'!$AJ$8:$AJ$42+('Aug 24'!$G$8:$G$42=$T18)*'Aug 24'!$AK$8:$AK$42) -> 0 | AS18: =SUMPRODUCT(('Aug 25'!$F$8:$F$42=$T18)*'Aug 25'!$AJ$8:$AJ$42+('Aug 25'!$G$8:$G$42=$T18)*'Aug 25'!$AK$8:$AK$42) -> 0 | AT18: =SUMPRODUCT(('Aug 26'!$F$8:$F$42=$T18)*'Aug 26'!$AJ$8:$AJ$42+('Aug 26'!$G$8:$G$42=$T18)*'Aug 26'!$AK$8:$AK$42) -> 0 | AU18: =SUMPRODUCT(('Aug 27'!$F$8:$F$42=$T18)*'Aug 27'!$AJ$8:$AJ$42+('Aug 27'!$G$8:$G$42=$T18)*'Aug 27'!$AK$8:$AK$42) -> 0 | AV18: =SUMPRODUCT(('Aug 28'!$F$8:$F$42=$T18)*'Aug 28'!$AJ$8:$AJ$42+('Aug 28'!$G$8:$G$42=$T18)*'Aug 28'!$AK$8:$AK$42) -> 0 | AW18: =SUMPRODUCT(('Aug 29'!$F$8:$F$42=$T18)*'Aug 29'!$AJ$8:$AJ$42+('Aug 29'!$G$8:$G$42=$T18)*'Aug 29'!$AK$8:$AK$42) -> 0 | AX18: =SUMPRODUCT(('Aug 30'!$F$8:$F$42=$T18)*'Aug 30'!$AJ$8:$AJ$42+('Aug 30'!$G$8:$G$42=$T18)*'Aug 30'!$AK$8:$AK$42) -> 0 | AY18: =SUMPRODUCT(('Aug 31'!$F$8:$F$42=$T18)*'Aug 31'!$AJ$8:$AJ$42+('Aug 31'!$G$8:$G$42=$T18)*'Aug 31'!$AK$8:$AK$42) -> 0 | BA18: =SUM(U18:AD18) -> 0 | BB18: =MATCH(BD18,'Pay Plan'!$C$6:$C$12,1) -> 1 | BC18: =SUMPRODUCT(('Aug 1'!$F$8:$F$42=$T18)*'Aug 1'!$AI$8:$AI$42*(('Aug 1'!$AM$8:$AM$42="Y")+('Aug 1'!$AN$8:$AN$42="Y")+('Aug 1'!$AO$8:$AO$42="Y")))+SUMPRODUCT(('Aug 2'!$F$8:$F$42=$T18)*'Aug 2'!$AI$8:$AI$42*(('Aug 2'!$AM$8:$AM$42="Y")+('Aug 2'!$AN$8:$AN$42="Y")+('Aug 2'!$AO$8:$AO$42="Y")))+SUMPRODUCT(('Aug 3'!$F$8:$F$42=$T18)*'Aug 3'!$AI$8:$AI$42*(('Aug 3'!$AM$8:$AM$42="Y")+('Aug 3'!$AN$8:$AN$42="Y")+('Aug 3'!$AO$8:$AO$42="Y")))+SUMPRODUCT(('Aug 4'!$F$8:$F$42=$T18)*'Aug 4'!$AI$8:$AI$42*(('Aug 4'!$AM$8:$AM$42="Y")+('Aug 4'!$AN$8:$AN$42="Y")+('Aug 4'!$AO$8:$AO$42="Y")))+SUMPRODUCT(('Aug 5'!$F$8:$F$42=$T18)*'Aug 5'!$AI$8:$AI$42*(('Aug 5'!$AM$8:$AM$42="Y")+('Aug 5'!$AN$8:$AN$42="Y")+('Aug 5'!$AO$8:$AO$42="Y")))+SUMPRODUCT(('Aug 6'!$F$8:$F$42=$T18)*'Aug 6'!$AI$8:$AI$42*(('Aug 6'!$AM$8:$AM$42="Y")+('Aug 6'!$AN$8:$AN$42="Y")+('Aug 6'!$AO$8:$AO$42="Y")))+SUMPRODUCT(('Aug 7'!$F$8:$F$42=$T18)*'Aug 7'!$AI$8:$AI$42*(('Aug 7'!$AM$8:$AM$42="Y")+('Aug 7'!$AN$8:$AN$42="Y")+('Aug 7'!$AO$8:$AO$42="Y")))+SUMPRODUCT(('Aug 8'!$F$8:$F$42=$T18)*'Aug 8'!$AI$8:$AI$42*(('Aug 8'!$AM$8:$AM$42="Y")+('Aug 8'!$AN$8:$AN$42="Y")+('Aug 8'!$AO$8:$AO$42="Y")))+SUMPRODUCT(('Aug 9'!$F$8:$F$42=$T18)*'Aug 9'!$AI$8:$AI$42*(('Aug 9'!$AM$8:$AM$42="Y")+('Aug 9'!$AN$8:$AN$42="Y")+('Aug 9'!$AO$8:$AO$42="Y")))+SUMPRODUCT(('Aug 10'!$F$8:$F$42=$T18)*'Aug 10'!$AI$8:$AI$42*(('Aug 10'!$AM$8:$AM$42="Y")+('Aug 10'!$AN$8:$AN$42="Y")+('Aug 10'!$AO$8:$AO$42="Y")))+SUMPRODUCT(('Aug 11'!$F$8:$F$42=$T18)*'Aug 11'!$AI$8:$AI$42*(('Aug 11'!$AM$8:$AM$42="Y")+('Aug 11'!$AN$8:$AN$42="Y")+('Aug 11'!$AO$8:$AO$42="Y")))+SUMPRODUCT(('Aug 12'!$F$8:$F$42=$T18)*'Aug 12'!$AI$8:$AI$42*(('Aug 12'!$AM$8:$AM$42="Y")+('Aug 12'!$AN$8:$AN$42="Y")+('Aug 12'!$AO$8:$AO$42="Y")))+SUMPRODUCT(('Aug 13'!$F$8:$F$42=$T18)*'Aug 13'!$AI$8:$AI$42*(('Aug 13'!$AM$8:$AM$42="Y")+('Aug 13'!$AN$8:$AN$42="Y")+('Aug 13'!$AO$8:$AO$42="Y")))+SUMPRODUCT(('Aug 14'!$F$8:$F$42=$T18)*'Aug 14'!$AI$8:$AI$42*(('Aug 14'!$AM$8:$AM$42="Y")+('Aug 14'!$AN$8:$AN$42="Y")+('Aug 14'!$AO$8:$AO$42="Y")))+SUMPRODUCT(('Aug 15'!$F$8:$F$42=$T18)*'Aug 15'!$AI$8:$AI$42*(('Aug 15'!$AM$8:$AM$42="Y")+('Aug 15'!$AN$8:$AN$42="Y")+('Aug 15'!$AO$8:$AO$42="Y")))+SUMPRODUCT(('Aug 16'!$F$8:$F$42=$T18)*'Aug 16'!$AI$8:$AI$42*(('Aug 16'!$AM$8:$AM$42="Y")+('Aug 16'!$AN$8:$AN$42="Y")+('Aug 16'!$AO$8:$AO$42="Y")))+SUMPRODUCT(('Aug 17'!$F$8:$F$42=$T18)*'Aug 17'!$AI$8:$AI$42*(('Aug 17'!$AM$8:$AM$42="Y")+('Aug 17'!$AN$8:$AN$42="Y")+('Aug 17'!$AO$8:$AO$42="Y")))+SUMPRODUCT(('Aug 18'!$F$8:$F$42=$T18)*'Aug 18'!$AI$8:$AI$42*(('Aug 18'!$AM$8:$AM$42="Y")+('Aug 18'!$AN$8:$AN$42="Y")+('Aug 18'!$AO$8:$AO$42="Y")))+SUMPRODUCT(('Aug 19'!$F$8:$F$42=$T18)*'Aug 19'!$AI$8:$AI$42*(('Aug 19'!$AM$8:$AM$42="Y")+('Aug 19'!$AN$8:$AN$42="Y")+('Aug 19'!$AO$8:$AO$42="Y")))+SUMPRODUCT(('Aug 20'!$F$8:$F$42=$T18)*'Aug 20'!$AI$8:$AI$42*(('Aug 20'!$AM$8:$AM$42="Y")+('Aug 20'!$AN$8:$AN$42="Y")+('Aug 20'!$AO$8:$AO$42="Y")))+SUMPRODUCT(('Aug 21'!$F$8:$F$42=$T18)*'Aug 21'!$AI$8:$AI$42*(('Aug 21'!$AM$8:$AM$42="Y")+('Aug 21'!$AN$8:$AN$42="Y")+('Aug 21'!$AO$8:$AO$42="Y")))+SUMPRODUCT(('Aug 22'!$F$8:$F$42=$T18)*'Aug 22'!$AI$8:$AI$42*(('Aug 22'!$AM$8:$AM$42="Y")+('Aug 22'!$AN$8:$AN$42="Y")+('Aug 22'!$AO$8:$AO$42="Y")))+SUMPRODUCT(('Aug 23'!$F$8:$F$42=$T18)*'Aug 23'!$AI$8:$AI$42*(('Aug 23'!$AM$8:$AM$42="Y")+('Aug 23'!$AN$8:$AN$42="Y")+('Aug 23'!$AO$8:$AO$42="Y")))+SUMPRODUCT(('Aug 24'!$F$8:$F$42=$T18)*'Aug 24'!$AI$8:$AI$42*(('Aug 24'!$AM$8:$AM$42="Y")+('Aug 24'!$AN$8:$AN$42="Y")+('Aug 24'!$AO$8:$AO$42="Y")))+SUMPRODUCT(('Aug 25'!$F$8:$F$42=$T18)*'Aug 25'!$AI$8:$AI$42*(('Aug 25'!$AM$8:$AM$42="Y")+('Aug 25'!$AN$8:$AN$42="Y")+('Aug 25'!$AO$8:$AO$42="Y")))+SUMPRODUCT(('Aug 26'!$F$8:$F$42=$T18)*'Aug 26'!$AI$8:$AI$42*(('Aug 26'!$AM$8:$AM$42="Y")+('Aug 26'!$AN$8:$AN$42="Y")+('Aug 26'!$AO$8:$AO$42="Y")))+SUMPRODUCT(('Aug 27'!$F$8:$F$42=$T18)*'Aug 27'!$AI$8:$AI$42*(('Aug 27'!$AM$8:$AM$42="Y")+('Aug 27'!$AN$8:$AN$42="Y")+('Aug 27'!$AO$8:$AO$42="Y")))+SUMPRODUCT(('Aug 28'!$F$8:$F$42=$T18)*'Aug 28'!$AI$8:$AI$42*(('Aug 28'!$AM$8:$AM$42="Y")+('Aug 28'!$AN$8:$AN$42="Y")+('Aug 28'!$AO$8:$AO$42="Y")))+SUMPRODUCT(('Aug 29'!$F$8:$F$42=$T18)*'Aug 29'!$AI$8:$AI$42*(('Aug 29'!$AM$8:$AM$42="Y")+('Aug 29'!$AN$8:$AN$42="Y")+('Aug 29'!$AO$8:$AO$42="Y")))+SUMPRODUCT(('Aug 30'!$F$8:$F$42=$T18)*'Aug 30'!$AI$8:$AI$42*(('Aug 30'!$AM$8:$AM$42="Y")+('Aug 30'!$AN$8:$AN$42="Y")+('Aug 30'!$AO$8:$AO$42="Y")))+SUMPRODUCT(('Aug 31'!$F$8:$F$42=$T18)*'Aug 31'!$AI$8:$AI$42*(('Aug 31'!$AM$8:$AM$42="Y")+('Aug 31'!$AN$8:$AN$42="Y")+('Aug 31'!$AO$8:$AO$42="Y"))) -> 0 | BD18: =SUM(U18:AY18) -> 0 | BE18: =SUM(U37:AY37) -> 0 | BF18: =SUM(U56:AY56) -> 0
